Workbook

Sheet Data
A1: CC NO | B1: OMC | C1: NAME OF THE RO | D1: LOCATION | E1: DISTT | F1: Trading Area for Dealers | G1: Trading Area | H1: Bigger Trading Area | I1: SO Name | J1: MS0424 | K1: MS-0425 | L1: HSD-0424 | M1: HSD-0425 | N1: MS-0524 | O1: MS-0525 | P1: HSD-0524 | Q1: HSD-0525 | R1: MS-0625 | S1: MS-0624 | T1: HSD-0624 | U1: HSD-0625 | V1: MS-0725 | W1: MS-0724 | X1: HSD-0725 | Y1: HSD-0724 | Z1: MS-0825 | AA1: MS-0824 | AB1: HSD-0825 | AC1: HSD-0824 | AD1: MS-0925 | AE1: MS-0924 | AF1: HSD-0925 | AG1: HSD-0924 | AH1: MS-1025 | AI1: MS-1024 | AJ1: HSD-1025 | AK1: HSD-1024 | AL1: MS-1125 | AM1: MS-1124 | AN1: HSD-1125 | AO1: HSD-1124 | AP1: MS-1225 | AQ1: MS-1224 | AR1: HSD-1225 | AS1: HSD-1224 | AT1: MS-0126 | AU1: MS-0125 | AV1: HSD-0126 | AW1: HSD-0125 | AX1: MS-0226 | AY1: MS-0225 | AZ1: HSD-0226 | BA1: HSD-0225 | BB1: MS-0326 | BC1: MS-0325 | BD1: HSD-0326 | BE1: HSD-0325 | BF1: Lattitude | BG1: Longitude | BH1: MS TM TY | BI1: MS TM LY | BJ1: Gain in KL MS TM | BK1: %Gain MS TM | BL1: HSD TMTY | BM1: HSDTMLY | BN1: Gain in KL HSD TM | BO1: %Gain HSD TM | BP1: MSTY | BQ1: MSLY | BR1: Gain in KL MS TY | BS1: %Gain MS TY | BT1: HSDTY | BU1: HSDLY | BV1: Gain in KL HSD TY | BW1: %Gain HSD TY | BX1: Speed TM | BY1: Speed Conversion % TM | BZ1: Speed TY | CA1: Speed Conversion TY | CB1: MS MS TMTY | CC1: MS MS TMLY | CD1: Change in Market Share MS | CE1: HSD MS TMTY | CF1: HSD MS TMLY | CG1: Change in Market Share HSD TM | CH1: MS MS TY | CI1: MS MS LY | CJ1: Change in Market Share MS TY | CK1: HSD MS TY | CL1: HSD MS LY | CM1: Change in Market Share HSD TY | CN1: Effectivity MS Ty | CO1: Effectivity HSD TY | CP1: Growth Feb Vs March | CQ1: reasons
A2: 129151 | B2: BPC | C2: ALLIED MOTORS LTD. | D2: PREET VIHAR DELHI | E2: EAST DELHI | F2: ALLIED_MASIH | G2: ALLIED_MASIH | H2: Mayur Vihar -Anand Vihar -Preet Vihar | I2: Bhanu Pratap | J2: 1004 | K2: 1096 | L2: 186 | M2: 172 | N2: 1057.5 | O2: 1175 | P2: 208.5 | Q2: 175 | R2: 1088 | S2: 1042 | T2: 190 | U2: 186 | V2: 1203 | W2: 1042 | X2: 169 | Y2: 200 | Z2: 1200 | AA2: 1042.5 | AB2: 180 | AC2: 201.5 | AD2: 1157 | AE2: 1092 | AF2: 165 | AG2: 180 | AH2: 1196 | AI2: 1012.5 | AJ2: 168 | AK2: 175.5 | AL2: 1142 | AM2: 1020.5 | AN2: 150 | AO2: 161.5 | AP2: 1100 | AQ2: 990 | AR2: 140 | AS2: 140 | AT2: 1072 | AU2: 963.5 | AV2: 140 | AW2: 164.5 | AX2: 1028 | AY2: 931 | AZ2: 150 | BA2: 163 | BB2: 1197 | BC2: 1008 | BD2: 175 | BE2: 172 | BF2: 28.63971 | BG2: 77.29353 | BH2: =BB2 -> 1197 | BI2: =BC2 -> 1008 | BJ2: =(BH2-BI2) -> 189 | BK2: =(BJ2)/BI2*100 -> 18.75 | BL2: =BD2 -> 175 | BM2: =BE2 -> 172 | BN2: =(BL2-BM2) -> 3 | BO2: =(BN2)/BM2*100 -> 1.744186 | BP2: =K2+O2+R2+V2+Z2+AD2+AH2+AL2+AP2+AT2+AX2+BB2 -> 13654 | BQ2: =J2+N2+S2+W2+AA2+AE2+AI2+AM2+AQ2+AU2+Table1[[#This Row],[MS-0225]]+Table1[[#This Row],[MS-0325]] -> 12205.5 | BR2: =(BP2-BQ2) -> 1448.4999 | BS2: =(BR2)/BQ2*100 -> 11.8676 | BT2: =M2+Q2+T2+X2+AB2+AF2+AJ2+AN2+AR2+AV2+AZ2+BD2 -> 1974 | BU2: =L2+P2+U2+Y2+AC2+AG2+AK2+AO2+AS2+AW2+BA2+BE2 -> 2138.5 | BV2: =(BT2-BU2) -> -164.5 | BW2: =(BV2)/BU2*100 -> -7.6923077 | BX2: 180 | BY2: =BX2/BH2 -> 0.15037594 | BZ2: 1197 | CA2: =BZ2/BP2 -> 0.087666618 | CB2: =BH2/SUMIFS(BH$2:BH$398,G$2:G$398,G2) -> 0.2898656 | CC2: =BI2/SUMIFS(BI$2:BI$398,G$2:G$398,G2) -> 0.26561265 | CD2: =CB2-CC2 -> 0.024252953 | CE2: =BL2/SUMIFS(BL$2:BL$398,G$2:G$398,G2) -> 0.2745098 | CF2: =BM2/SUMIFS(BM$2:BM$398,G$2:G$398,G2) -> 0.25671642 | CG2: =CE2-CF2 -> 0.017793386 | CH2: =BP2/SUMIFS(BP$2:BP$398,G$2:G$398,G2) -> 0.27816037 | CI2: =BQ2/SUMIFS(BQ$2:BQ$398,G$2:G$398,G2) -> 0.26668488 | CJ2: =CH2-CI2 -> 0.011475495 | CK2: =BT2/SUMIFS(BT$2:BT$398,G$2:G$398,G2) -> 0.25436676 | CL2: =BU2/SUMIFS(BU$2:BU$398,G$2:G$398,G2) -> 0.25288539 | CM2: =CK2-CL2 -> 0.0014813736 | CN2: =COUNTIFS(G$2:G$398,G2)*CH2 -> 2.225283 | CO2: =COUNTIFS(G$2:G$398,G2)*CK2 -> 2.0349341
A3: 41030786 | B3: HPC | C3: R D MOTORS | D3: JASOLA | E3: SOUTH EAST DELHI | F3: AUTO REST_OKHLA | G3: AUTO REST_OKHLA | H3: Okhla | I3: Bhanu Pratap | J3: 950 | K3: 974 | L3: 335 | M3: 302 | N3: 1008.5 | O3: 1050.5 | P3: 359.5 | Q3: 329.5 | R3: 1032 | S3: 1007.5 | T3: 307 | U3: 363.5 | V3: 1059.5 | W3: 1027.5 | X3: 309.5 | Y3: 343.5 | Z3: 1082.5 | AA3: 1052 | AB3: 282.5 | AC3: 377 | AD3: 996 | AE3: 1024 | AF3: 283 | AG3: 344 | AH3: 1025 | AI3: 1050 | AJ3: 305 | AK3: 380 | AL3: 1033 | AM3: 937 | AN3: 300 | AO3: 293 | AP3: 969 | AQ3: 932.5 | AR3: 283 | AS3: 288.5 | AT3: 932 | AU3: 885 | AV3: 307 | AW3: 330 | AX3: 969.5 | AY3: 925.5 | AZ3: 303.5 | BA3: 329.5 | BB3: 1091 | BC3: 973 | BD3: 314 | BE3: 315 | BF3: 28.53871 | BG3: 77.29157 | BH3: =BB3 -> 1091 | BI3: =BC3 -> 973 | BJ3: =(BH3-BI3) -> 118 | BK3: =(BJ3)/BI3*100 -> 12.127441 | BL3: =BD3 -> 314 | BM3: =BE3 -> 315 | BN3: =(BL3-BM3) -> -1 | BO3: =(BN3)/BM3*100 -> -0.31746032 | BP3: =K3+O3+R3+V3+Z3+AD3+AH3+AL3+AP3+AT3+AX3+BB3 -> 12214 | BQ3: =J3+N3+S3+W3+AA3+AE3+AI3+AM3+AQ3+AU3+Table1[[#This Row],[MS-0225]]+Table1[[#This Row],[MS-0325]] -> 11772.5 | BR3: =(BP3-BQ3) -> 441.5 | BS3: =(BR3)/BQ3*100 -> 3.7502654 | BT3: =M3+Q3+T3+X3+AB3+AF3+AJ3+AN3+AR3+AV3+AZ3+BD3 -> 3626 | BU3: =L3+P3+U3+Y3+AC3+AG3+AK3+AO3+AS3+AW3+BA3+BE3 -> 4058.5 | BV3: =(BT3-BU3) -> -432.5 | BW3: =(BV3)/BU3*100 -> -10.656647 | BX3: 0 | BY3: =BX3/BH3 -> 0 | BZ3: 0 | CA3: =BZ3/BP3 -> 0 | CB3: =BH3/SUMIFS(BH$2:BH$398,G$2:G$398,G3) -> 0.19818347 | CC3: =BI3/SUMIFS(BI$2:BI$398,G$2:G$398,G3) -> 0.18636277 | CD3: =CB3-CC3 -> 0.011820704 | CE3: =BL3/SUMIFS(BL$2:BL$398,G$2:G$398,G3) -> 0.21820709 | CF3: =BM3/SUMIFS(BM$2:BM$398,G$2:G$398,G3) -> 0.20257235 | CG3: =CE3-CF3 -> 0.015634741 | CH3: =BP3/SUMIFS(BP$2:BP$398,G$2:G$398,G3) -> 0.19019293 | CI3: =BQ3/SUMIFS(BQ$2:BQ$398,G$2:G$398,G3) -> 0.18457257 | CJ3: =CH3-CI3 -> 0.0056203628 | CK3: =BT3/SUMIFS(BT$2:BT$398,G$2:G$398,G3) -> 0.20198307 | CL3: =BU3/SUMIFS(BU$2:BU$398,G$2:G$398,G3) -> 0.1941866 | CM3: =CK3-CL3 -> 0.0077964631 | CN3: =COUNTIFS(G$2:G$398,G3)*CH3 -> 2.0921223 | CO3: =COUNTIFS(G$2:G$398,G3)*CK3 -> 2.2218137
A4: 106330 | B4: IOC | C4: RAJPATH MOTORS | D4: GEETA COLONY, SITE I | E4: EAST DELHI | F4: White Patch_Geeta Colony | G4: White Patch_Geeta Colony | H4: Mayur Vihar -Anand Vihar -Preet Vihar | I4: Bhanu Pratap | J4: 711 | K4: 695.5 | L4: 135 | M4: 120.5 | N4: 728 | O4: 710.5 | P4: 140 | Q4: 103.5 | R4: 646 | S4: 738 | T4: 102 | U4: 126 | V4: 677.5 | W4: 738 | X4: 98.5 | Y4: 126 | Z4: 648 | AA4: 787.5 | AB4: 116 | AC4: 130.5 | AD4: 646 | AE4: 720 | AF4: 92 | AG4: 126 | AH4: 736 | AI4: 821 | AJ4: 98 | AK4: 117 | AL4: 727 | AM4: 717.5 | AN4: 97 | AO4: 112.5 | AP4: 734.5 | AQ4: 688.5 | AR4: 111.5 | AS4: 103.5 | AT4: 788 | AU4: 680 | AV4: 110 | AW4: 118 | AX4: 797.5 | AY4: 638 | AZ4: 128.5 | BA4: 142 | BB4: 959 | BC4: 675 | BD4: 157 | BE4: 99 | BF4: 28.6518 | BG4: 77.2683 | BH4: =BB4 -> 959 | BI4: =BC4 -> 675 | BJ4: =(BH4-BI4) -> 284 | BK4: =(BJ4)/BI4*100 -> 42.074074 | BL4: =BD4 -> 157 | BM4: =BE4 -> 99 | BN4: =(BL4-BM4) -> 58 | BO4: =(BN4)/BM4*100 -> 58.585859 | BP4: =K4+O4+R4+V4+Z4+AD4+AH4+AL4+AP4+AT4+AX4+BB4 -> 8765.5 | BQ4: =J4+N4+S4+W4+AA4+AE4+AI4+AM4+AQ4+AU4+Table1[[#This Row],[MS-0225]]+Table1[[#This Row],[MS-0325]] -> 8642.5 | BR4: =(BP4-BQ4) -> 123 | BS4: =(BR4)/BQ4*100 -> 1.4231993 | BT4: =M4+Q4+T4+X4+AB4+AF4+AJ4+AN4+AR4+AV4+AZ4+BD4 -> 1334.5 | BU4: =L4+P4+U4+Y4+AC4+AG4+AK4+AO4+AS4+AW4+BA4+BE4 -> 1475.5 | BV4: =(BT4-BU4) -> -141 | BW4: =(BV4)/BU4*100 -> -9.5560827 | BX4: 0 | BY4: =BX4/BH4 -> 0 | BZ4: 0 | CA4: =BZ4/BP4 -> 0 | CB4: =BH4/SUMIFS(BH$2:BH$398,G$2:G$398,G4) -> 0.65649004 | CC4: =BI4/SUMIFS(BI$2:BI$398,G$2:G$398,G4) -> 0.58039553 | CD4: =CB4-CC4 -> 0.076094515 | CE4: =BL4/SUMIFS(BL$2:BL$398,G$2:G$398,G4) -> 0.71984338 | CF4: =BM4/SUMIFS(BM$2:BM$398,G$2:G$398,G4) -> 0.64705882 | CG4: =CE4-CF4 -> 0.072784553 | CH4: =BP4/SUMIFS(BP$2:BP$398,G$2:G$398,G4) -> 0.58934363 | CI4: =BQ4/SUMIFS(BQ$2:BQ$398,G$2:G$398,G4) -> 0.60451707 | CJ4: =CH4-CI4 -> -0.015173432 | CK4: =BT4/SUMIFS(BT$2:BT$398,G$2:G$398,G4) -> 0.68991188 | CL4: =BU4/SUMIFS(BU$2:BU$398,G$2:G$398,G4) -> 0.71709585 | CM4: =CK4-CL4 -> -0.027183966 | CN4: =COUNTIFS(G$2:G$398,G4)*CH4 -> 1.1786873 | CO4: =COUNTIFS(G$2:G$398,G4)*CK4 -> 1.3798238
A5: 186841 | B5: IOC | C5: WELCOME MOTORS | D5: SAKET | E5: SOUTH DELHI | F5: White Patch_Saket | G5: White Patch_Saket | H5: Hauj Khas-Saket-Vasant Kunj | I5: Raj Doshi | J5: 877.5 | K5: 886.5 | L5: 166.5 | M5: 157.5 | N5: 962.5 | O5: 954 | P5: 193.5 | Q5: 162 | R5: 874.5 | S5: 953.5 | T5: 139.5 | U5: 184.5 | V5: 958.5 | W5: 1014.5 | X5: 157.5 | Y5: 191.5 | Z5: 962.5 | AA5: 1059.5 | AB5: 161.5 | AC5: 208.5 | AD5: 899.5 | AE5: 889.5 | AF5: 148.5 | AG5: 174.5 | AH5: 908.5 | AI5: 902.5 | AJ5: 139.5 | AK5: 161.5 | AL5: 872.5 | AM5: 822.5 | AN5: 121.5 | AO5: 139.5 | AP5: 847.5 | AQ5: 827 | AR5: 130.5 | AS5: 135 | AT5: 827.5 | AU5: 769 | AV5: 130.5 | AW5: 135 | AX5: 783 | AY5: 743.5 | AZ5: 135 | BA5: 130.5 | BB5: 904 | BC5: 810 | BD5: 126 | BE5: 144 | BF5: 28.5278 | BG5: 77.2156 | BH5: =BB5 -> 904 | BI5: =BC5 -> 810 | BJ5: =(BH5-BI5) -> 94 | BK5: =(BJ5)/BI5*100 -> 11.604938 | BL5: =BD5 -> 126 | BM5: =BE5 -> 144 | BN5: =(BL5-BM5) -> -18 | BO5: =(BN5)/BM5*100 -> -12.5 | BP5: =K5+O5+R5+V5+Z5+AD5+AH5+AL5+AP5+AT5+AX5+BB5 -> 10678.5 | BQ5: =J5+N5+S5+W5+AA5+AE5+AI5+AM5+AQ5+AU5+Table1[[#This Row],[MS-0225]]+Table1[[#This Row],[MS-0325]] -> 10631.5 | BR5: =(BP5-BQ5) -> 47 | BS5: =(BR5)/BQ5*100 -> 0.44208249 | BT5: =M5+Q5+T5+X5+AB5+AF5+AJ5+AN5+AR5+AV5+AZ5+BD5 -> 1709.5 | BU5: =L5+P5+U5+Y5+AC5+AG5+AK5+AO5+AS5+AW5+BA5+BE5 -> 1964.5 | BV5: =(BT5-BU5) -> -255 | BW5: =(BV5)/BU5*100 -> -12.980402 | BX5: 0 | BY5: =BX5/BH5 -> 0 | BZ5: 0 | CA5: =BZ5/BP5 -> 0 | CB5: =BH5/SUMIFS(BH$2:BH$398,G$2:G$398,G5) -> 1 | CC5: =BI5/SUMIFS(BI$2:BI$398,G$2:G$398,G5) -> 1 | CD5: =CB5-CC5 -> 0 | CE5: =BL5/SUMIFS(BL$2:BL$398,G$2:G$398,G5) -> 1 | CF5: =BM5/SUMIFS(BM$2:BM$398,G$2:G$398,G5) -> 1 | CG5: =CE5-CF5 -> 0 | CH5: =BP5/SUMIFS(BP$2:BP$398,G$2:G$398,G5) -> 1 | CI5: =BQ5/SUMIFS(BQ$2:BQ$398,G$2:G$398,G5) -> 1 | CJ5: =CH5-CI5 -> 0 | CK5: =BT5/SUMIFS(BT$2:BT$398,G$2:G$398,G5) -> 1 | CL5: =BU5/SUMIFS(BU$2:BU$398,G$2:G$398,G5) -> 1 | CM5: =CK5-CL5 -> 0 | CN5: =COUNTIFS(G$2:G$398,G5)*CH5 -> 1 | CO5: =COUNTIFS(G$2:G$398,G5)*CK5 -> 1
A6: 112458 | B6: BPC | C6: VAIBHAV FILLING STATION | D6: VIKAS PURI DELHI | E6: WEST DELHI | F6: VAIBHAV-KARTIK-LAXMI | G6: VAIBHAV-KARTIK-LAXMI | H6: Punjabi Bagh | I6: Abhinav | J6: 800 | K6: 840 | L6: 100 | M6: 100 | N6: 860 | O6: 855 | P6: 140 | Q6: 105 | R6: 825 | S6: 835 | T6: 115 | U6: 145 | V6: 890 | W6: 845 | X6: 110 | Y6: 115 | Z6: 925 | AA6: 880 | AB6: 95 | AC6: 120 | AD6: 858 | AE6: 820 | AF6: 100 | AG6: 100 | AH6: 935 | AI6: 910 | AJ6: 105 | AK6: 130 | AL6: 820 | AM6: 790 | AN6: 100 | AO6: 90 | AP6: 840 | AQ6: 800 | AR6: 80 | AS6: 80 | AT6: 775 | AU6: 795 | AV6: 85 | AW6: 105 | AX6: 805 | AY6: 729 | AZ6: 95 | BA6: 85 | BB6: 860 | BC6: 820 | BD6: 100 | BE6: 100 | BF6: 28.63042 | BG6: 77.06826 | BH6: =BB6 -> 860 | BI6: =BC6 -> 820 | BJ6: =(BH6-BI6) -> 40 | BK6: =(BJ6)/BI6*100 -> 4.8780488 | BL6: =BD6 -> 100 | BM6: =BE6 -> 100 | BN6: =(BL6-BM6) -> 0 | BO6: =(BN6)/BM6*100 -> 0 | BP6: =K6+O6+R6+V6+Z6+AD6+AH6+AL6+AP6+AT6+AX6+BB6 -> 10228 | BQ6: =J6+N6+S6+W6+AA6+AE6+AI6+AM6+AQ6+AU6+Table1[[#This Row],[MS-0225]]+Table1[[#This Row],[MS-0325]] -> 9884 | BR6: =(BP6-BQ6) -> 344 | BS6: =(BR6)/BQ6*100 -> 3.4803723 | BT6: =M6+Q6+T6+X6+AB6+AF6+AJ6+AN6+AR6+AV6+AZ6+BD6 -> 1190 | BU6: =L6+P6+U6+Y6+AC6+AG6+AK6+AO6+AS6+AW6+BA6+BE6 -> 1310 | BV6: =(BT6-BU6) -> -120 | BW6: =(BV6)/BU6*100 -> -9.1603053 | BX6: 45 | BY6: =BX6/BH6 -> 0.052325581 | BZ6: 245 | CA6: =BZ6/BP6 -> 0.023953852 | CB6: =BH6/SUMIFS(BH$2:BH$398,G$2:G$398,G6) -> 0.34916768 | CC6: =BI6/SUMIFS(BI$2:BI$398,G$2:G$398,G6) -> 0.34775233 | CD6: =CB6-CC6 -> 0.0014153492 | CE6: =BL6/SUMIFS(BL$2:BL$398,G$2:G$398,G6) -> 0.38834951 | CF6: =BM6/SUMIFS(BM$2:BM$398,G$2:G$398,G6) -> 0.3125 | CG6: =CE6-CF6 -> 0.075849515 | CH6: =BP6/SUMIFS(BP$2:BP$398,G$2:G$398,G6) -> 0.34648283 | CI6: =BQ6/SUMIFS(BQ$2:BQ$398,G$2:G$398,G6) -> 0.34626636 | CJ6: =CH6-CI6 -> 0.00021647829 | CK6: =BT6/SUMIFS(BT$2:BT$398,G$2:G$398,G6) -> 0.34293948 | CL6: =BU6/SUMIFS(BU$2:BU$398,G$2:G$398,G6) -> 0.32639841 | CM6: =CK6-CL6 -> 0.016541076 | CN6: =COUNTIFS(G$2:G$398,G6)*CH6 -> 1.3859313 | CO6: =COUNTIFS(G$2:G$398,G6)*CK6 -> 1.3717579
A7: 112451 | B7: BPC | C7: SHIV SERVICE STATION | D7: DWARKA PURI DELHI | E7: SOUTH WEST DELHI | F7: SHIV SS | G7: SHIV SS | H7: Dwarka | I7: Raj Doshi | J7: 922.50001 | K7: 1015.5 | L7: 121.5 | M7: 130.5 | N7: 1063 | O7: 1008.5 | P7: 171 | Q7: 125.5 | R7: 937 | S7: 931.50001 | T7: 123 | U7: 148.5 | V7: 1008 | W7: 1011 | X7: 110 | Y7: 135 | Z7: 1014 | AA7: 918 | AB7: 122 | AC7: 144 | AD7: 994 | AE7: 984.5 | AF7: 110 | AG7: 121.5 | AH7: 974 | AI7: 957.5 | AJ7: 114 | AK7: 148.5 | AL7: 974 | AM7: 966.00001 | AN7: 106 | AO7: 108 | AP7: 960 | AQ7: 951 | AR7: 94 | AS7: 105 | AT7: 906 | AU7: 913 | AV7: 100 | AW7: 109 | AX7: 834 | AY7: 915.5 | AZ7: 102 | BA7: 126.5 | BB7: 853 | BC7: 928 | BD7: 87 | BE7: 126 | BF7: 28.59386 | BG7: 77.07785 | BH7: =BB7 -> 853 | BI7: =BC7 -> 928 | BJ7: =(BH7-BI7) -> -75 | BK7: =(BJ7)/BI7*100 -> -8.0818966 | BL7: =BD7 -> 87 | BM7: =BE7 -> 126 | BN7: =(BL7-BM7) -> -39 | BO7: =(BN7)/BM7*100 -> -30.952381 | BP7: =K7+O7+R7+V7+Z7+AD7+AH7+AL7+AP7+AT7+AX7+BB7 -> 11478 | BQ7: =J7+N7+S7+W7+AA7+AE7+AI7+AM7+AQ7+AU7+Table1[[#This Row],[MS-0225]]+Table1[[#This Row],[MS-0325]] -> 11461.5 | BR7: =(BP7-BQ7) -> 16.499972 | BS7: =(BR7)/BQ7*100 -> 0.14395997 | BT7: =M7+Q7+T7+X7+AB7+AF7+AJ7+AN7+AR7+AV7+AZ7+BD7 -> 1324 | BU7: =L7+P7+U7+Y7+AC7+AG7+AK7+AO7+AS7+AW7+BA7+BE7 -> 1564.5 | BV7: =(BT7-BU7) -> -240.5 | BW7: =(BV7)/BU7*100 -> -15.372323 | BX7: 60 | BY7: =BX7/BH7 -> 0.070339977 | BZ7: 279 | CA7: =BZ7/BP7 -> 0.024307371 | CB7: =BH7/SUMIFS(BH$2:BH$398,G$2:G$398,G7) -> 0.2233569 | CC7: =BI7/SUMIFS(BI$2:BI$398,G$2:G$398,G7) -> 0.25621204 | CD7: =CB7-CC7 -> -0.032855138 | CE7: =BL7/SUMIFS(BL$2:BL$398,G$2:G$398,G7) -> 0.16201117 | CF7: =BM7/SUMIFS(BM$2:BM$398,G$2:G$398,G7) -> 0.22105263 | CG7: =CE7-CF7 -> -0.059041458 | CH7: =BP7/SUMIFS(BP$2:BP$398,G$2:G$398,G7) -> 0.25405609 | CI7: =BQ7/SUMIFS(BQ$2:BQ$398,G$2:G$398,G7) -> 0.26239698 | CJ7: =CH7-CI7 -> -0.0083408905 | CK7: =BT7/SUMIFS(BT$2:BT$398,G$2:G$398,G7) -> 0.20652004 | CL7: =BU7/SUMIFS(BU$2:BU$398,G$2:G$398,G7) -> 0.22134975 | CM7: =CK7-CL7 -> -0.014829702 | CN7: =COUNTIFS(G$2:G$398,G7)*CH7 -> 1.7783926 | CO7: =COUNTIFS(G$2:G$398,G7)*CK7 -> 1.4456403
A8: 231764 | B8: IOC | C8: UNITED FUEL STATION | D8: PITAMPURA | E8: NORTH WEST DELHI | F8: White Patch- Inner Ring Road | G8: White Patch- Inner Ring Road | H8: Inner Ring Road | I8: Abhinav | J8: 164 | K8: 216 | L8: 196 | M8: 108 | N8: 189 | O8: 220 | P8: 201 | Q8: 128 | R8: 216 | S8: 204 | T8: 132 | U8: 180 | V8: 227 | W8: 201 | X8: 195 | Y8: 153 | Z8: 224 | AA8: 200 | AB8: 226 | AC8: 124 | AD8: 198.5 | AE8: 176 | AF8: 191.5 | AG8: 112 | AH8: 212 | AI8: 179 | AJ8: 212 | AK8: 151 | AL8: 197 | AM8: 192 | AN8: 195 | AO8: 96 | AP8: 194 | AQ8: 204 | AR8: 198 | AS8: 84 | AT8: 195 | AU8: 194 | AV8: 169 | AW8: 110 | AX8: 182 | AY8: 178 | AZ8: 182 | BA8: 118 | BB8: 188 | BC8: 204 | BD8: 218 | BE8: 120 | BF8: 28.6966 | BG8: 77.1554 | BH8: =BB8 -> 188 | BI8: =BC8 -> 204 | BJ8: =(BH8-BI8) -> -16 | BK8: =(BJ8)/BI8*100 -> -7.8431373 | BL8: =BD8 -> 218 | BM8: =BE8 -> 120 | BN8: =(BL8-BM8) -> 98 | BO8: =(BN8)/BM8*100 -> 81.666667 | BP8: =K8+O8+R8+V8+Z8+AD8+AH8+AL8+AP8+AT8+AX8+BB8 -> 2469.5 | BQ8: =J8+N8+S8+W8+AA8+AE8+AI8+AM8+AQ8+AU8+Table1[[#This Row],[MS-0225]]+Table1[[#This Row],[MS-0325]] -> 2285 | BR8: =(BP8-BQ8) -> 184.5 | BS8: =(BR8)/BQ8*100 -> 8.0743982 | BT8: =M8+Q8+T8+X8+AB8+AF8+AJ8+AN8+AR8+AV8+AZ8+BD8 -> 2154.5 | BU8: =L8+P8+U8+Y8+AC8+AG8+AK8+AO8+AS8+AW8+BA8+BE8 -> 1645 | BV8: =(BT8-BU8) -> 509.5 | BW8: =(BV8)/BU8*100 -> 30.972644 | BX8: 0 | BY8: =BX8/BH8 -> 0 | BZ8: 0 | CA8: =BZ8/BP8 -> 0 | CB8: =BH8/SUMIFS(BH$2:BH$398,G$2:G$398,G8) -> 0.077589765 | CC8: =BI8/SUMIFS(BI$2:BI$398,G$2:G$398,G8) -> 0.084384695 | CD8: =CB8-CC8 -> -0.0067949302 | CE8: =BL8/SUMIFS(BL$2:BL$398,G$2:G$398,G8) -> 0.2249742 | CF8: =BM8/SUMIFS(BM$2:BM$398,G$2:G$398,G8) -> 0.11412268 | CG8: =CE8-CF8 -> 0.11085152 | CH8: =BP8/SUMIFS(BP$2:BP$398,G$2:G$398,G8) -> 0.082125042 | CI8: =BQ8/SUMIFS(BQ$2:BQ$398,G$2:G$398,G8) -> 0.080480417 | CJ8: =CH8-CI8 -> 0.0016446246 | CK8: =BT8/SUMIFS(BT$2:BT$398,G$2:G$398,G8) -> 0.17182391 | CL8: =BU8/SUMIFS(BU$2:BU$398,G$2:G$398,G8) -> 0.12989577 | CM8: =CK8-CL8 -> 0.041928142 | CN8: =COUNTIFS(G$2:G$398,G8)*CH8 -> 0.49275025 | CO8: =COUNTIFS(G$2:G$398,G8)*CK8 -> 1.0309435
A9: 41056502 | B9: HPC | C9: INDRA FILLING STATION | D9: NARAINA | E9: NEW DELHI | F9: SYALL SS | G9: White Patch- Naraina | H9: Punjabi Bagh | I9: Abhinav | J9: 265 | K9: 284 | L9: 289 | M9: 574 | N9: 324 | O9: 317 | P9: 441 | Q9: 665 | R9: 314.5 | S9: 278 | T9: 643.5 | U9: 369 | V9: 321.5 | W9: 294.5 | X9: 569.5 | Y9: 516.5 | Z9: 326.5 | AA9: 317.5 | AB9: 570.5 | AC9: 567.5 | AD9: 331.5 | AE9: 315 | AF9: 703.5 | AG9: 592 | AH9: 313 | AI9: 322 | AJ9: 645 | AK9: 597 | AL9: 312.5 | AM9: 287 | AN9: 614.5 | AO9: 488 | AP9: 298 | AQ9: 291 | AR9: 787 | AS9: 521 | AT9: 304.5 | AU9: 295 | AV9: 613.5 | AW9: 594 | AX9: 281 | AY9: 255 | AZ9: 386 | BA9: 587 | BB9: 302.5 | BC9: 304 | BD9: 610.5 | BE9: 579 | BF9: 28.64191 | BG9: 77.14535 | BH9: =BB9 -> 302.5 | BI9: =BC9 -> 304 | BJ9: =(BH9-BI9) -> -1.5 | BK9: =(BJ9)/BI9*100 -> -0.49342105 | BL9: =BD9 -> 610.5 | BM9: =BE9 -> 579 | BN9: =(BL9-BM9) -> 31.5 | BO9: =(BN9)/BM9*100 -> 5.4404145 | BP9: =K9+O9+R9+V9+Z9+AD9+AH9+AL9+AP9+AT9+AX9+BB9 -> 3706.5 | BQ9: =J9+N9+S9+W9+AA9+AE9+AI9+AM9+AQ9+AU9+Table1[[#This Row],[MS-0225]]+Table1[[#This Row],[MS-0325]] -> 3548 | BR9: =(BP9-BQ9) -> 158.5 | BS9: =(BR9)/BQ9*100 -> 4.4673055 | BT9: =M9+Q9+T9+X9+AB9+AF9+AJ9+AN9+AR9+AV9+AZ9+BD9 -> 7382.5 | BU9: =L9+P9+U9+Y9+AC9+AG9+AK9+AO9+AS9+AW9+BA9+BE9 -> 6141 | BV9: =(BT9-BU9) -> 1241.5 | BW9: =(BV9)/BU9*100 -> 20.216577 | BX9: 0 | BY9: =BX9/BH9 -> 0 | BZ9: 0 | CA9: =BZ9/BP9 -> 0 | CB9: =BH9/SUMIFS(BH$2:BH$398,G$2:G$398,G9) -> 0.43872371 | CC9: =BI9/SUMIFS(BI$2:BI$398,G$2:G$398,G9) -> 0.39895013 | CD9: =CB9-CC9 -> 0.039773582 | CE9: =BL9/SUMIFS(BL$2:BL$398,G$2:G$398,G9) -> 0.70618855 | CF9: =BM9/SUMIFS(BM$2:BM$398,G$2:G$398,G9) -> 0.66475316 | CG9: =CE9-CF9 -> 0.041435391 | CH9: =BP9/SUMIFS(BP$2:BP$398,G$2:G$398,G9) -> 0.40565831 | CI9: =BQ9/SUMIFS(BQ$2:BQ$398,G$2:G$398,G9) -> 0.40993645 | CJ9: =CH9-CI9 -> -0.0042781406 | CK9: =BT9/SUMIFS(BT$2:BT$398,G$2:G$398,G9) -> 0.73210036 | CL9: =BU9/SUMIFS(BU$2:BU$398,G$2:G$398,G9) -> 0.64270016 | CM9: =CK9-CL9 -> 0.0894002 | CN9: =COUNTIFS(G$2:G$398,G9)*CH9 -> 0.81131662 | CO9: =COUNTIFS(G$2:G$398,G9)*CK9 -> 1.4642007 | CP9: =BD9-AZ9 -> 224.5
A10: 41056524 | B10: HPC | C10: ASSOCIATED SERVICE STATION | D10: SHAMNATH MARG | E10: CENTRAL DELHI | F10: RAJINDER-RS BHOLA | G10: RAJINDER-RS BHOLA | H10: Old Delhi | I10: Abhinav | J10: 144.5 | K10: 187 | L10: 438.5 | M10: 441 | N10: 172 | O10: 195 | P10: 512 | Q10: 513 | R10: 179.5 | S10: 117 | T10: 470.5 | U10: 483 | V10: 199 | W10: 148.5 | X10: 333 | Y10: 394.5 | Z10: 197 | AA10: 137.5 | AB10: 342 | AC10: 379.5 | AD10: 179 | AE10: 134 | AF10: 245 | AG10: 314 | AH10: 180 | AI10: 73 | AJ10: 289 | AK10: 339 | AL10: 182 | AM10: 109.5 | AN10: 301 | AO10: 317.5 | AP10: 179 | AQ10: 128 | AR10: 281 | AS10: 345 | AT10: 168 | AU10: 150 | AV10: 300 | AW10: 359 | AX10: 174 | AY10: 134 | AZ10: 328 | BA10: 449 | BB10: 185.5 | BC10: 169.5 | BD10: 379.5 | BE10: 445.5 | BF10: 28.67008 | BG10: 77.22636 | BH10: =BB10 -> 185.5 | BI10: =BC10 -> 169.5 | BJ10: =(BH10-BI10) -> 16 | BK10: =(BJ10)/BI10*100 -> 9.439528 | BL10: =BD10 -> 379.5 | BM10: =BE10 -> 445.5 | BN10: =(BL10-BM10) -> -66 | BO10: =(BN10)/BM10*100 -> -14.814815 | BP10: =K10+O10+R10+V10+Z10+AD10+AH10+AL10+AP10+AT10+AX10+BB10 -> 2205 | BQ10: =J10+N10+S10+W10+AA10+AE10+AI10+AM10+AQ10+AU10+Table1[[#This Row],[MS-0225]]+Table1[[#This Row],[MS-0325]] -> 1617.5 | BR10: =(BP10-BQ10) -> 587.5 | BS10: =(BR10)/BQ10*100 -> 36.321484 | BT10: =M10+Q10+T10+X10+AB10+AF10+AJ10+AN10+AR10+AV10+AZ10+BD10 -> 4223 | BU10: =L10+P10+U10+Y10+AC10+AG10+AK10+AO10+AS10+AW10+BA10+BE10 -> 4776.5 | BV10: =(BT10-BU10) -> -553.5 | BW10: =(BV10)/BU10*100 -> -11.587983 | BX10: 0 | BY10: =BX10/BH10 -> 0 | BZ10: 0 | CA10: =BZ10/BP10 -> 0 | CB10: =BH10/SUMIFS(BH$2:BH$398,G$2:G$398,G10) -> 0.2601683 | CC10: =BI10/SUMIFS(BI$2:BI$398,G$2:G$398,G10) -> 0.23722883 | CD10: =CB10-CC10 -> 0.022939472 | CE10: =BL10/SUMIFS(BL$2:BL$398,G$2:G$398,G10) -> 0.22833935 | CF10: =BM10/SUMIFS(BM$2:BM$398,G$2:G$398,G10) -> 0.28330684 | CG10: =CE10-CF10 -> -0.054967486 | CH10: =BP10/SUMIFS(BP$2:BP$398,G$2:G$398,G10) -> 0.24405091 | CI10: =BQ10/SUMIFS(BQ$2:BQ$398,G$2:G$398,G10) -> 0.18496284 | CJ10: =CH10-CI10 -> 0.059088077 | CK10: =BT10/SUMIFS(BT$2:BT$398,G$2:G$398,G10) -> 0.25549035 | CL10: =BU10/SUMIFS(BU$2:BU$398,G$2:G$398,G10) -> 0.27651384 | CM10: =CK10-CL10 -> -0.021023486 | CN10: =COUNTIFS(G$2:G$398,G10)*CH10 -> 0.73215274 | CO10: =COUNTIFS(G$2:G$398,G10)*CK10 -> 0.76647105 | CP10: =BD10-AZ10 -> 51.5
A11: 106336 | B11: IOC | C11: S VIDYA SERVICE STATION | D11: SEC-3, DWARKA | E11: SOUTH WEST DELHI | F11: SHIV SS | G11: SHIV SS | H11: Dwarka | I11: Raj Doshi | J11: 789.5 | K11: 800 | L11: 112.5 | M11: 100 | N11: 824.5 | O11: 825 | P11: 131.5 | Q11: 115 | R11: 780 | S11: 789 | T11: 114 | U11: 113 | V11: 805 | W11: 845 | X11: 115 | Y11: 115 | Z11: 830 | AA11: 850 | AB11: 90 | AC11: 110 | AD11: 800 | AE11: 805 | AF11: 100 | AG11: 113 | AH11: 854 | AI11: 870 | AJ11: 100 | AK11: 110 | AL11: 800 | AM11: 780 | AN11: 100 | AO11: 94 | AP11: 770 | AQ11: 765 | AR11: 70 | AS11: 95 | AT11: 745 | AU11: 758 | AV11: 95 | AW11: 100 | AX11: 740 | AY11: 699 | AZ11: 94 | BA11: 95 | BB11: 823 | BC11: 775 | BD11: 109 | BE11: 105 | BF11: 28.6048 | BG11: 77.0541 | BH11: =BB11 -> 823 | BI11: =BC11 -> 775 | BJ11: =(BH11-BI11) -> 48 | BK11: =(BJ11)/BI11*100 -> 6.1935484 | BL11: =BD11 -> 109 | BM11: =BE11 -> 105 | BN11: =(BL11-BM11) -> 4 | BO11: =(BN11)/BM11*100 -> 3.8095238 | BP11: =K11+O11+R11+V11+Z11+AD11+AH11+AL11+AP11+AT11+AX11+BB11 -> 9572 | BQ11: =J11+N11+S11+W11+AA11+AE11+AI11+AM11+AQ11+AU11+Table1[[#This Row],[MS-0225]]+Table1[[#This Row],[MS-0325]] -> 9550 | BR11: =(BP11-BQ11) -> 22 | BS11: =(BR11)/BQ11*100 -> 0.23036649 | BT11: =M11+Q11+T11+X11+AB11+AF11+AJ11+AN11+AR11+AV11+AZ11+BD11 -> 1202 | BU11: =L11+P11+U11+Y11+AC11+AG11+AK11+AO11+AS11+AW11+BA11+BE11 -> 1294 | BV11: =(BT11-BU11) -> -92 | BW11: =(BV11)/BU11*100 -> -7.1097372 | BX11: 0 | BY11: =BX11/BH11 -> 0 | BZ11: 0 | CA11: =BZ11/BP11 -> 0 | CB11: =BH11/SUMIFS(BH$2:BH$398,G$2:G$398,G11) -> 0.21550144 | CC11: =BI11/SUMIFS(BI$2:BI$398,G$2:G$398,G11) -> 0.21397018 | CD11: =CB11-CC11 -> 0.0015312579 | CE11: =BL11/SUMIFS(BL$2:BL$398,G$2:G$398,G11) -> 0.20297952 | CF11: =BM11/SUMIFS(BM$2:BM$398,G$2:G$398,G11) -> 0.18421053 | CG11: =CE11-CF11 -> 0.01876899 | CH11: =BP11/SUMIFS(BP$2:BP$398,G$2:G$398,G11) -> 0.21186835 | CI11: =BQ11/SUMIFS(BQ$2:BQ$398,G$2:G$398,G11) -> 0.21863553 | CJ11: =CH11-CI11 -> -0.0067671851 | CK11: =BT11/SUMIFS(BT$2:BT$398,G$2:G$398,G11) -> 0.18749025 | CL11: =BU11/SUMIFS(BU$2:BU$398,G$2:G$398,G11) -> 0.18307866 | CM11: =CK11-CL11 -> 0.0044115867 | CN11: =COUNTIFS(G$2:G$398,G11)*CH11 -> 1.4830784 | CO11: =COUNTIFS(G$2:G$398,G11)*CK11 -> 1.3124318
A12: 186866 | B12: IOC | C12: LOTUS AUTOMOBILES | D12: ANDHERIA MOR | E12: SOUTH DELHI | F12: White Patch_Chhatarpur_to_Gurgaon | G12: White Patch_Chhatarpur_to_Gurgaon | H12: Hauj Khas-Saket-Vasant Kunj | I12: Raj Doshi | J12: 658.5 | K12: 729 | L12: 235.5 | M12: 219 | N12: 719.5 | O12: 842.5 | P12: 256.5 | Q12: 275.5 | R12: 772.5 | S12: 688.5 | T12: 241.5 | U12: 277.5 | V12: 892 | W12: 719.5 | X12: 252 | Y12: 234.5 | Z12: 816.5 | AA12: 732.5 | AB12: 239.5 | AC12: 249.5 | AD12: 756.5 | AE12: 693 | AF12: 207.5 | AG12: 217 | AH12: 790.5 | AI12: 744 | AJ12: 217.5 | AK12: 222 | AL12: 741 | AM12: 646 | AN12: 187 | AO12: 186 | AP12: 746.5 | AQ12: 648 | AR12: 165.5 | AS12: 178 | AT12: 705.5 | AU12: 667 | AV12: 174.5 | AW12: 193 | AX12: 725 | AY12: 641 | AZ12: 173 | BA12: 181 | BB12: 809 | BC12: 680 | BD12: 221 | BE12: 190 | BF12: 28.5043 | BG12: 77.1721 | BH12: =BB12 -> 809 | BI12: =BC12 -> 680 | BJ12: =(BH12-BI12) -> 129 | BK12: =(BJ12)/BI12*100 -> 18.970588 | BL12: =BD12 -> 221 | BM12: =BE12 -> 190 | BN12: =(BL12-BM12) -> 31 | BO12: =(BN12)/BM12*100 -> 16.315789 | BP12: =K12+O12+R12+V12+Z12+AD12+AH12+AL12+AP12+AT12+AX12+BB12 -> 9326.5 | BQ12: =J12+N12+S12+W12+AA12+AE12+AI12+AM12+AQ12+AU12+Table1[[#This Row],[MS-0225]]+Table1[[#This Row],[MS-0325]] -> 8237.5 | BR12: =(BP12-BQ12) -> 1089 | BS12: =(BR12)/BQ12*100 -> 13.22003 | BT12: =M12+Q12+T12+X12+AB12+AF12+AJ12+AN12+AR12+AV12+AZ12+BD12 -> 2573.5 | BU12: =L12+P12+U12+Y12+AC12+AG12+AK12+AO12+AS12+AW12+BA12+BE12 -> 2620.5 | BV12: =(BT12-BU12) -> -47 | BW12: =(BV12)/BU12*100 -> -1.7935508 | BX12: 0 | BY12: =BX12/BH12 -> 0 | BZ12: 0 | CA12: =BZ12/BP12 -> 0 | CB12: =BH12/SUMIFS(BH$2:BH$398,G$2:G$398,G12) -> 0.57723867 | CC12: =BI12/SUMIFS(BI$2:BI$398,G$2:G$398,G12) -> 0.55578259 | CD12: =CB12-CC12 -> 0.021456082 | CE12: =BL12/SUMIFS(BL$2:BL$398,G$2:G$398,G12) -> 0.57477243 | CF12: =BM12/SUMIFS(BM$2:BM$398,G$2:G$398,G12) -> 0.49414824 | CG12: =CE12-CF12 -> 0.080624187 | CH12: =BP12/SUMIFS(BP$2:BP$398,G$2:G$398,G12) -> 0.58922197 | CI12: =BQ12/SUMIFS(BQ$2:BQ$398,G$2:G$398,G12) -> 0.55339088 | CJ12: =CH12-CI12 -> 0.035831089 | CK12: =BT12/SUMIFS(BT$2:BT$398,G$2:G$398,G12) -> 0.52525768 | CL12: =BU12/SUMIFS(BU$2:BU$398,G$2:G$398,G12) -> 0.50834142 | CM12: =CK12-CL12 -> 0.016916263 | CN12: =COUNTIFS(G$2:G$398,G12)*CH12 -> 1.1784439 | CO12: =COUNTIFS(G$2:G$398,G12)*CK12 -> 1.0505154
A13: 106289 | B13: IOC | C13: KOMAL and BROS. SERVICE STN. | D13: MANDAVALI, FAZALPUR | E13: EAST DELHI | F13: White Patch_Merrut Expressway | G13: White Patch_Merrut Expressway | H13: Mayur Vihar -Anand Vihar -Preet Vihar | I13: Bhanu Pratap | J13: 688.5 | K13: 717.5 | L13: 185.5 | M13: 166.5 | N13: 721.5 | O13: 748 | P13: 196.5 | Q13: 158 | R13: 758.5 | S13: 724 | T13: 145.5 | U13: 186 | V13: 759.5 | W13: 728 | X13: 150.5 | Y13: 196 | Z13: 759 | AA13: 714 | AB13: 147 | AC13: 186 | AD13: 710.5 | AE13: 675 | AF13: 157.5 | AG13: 157 | AH13: 774 | AI13: 714.5 | AJ13: 150 | AK13: 173.5 | AL13: 738 | AM13: 701.5 | AN13: 140 | AO13: 158.5 | AP13: 718 | AQ13: 700.5 | AR13: 132 | AS13: 135.5 | AT13: 685 | AU13: 692.5 | AV13: 145 | AW13: 153.5 | AX13: 693 | AY13: 665 | AZ13: 131 | BA13: 163 | BB13: 787 | BC13: 723.5 | BD13: 151 | BE13: 166.5 | BF13: 28.6292 | BG13: 77.3122 | BH13: =BB13 -> 787 | BI13: =BC13 -> 723.5 | BJ13: =(BH13-BI13) -> 63.5 | BK13: =(BJ13)/BI13*100 -> 8.7767795 | BL13: =BD13 -> 151 | BM13: =BE13 -> 166.5 | BN13: =(BL13-BM13) -> -15.5 | BO13: =(BN13)/BM13*100 -> -9.3093093 | BP13: =K13+O13+R13+V13+Z13+AD13+AH13+AL13+AP13+AT13+AX13+BB13 -> 8848 | BQ13: =J13+N13+S13+W13+AA13+AE13+AI13+AM13+AQ13+AU13+Table1[[#This Row],[MS-0225]]+Table1[[#This Row],[MS-0325]] -> 8448.5 | BR13: =(BP13-BQ13) -> 399.5 | BS13: =(BR13)/BQ13*100 -> 4.7286501 | BT13: =M13+Q13+T13+X13+AB13+AF13+AJ13+AN13+AR13+AV13+AZ13+BD13 -> 1774 | BU13: =L13+P13+U13+Y13+AC13+AG13+AK13+AO13+AS13+AW13+BA13+BE13 -> 2057.5 | BV13: =(BT13-BU13) -> -283.5 | BW13: =(BV13)/BU13*100 -> -13.778858 | BX13: 0 | BY13: =BX13/BH13 -> 0 | BZ13: 0 | CA13: =BZ13/BP13 -> 0 | CB13: =BH13/SUMIFS(BH$2:BH$398,G$2:G$398,G13) -> 0.42993718 | CC13: =BI13/SUMIFS(BI$2:BI$398,G$2:G$398,G13) -> 0.43323353 | CD13: =CB13-CC13 -> -0.0032963573 | CE13: =BL13/SUMIFS(BL$2:BL$398,G$2:G$398,G13) -> 0.39169909 | CF13: =BM13/SUMIFS(BM$2:BM$398,G$2:G$398,G13) -> 0.40609756 | CG13: =CE13-CF13 -> -0.014398469 | CH13: =BP13/SUMIFS(BP$2:BP$398,G$2:G$398,G13) -> 0.42185563 | CI13: =BQ13/SUMIFS(BQ$2:BQ$398,G$2:G$398,G13) -> 0.42498554 | CJ13: =CH13-CI13 -> -0.0031299071 | CK13: =BT13/SUMIFS(BT$2:BT$398,G$2:G$398,G13) -> 0.37857448 | CL13: =BU13/SUMIFS(BU$2:BU$398,G$2:G$398,G13) -> 0.40466123 | CM13: =CK13-CL13 -> -0.026086748 | CN13: =COUNTIFS(G$2:G$398,G13)*CH13 -> 2.1092782 | CO13: =COUNTIFS(G$2:G$398,G13)*CK13 -> 1.8928724
A14: 106270 | B14: IOC | C14: IMAGE FILLING STATION | D14: MAYUR VIHAR, PHASE-I | E14: EAST DELHI | F14: White Patch_Noida Link road to Greater Noida Expwy | G14: White Patch_Noida Link road to Greater Noida Expwy | H14: Mayur Vihar -Anand Vihar -Preet Vihar | I14: Bhanu Pratap | J14: 707.5 | K14: 761 | L14: 194.5 | M14: 173 | N14: 755.5 | O14: 803 | P14: 208.5 | Q14: 173 | R14: 757 | S14: 735.5 | T14: 159 | U14: 192.5 | V14: 791.5 | W14: 765.5 | X14: 154.5 | Y14: 184.5 | Z14: 790 | AA14: 781.5 | AB14: 162 | AC14: 202.5 | AD14: 755 | AE14: 735.5 | AF14: 185 | AG14: 184.5 | AH14: 782.5 | AI14: 779.5 | AJ14: 233.5 | AK14: 196.5 | AL14: 723.5 | AM14: 710.5 | AN14: 168.5 | AO14: 155.5 | AP14: 708 | AQ14: 721.5 | AR14: 148 | AS14: 152.5 | AT14: 690 | AU14: 696 | AV14: 130 | AW14: 160 | AX14: 678 | AY14: 655 | AZ14: 138 | BA14: 179 | BB14: 770 | BC14: 745.5 | BD14: 150 | BE14: 166.5 | BF14: 28.5937 | BG14: 77.2968 | BH14: =BB14 -> 770 | BI14: =BC14 -> 745.5 | BJ14: =(BH14-BI14) -> 24.5 | BK14: =(BJ14)/BI14*100 -> 3.286385 | BL14: =BD14 -> 150 | BM14: =BE14 -> 166.5 | BN14: =(BL14-BM14) -> -16.5 | BO14: =(BN14)/BM14*100 -> -9.9099099 | BP14: =K14+O14+R14+V14+Z14+AD14+AH14+AL14+AP14+AT14+AX14+BB14 -> 9009.5 | BQ14: =J14+N14+S14+W14+AA14+AE14+AI14+AM14+AQ14+AU14+Table1[[#This Row],[MS-0225]]+Table1[[#This Row],[MS-0325]] -> 8789 | BR14: =(BP14-BQ14) -> 220.5 | BS14: =(BR14)/BQ14*100 -> 2.5088178 | BT14: =M14+Q14+T14+X14+AB14+AF14+AJ14+AN14+AR14+AV14+AZ14+BD14 -> 1974.5 | BU14: =L14+P14+U14+Y14+AC14+AG14+AK14+AO14+AS14+AW14+BA14+BE14 -> 2177 | BV14: =(BT14-BU14) -> -202.5 | BW14: =(BV14)/BU14*100 -> -9.3017915 | BX14: 0 | BY14: =BX14/BH14 -> 0 | BZ14: 0 | CA14: =BZ14/BP14 -> 0 | CB14: =BH14/SUMIFS(BH$2:BH$398,G$2:G$398,G14) -> 1 | CC14: =BI14/SUMIFS(BI$2:BI$398,G$2:G$398,G14) -> 1 | CD14: =CB14-CC14 -> 0 | CE14: =BL14/SUMIFS(BL$2:BL$398,G$2:G$398,G14) -> 1 | CF14: =BM14/SUMIFS(BM$2:BM$398,G$2:G$398,G14) -> 1 | CG14: =CE14-CF14 -> 0 | CH14: =BP14/SUMIFS(BP$2:BP$398,G$2:G$398,G14) -> 1 | CI14: =BQ14/SUMIFS(BQ$2:BQ$398,G$2:G$398,G14) -> 1 | CJ14: =CH14-CI14 -> 0 | CK14: =BT14/SUMIFS(BT$2:BT$398,G$2:G$398,G14) -> 1 | CL14: =BU14/SUMIFS(BU$2:BU$398,G$2:G$398,G14) -> 1 | CM14: =CK14-CL14 -> 0 | CN14: =COUNTIFS(G$2:G$398,G14)*CH14 -> 1 | CO14: =COUNTIFS(G$2:G$398,G14)*CK14 -> 1
A15: 186860 | B15: IOC | C15: SATBIR FILLING STATION | D15: IGI MOR | E15: NEW DELHI | F15: White Patch_IGI_NH8 | G15: White Patch_IGI_NH8 | H15: Dwarka | I15: Raj Doshi | J15: 729 | K15: 765 | L15: 279 | M15: 255 | N15: 791 | O15: 800 | P15: 301 | Q15: 260 | R15: 755 | S15: 787.5 | T15: 245 | U15: 310.5 | V15: 835 | W15: 765 | X15: 265 | Y15: 297 | Z15: 795 | AA15: 805.5 | AB15: 245 | AC15: 292.5 | AD15: 755 | AE15: 706.5 | AF15: 245 | AG15: 265.5 | AH15: 795 | AI15: 711 | AJ15: 245 | AK15: 261 | AL15: 750 | AM15: 630 | AN15: 210 | AO15: 216 | AP15: 740 | AQ15: 679.5 | AR15: 180 | AS15: 202.5 | AT15: 720 | AU15: 666 | AV15: 200 | AW15: 216 | AX15: 705 | AY15: 630 | AZ15: 215 | BA15: 216 | BB15: 770 | BC15: 733 | BD15: 210 | BE15: 233 | BF15: 28.5336 | BG15: 77.1069 | BH15: =BB15 -> 770 | BI15: =BC15 -> 733 | BJ15: =(BH15-BI15) -> 37 | BK15: =(BJ15)/BI15*100 -> 5.047749 | BL15: =BD15 -> 210 | BM15: =BE15 -> 233 | BN15: =(BL15-BM15) -> -23 | BO15: =(BN15)/BM15*100 -> -9.8712446 | BP15: =K15+O15+R15+V15+Z15+AD15+AH15+AL15+AP15+AT15+AX15+BB15 -> 9185 | BQ15: =J15+N15+S15+W15+AA15+AE15+AI15+AM15+AQ15+AU15+Table1[[#This Row],[MS-0225]]+Table1[[#This Row],[MS-0325]] -> 8634 | BR15: =(BP15-BQ15) -> 551 | BS15: =(BR15)/BQ15*100 -> 6.3817466 | BT15: =M15+Q15+T15+X15+AB15+AF15+AJ15+AN15+AR15+AV15+AZ15+BD15 -> 2775 | BU15: =L15+P15+U15+Y15+AC15+AG15+AK15+AO15+AS15+AW15+BA15+BE15 -> 3090 | BV15: =(BT15-BU15) -> -315 | BW15: =(BV15)/BU15*100 -> -10.194175 | BX15: 0 | BY15: =BX15/BH15 -> 0 | BZ15: 0 | CA15: =BZ15/BP15 -> 0 | CB15: =BH15/SUMIFS(BH$2:BH$398,G$2:G$398,G15) -> 1 | CC15: =BI15/SUMIFS(BI$2:BI$398,G$2:G$398,G15) -> 1 | CD15: =CB15-CC15 -> 0 | CE15: =BL15/SUMIFS(BL$2:BL$398,G$2:G$398,G15) -> 1 | CF15: =BM15/SUMIFS(BM$2:BM$398,G$2:G$398,G15) -> 1 | CG15: =CE15-CF15 -> 0 | CH15: =BP15/SUMIFS(BP$2:BP$398,G$2:G$398,G15) -> 1 | CI15: =BQ15/SUMIFS(BQ$2:BQ$398,G$2:G$398,G15) -> 1 | CJ15: =CH15-CI15 -> 0 | CK15: =BT15/SUMIFS(BT$2:BT$398,G$2:G$398,G15) -> 1 | CL15: =BU15/SUMIFS(BU$2:BU$398,G$2:G$398,G15) -> 1 | CM15: =CK15-CL15 -> 0 | CN15: =COUNTIFS(G$2:G$398,G15)*CH15 -> 1 | CO15: =COUNTIFS(G$2:G$398,G15)*CK15 -> 1
A16: 112397 | B16: BPC | C16: BUDH SINGH GULAB SINGH | D16: MEHRAULI ROAD DELHI | E16: SOUTH DELHI | F16: BSGS | G16: BSGS | H16: Hauj Khas-Saket-Vasant Kunj | I16: Raj Doshi | J16: 634.5 | K16: 642 | L16: 193.5 | M16: 180 | N16: 684 | O16: 693 | P16: 252 | Q16: 225 | R16: 652.5 | S16: 639 | T16: 175.5 | U16: 207 | V16: 729 | W16: 711 | X16: 189 | Y16: 225 | Z16: 715.5 | AA16: 679.5 | AB16: 184.5 | AC16: 238.5 | AD16: 724.5 | AE16: 688.5 | AF16: 211.5 | AG16: 193.5 | AH16: 717 | AI16: 697.5 | AJ16: 195 | AK16: 220.5 | AL16: 675 | AM16: 616.5 | AN16: 165 | AO16: 193.5 | AP16: 685 | AQ16: 607.5 | AR16: 135 | AS16: 166.5 | AT16: 625 | AU16: 621 | AV16: 175 | AW16: 171 | AX16: 650 | AY16: 578 | AZ16: 170 | BA16: 180 | BB16: 760 | BC16: 639 | BD16: 220 | BE16: 207 | BF16: 28.52799 | BG16: 77.18981 | BH16: =BB16 -> 760 | BI16: =BC16 -> 639 | BJ16: =(BH16-BI16) -> 121 | BK16: =(BJ16)/BI16*100 -> 18.935837 | BL16: =BD16 -> 220 | BM16: =BE16 -> 207 | BN16: =(BL16-BM16) -> 13 | BO16: =(BN16)/BM16*100 -> 6.2801932 | BP16: =K16+O16+R16+V16+Z16+AD16+AH16+AL16+AP16+AT16+AX16+BB16 -> 8268.5 | BQ16: =J16+N16+S16+W16+AA16+AE16+AI16+AM16+AQ16+AU16+Table1[[#This Row],[MS-0225]]+Table1[[#This Row],[MS-0325]] -> 7796 | BR16: =(BP16-BQ16) -> 472.49999 | BS16: =(BR16)/BQ16*100 -> 6.0608003 | BT16: =M16+Q16+T16+X16+AB16+AF16+AJ16+AN16+AR16+AV16+AZ16+BD16 -> 2225.5 | BU16: =L16+P16+U16+Y16+AC16+AG16+AK16+AO16+AS16+AW16+BA16+BE16 -> 2448 | BV16: =(BT16-BU16) -> -222.5 | BW16: =(BV16)/BU16*100 -> -9.0890523 | BX16: 143.5 | BY16: =BX16/BH16 -> 0.18881579 | BZ16: 809.5 | CA16: =BZ16/BP16 -> 0.097901675 | CB16: =BH16/SUMIFS(BH$2:BH$398,G$2:G$398,G16) -> 0.46270928 | CC16: =BI16/SUMIFS(BI$2:BI$398,G$2:G$398,G16) -> 0.42150396 | CD16: =CB16-CC16 -> 0.041205327 | CE16: =BL16/SUMIFS(BL$2:BL$398,G$2:G$398,G16) -> 0.5398773 | CF16: =BM16/SUMIFS(BM$2:BM$398,G$2:G$398,G16) -> 0.4579646 | CG16: =CE16-CF16 -> 0.081912699 | CH16: =BP16/SUMIFS(BP$2:BP$398,G$2:G$398,G16) -> 0.42974455 | CI16: =BQ16/SUMIFS(BQ$2:BQ$398,G$2:G$398,G16) -> 0.42520931 | CJ16: =CH16-CI16 -> 0.0045352442 | CK16: =BT16/SUMIFS(BT$2:BT$398,G$2:G$398,G16) -> 0.48238864 | CL16: =BU16/SUMIFS(BU$2:BU$398,G$2:G$398,G16) -> 0.45552661 | CM16: =CK16-CL16 -> 0.026862032 | CN16: =COUNTIFS(G$2:G$398,G16)*CH16 -> 1.2892336 | CO16: =COUNTIFS(G$2:G$398,G16)*CK16 -> 1.4471659
A17: 112720 | B17: BPC | C17: MASIH AUTOMOBILES | D17: ANAND VIHAR,NEW DELHI | E17: SHAHDARA | F17: ALLIED_MASIH | G17: ALLIED_MASIH | H17: Mayur Vihar -Anand Vihar -Preet Vihar | I17: Bhanu Pratap | J17: 697 | K17: 770.5 | L17: 203 | M17: 183.5 | N17: 769 | O17: 772 | P17: 221 | Q17: 204 | R17: 707 | S17: 707.5 | T17: 175 | U17: 228.5 | V17: 834 | W17: 809 | X17: 200 | Y17: 217 | Z17: 781 | AA17: 772.5 | AB17: 187 | AC17: 217.5 | AD17: 737 | AE17: 732.5 | AF17: 165 | AG17: 203.5 | AH17: 768 | AI17: 755 | AJ17: 178 | AK17: 199 | AL17: 693 | AM17: 686 | AN17: 165 | AO17: 160 | AP17: 703 | AQ17: 694 | AR17: 155 | AS17: 152 | AT17: 659 | AU17: 622.5 | AV17: 155 | AW17: 169.5 | AX17: 644 | AY17: 639 | AZ17: 148 | BA17: 153 | BB17: 754 | BC17: 706 | BD17: 170 | BE17: 176 | BF17: 28.65808 | BG17: 77.31086 | BH17: =BB17 -> 754 | BI17: =BC17 -> 706 | BJ17: =(BH17-BI17) -> 48 | BK17: =(BJ17)/BI17*100 -> 6.7988669 | BL17: =BD17 -> 170 | BM17: =BE17 -> 176 | BN17: =(BL17-BM17) -> -6 | BO17: =(BN17)/BM17*100 -> -3.4090909 | BP17: =K17+O17+R17+V17+Z17+AD17+AH17+AL17+AP17+AT17+AX17+BB17 -> 8822.5 | BQ17: =J17+N17+S17+W17+AA17+AE17+AI17+AM17+AQ17+AU17+Table1[[#This Row],[MS-0225]]+Table1[[#This Row],[MS-0325]] -> 8590 | BR17: =(BP17-BQ17) -> 232.5 | BS17: =(BR17)/BQ17*100 -> 2.7066356 | BT17: =M17+Q17+T17+X17+AB17+AF17+AJ17+AN17+AR17+AV17+AZ17+BD17 -> 2085.5 | BU17: =L17+P17+U17+Y17+AC17+AG17+AK17+AO17+AS17+AW17+BA17+BE17 -> 2300 | BV17: =(BT17-BU17) -> -214.5 | BW17: =(BV17)/BU17*100 -> -9.326087 | BX17: 64 | BY17: =BX17/BH17 -> 0.084880637 | BZ17: 397.5 | CA17: =BZ17/BP17 -> 0.045055256 | CB17: =BH17/SUMIFS(BH$2:BH$398,G$2:G$398,G17) -> 0.18258869 | CC17: =BI17/SUMIFS(BI$2:BI$398,G$2:G$398,G17) -> 0.18603426 | CD17: =CB17-CC17 -> -0.0034455645 | CE17: =BL17/SUMIFS(BL$2:BL$398,G$2:G$398,G17) -> 0.26666667 | CF17: =BM17/SUMIFS(BM$2:BM$398,G$2:G$398,G17) -> 0.26268657 | CG17: =CE17-CF17 -> 0.0039800995 | CH17: =BP17/SUMIFS(BP$2:BP$398,G$2:G$398,G17) -> 0.17973267 | CI17: =BQ17/SUMIFS(BQ$2:BQ$398,G$2:G$398,G17) -> 0.18768777 | CJ17: =CH17-CI17 -> -0.0079550998 | CK17: =BT17/SUMIFS(BT$2:BT$398,G$2:G$398,G17) -> 0.26873449 | CL17: =BU17/SUMIFS(BU$2:BU$398,G$2:G$398,G17) -> 0.27198335 | CM17: =CK17-CL17 -> -0.0032488603 | CN17: =COUNTIFS(G$2:G$398,G17)*CH17 -> 1.4378614 | CO17: =COUNTIFS(G$2:G$398,G17)*CK17 -> 2.1498759
A18: 41056494 | B18: HPC | C18: SHANTI SERVICE STATION | D18: MADANPUR KHADAR | E18: SOUTH EAST DELHI | F18: AUTO REST_OKHLA | G18: AUTO REST_OKHLA | H18: Mathura Road | I18: Bhanu Pratap | J18: 610 | K18: 691 | L18: 216 | M18: 230 | N18: 688 | O18: 746 | P18: 246 | Q18: 239 | R18: 680 | S18: 558 | T18: 200 | U18: 211 | V18: 743 | W18: 575.5 | X18: 215 | Y18: 201.5 | Z18: 757 | AA18: 659.5 | AB18: 203 | AC18: 217.5 | AD18: 705 | AE18: 609.5 | AF18: 218 | AG18: 218.5 | AH18: 729 | AI18: 675 | AJ18: 205 | AK18: 245 | AL18: 739.5 | AM18: 733 | AN18: 204.5 | AO18: 208 | AP18: 746.5 | AQ18: 670 | AR18: 163.5 | AS18: 182 | AT18: 726 | AU18: 651 | AV18: 196 | AW18: 175 | AX18: 699.5 | AY18: 649 | AZ18: 202.5 | BA18: 200 | BB18: 733 | BC18: 714 | BD18: 184 | BE18: 230 | BF18: 28.52094 | BG18: 77.29476 | BH18: =BB18 -> 733 | BI18: =BC18 -> 714 | BJ18: =(BH18-BI18) -> 19 | BK18: =(BJ18)/BI18*100 -> 2.6610644 | BL18: =BD18 -> 184 | BM18: =BE18 -> 230 | BN18: =(BL18-BM18) -> -46 | BO18: =(BN18)/BM18*100 -> -20 | BP18: =K18+O18+R18+V18+Z18+AD18+AH18+AL18+AP18+AT18+AX18+BB18 -> 8695.5 | BQ18: =J18+N18+S18+W18+AA18+AE18+AI18+AM18+AQ18+AU18+Table1[[#This Row],[MS-0225]]+Table1[[#This Row],[MS-0325]] -> 7792.5 | BR18: =(BP18-BQ18) -> 903 | BS18: =(BR18)/BQ18*100 -> 11.588065 | BT18: =M18+Q18+T18+X18+AB18+AF18+AJ18+AN18+AR18+AV18+AZ18+BD18 -> 2460.5 | BU18: =L18+P18+U18+Y18+AC18+AG18+AK18+AO18+AS18+AW18+BA18+BE18 -> 2550.5 | BV18: =(BT18-BU18) -> -90 | BW18: =(BV18)/BU18*100 -> -3.5287199 | BX18: 0 | BY18: =BX18/BH18 -> 0 | BZ18: 0 | CA18: =BZ18/BP18 -> 0 | CB18: =BH18/SUMIFS(BH$2:BH$398,G$2:G$398,G18) -> 0.13315168 | CC18: =BI18/SUMIFS(BI$2:BI$398,G$2:G$398,G18) -> 0.13675541 | CD18: =CB18-CC18 -> -0.0036037306 | CE18: =BL18/SUMIFS(BL$2:BL$398,G$2:G$398,G18) -> 0.12786657 | CF18: =BM18/SUMIFS(BM$2:BM$398,G$2:G$398,G18) -> 0.14790997 | CG18: =CE18-CF18 -> -0.020043394 | CH18: =BP18/SUMIFS(BP$2:BP$398,G$2:G$398,G18) -> 0.13540385 | CI18: =BQ18/SUMIFS(BQ$2:BQ$398,G$2:G$398,G18) -> 0.12217301 | CJ18: =CH18-CI18 -> 0.013230843 | CK18: =BT18/SUMIFS(BT$2:BT$398,G$2:G$398,G18) -> 0.13705994 | CL18: =BU18/SUMIFS(BU$2:BU$398,G$2:G$398,G18) -> 0.12203349 | CM18: =CK18-CL18 -> 0.015026445 | CN18: =COUNTIFS(G$2:G$398,G18)*CH18 -> 1.4894424 | CO18: =COUNTIFS(G$2:G$398,G18)*CK18 -> 1.5076593
A19: 112441 | B19: BPC | C19: RAJDHANI SERVICE STN.(CC 112441) | D19: SHAHDARA DELHI | E19: EAST DELHI | F19: MATTA | G19: MATTA | H19: Mayur Vihar -Anand Vihar -Preet Vihar | I19: Bhanu Pratap | J19: 640 | K19: 697.5 | L19: 280 | M19: 310.5 | N19: 702 | O19: 706.5 | P19: 270 | Q19: 337.5 | R19: 688.5 | S19: 657 | T19: 319.5 | U19: 333 | V19: 703.5 | W19: 670.5 | X19: 306.5 | Y19: 373.5 | Z19: 715.5 | AA19: 688.5 | AB19: 274.5 | AC19: 337.5 | AD19: 684 | AE19: 666 | AF19: 324 | AG19: 342 | AH19: 706.5 | AI19: 711 | AJ19: 349.5 | AK19: 387 | AL19: 675 | AM19: 652.5 | AN19: 315 | AO19: 355.5 | AP19: 643.5 | AQ19: 655.5 | AR19: 274.5 | AS19: 292.5 | AT19: 652.5 | AU19: 643.5 | AV19: 277.5 | AW19: 328.5 | AX19: 625.5 | AY19: 630 | AZ19: 292.5 | BA19: 342 | BB19: 706.5 | BC19: 666 | BD19: 301.5 | BE19: 324 | BF19: 28.625687 | BG19: 77.313728 | BH19: =BB19 -> 706.5 | BI19: =BC19 -> 666 | BJ19: =(BH19-BI19) -> 40.5 | BK19: =(BJ19)/BI19*100 -> 6.0810811 | BL19: =BD19 -> 301.5 | BM19: =BE19 -> 324 | BN19: =(BL19-BM19) -> -22.5 | BO19: =(BN19)/BM19*100 -> -6.9444444 | BP19: =K19+O19+R19+V19+Z19+AD19+AH19+AL19+AP19+AT19+AX19+BB19 -> 8205 | BQ19: =J19+N19+S19+W19+AA19+AE19+AI19+AM19+AQ19+AU19+Table1[[#This Row],[MS-0225]]+Table1[[#This Row],[MS-0325]] -> 7982.5 | BR19: =(BP19-BQ19) -> 222.5 | BS19: =(BR19)/BQ19*100 -> 2.7873473 | BT19: =M19+Q19+T19+X19+AB19+AF19+AJ19+AN19+AR19+AV19+AZ19+BD19 -> 3683 | BU19: =L19+P19+U19+Y19+AC19+AG19+AK19+AO19+AS19+AW19+BA19+BE19 -> 3965.5 | BV19: =(BT19-BU19) -> -282.5 | BW19: =(BV19)/BU19*100 -> -7.123944 | BX19: 0 | BY19: =BX19/BH19 -> 0 | BZ19: 0 | CA19: =BZ19/BP19 -> 0 | CB19: =BH19/SUMIFS(BH$2:BH$398,G$2:G$398,G19) -> 0.3087175 | CC19: =BI19/SUMIFS(BI$2:BI$398,G$2:G$398,G19) -> 0.30762125 | CD19: =CB19-CC19 -> 0.0010962534 | CE19: =BL19/SUMIFS(BL$2:BL$398,G$2:G$398,G19) -> 0.30074813 | CF19: =BM19/SUMIFS(BM$2:BM$398,G$2:G$398,G19) -> 0.35801105 | CG19: =CE19-CF19 -> -0.05726292 | CH19: =BP19/SUMIFS(BP$2:BP$398,G$2:G$398,G19) -> 0.29285791 | CI19: =BQ19/SUMIFS(BQ$2:BQ$398,G$2:G$398,G19) -> 0.30104465 | CJ19: =CH19-CI19 -> -0.0081867446 | CK19: =BT19/SUMIFS(BT$2:BT$398,G$2:G$398,G19) -> 0.31698081 | CL19: =BU19/SUMIFS(BU$2:BU$398,G$2:G$398,G19) -> 0.31199843 | CM19: =CK19-CL19 -> 0.0049823809 | CN19: =COUNTIFS(G$2:G$398,G19)*CH19 -> 1.7571474 | CO19: =COUNTIFS(G$2:G$398,G19)*CK19 -> 1.9018848
A20: 106287 | B20: IOC | C20: KHYBER SERVICE STATION | D20: RING ROAD, MOTI BAGH | E20: NEW DELHI | F20: White Patch_Moti Bagh | G20: White Patch_Moti Bagh | H20: Inner Ring Road | I20: Bhanu Pratap | J20: 614 | K20: 751 | L20: 314 | M20: 305 | N20: 704.5 | O20: 753 | P20: 299.5 | Q20: 303 | R20: 734.5 | S20: 706 | T20: 279.5 | U20: 310 | V20: 767 | W20: 704 | X20: 285 | Y20: 314 | Z20: 800.5 | AA20: 702 | AB20: 281.5 | AC20: 328 | AD20: 711.5 | AE20: 708 | AF20: 270.5 | AG20: 324 | AH20: 751 | AI20: 702 | AJ20: 279 | AK20: 270 | AL20: 752 | AM20: 738 | AN20: 270 | AO20: 260 | AP20: 651 | AQ20: 701.5 | AR20: 263 | AS20: 250.5 | AT20: 670 | AU20: 652 | AV20: 290 | AW20: 290 | AX20: 684 | AY20: 670 | AZ20: 290 | BA20: 270 | BB20: 700 | BC20: 750 | BD20: 408 | BE20: 308 | BF20: 28.5874 | BG20: 77.1713 | BH20: =BB20 -> 700 | BI20: =BC20 -> 750 | BJ20: =(BH20-BI20) -> -50 | BK20: =(BJ20)/BI20*100 -> -6.6666667 | BL20: =BD20 -> 408 | BM20: =BE20 -> 308 | BN20: =(BL20-BM20) -> 100 | BO20: =(BN20)/BM20*100 -> 32.467532 | BP20: =K20+O20+R20+V20+Z20+AD20+AH20+AL20+AP20+AT20+AX20+BB20 -> 8725.5 | BQ20: =J20+N20+S20+W20+AA20+AE20+AI20+AM20+AQ20+AU20+Table1[[#This Row],[MS-0225]]+Table1[[#This Row],[MS-0325]] -> 8352 | BR20: =(BP20-BQ20) -> 373.5 | BS20: =(BR20)/BQ20*100 -> 4.4719828 | BT20: =M20+Q20+T20+X20+AB20+AF20+AJ20+AN20+AR20+AV20+AZ20+BD20 -> 3524.5 | BU20: =L20+P20+U20+Y20+AC20+AG20+AK20+AO20+AS20+AW20+BA20+BE20 -> 3538 | BV20: =(BT20-BU20) -> -13.5 | BW20: =(BV20)/BU20*100 -> -0.38157151 | BX20: 0 | BY20: =BX20/BH20 -> 0 | BZ20: 0 | CA20: =BZ20/BP20 -> 0 | CB20: =BH20/SUMIFS(BH$2:BH$398,G$2:G$398,G20) -> 0.49928673 | CC20: =BI20/SUMIFS(BI$2:BI$398,G$2:G$398,G20) -> 0.5179558 | CD20: =CB20-CC20 -> -0.018669068 | CE20: =BL20/SUMIFS(BL$2:BL$398,G$2:G$398,G20) -> 0.64353312 | CF20: =BM20/SUMIFS(BM$2:BM$398,G$2:G$398,G20) -> 0.47678019 | CG20: =CE20-CF20 -> 0.16675294 | CH20: =BP20/SUMIFS(BP$2:BP$398,G$2:G$398,G20) -> 0.50299764 | CI20: =BQ20/SUMIFS(BQ$2:BQ$398,G$2:G$398,G20) -> 0.4969358 | CJ20: =CH20-CI20 -> 0.0060618359 | CK20: =BT20/SUMIFS(BT$2:BT$398,G$2:G$398,G20) -> 0.47596219 | CL20: =BU20/SUMIFS(BU$2:BU$398,G$2:G$398,G20) -> 0.46467034 | CM20: =CK20-CL20 -> 0.011291844 | CN20: =COUNTIFS(G$2:G$398,G20)*CH20 -> 1.5089929 | CO20: =COUNTIFS(G$2:G$398,G20)*CK20 -> 1.4278866
A21: 106344 | B21: IOC | C21: SENANI SERVICE STATION | D21: SECTOR-23, ROHINI | E21: NORTH WEST DELHI | F21: White Patch- Rohini | G21: ROHINI_SANJEEV | H21: Rohini | I21: Abhinav | J21: 669 | K21: 742.5 | L21: 165 | M21: 139.5 | N21: 728.5 | O21: 755 | P21: 177.5 | Q21: 141 | R21: 701.5 | S21: 689 | T21: 158.5 | U21: 175 | V21: 793 | W21: 748.5 | X21: 149 | Y21: 175.5 | Z21: 759 | AA21: 753.5 | AB21: 149 | AC21: 172.5 | AD21: 737 | AE21: 713 | AF21: 159 | AG21: 169 | AH21: 816 | AI21: 753.5 | AJ21: 144 | AK21: 188.5 | AL21: 727 | AM21: 706.5 | AN21: 145 | AO21: 121.5 | AP21: 717 | AQ21: 690.5 | AR21: 135 | AS21: 119.5 | AT21: 717 | AU21: 684.5 | AV21: 167 | AW21: 173.5 | AX21: 725 | AY21: 676.5 | AZ21: 163 | BA21: 157.5 | BB21: 831.5 | BC21: 729.5 | BD21: 222.5 | BE21: 134.5 | BF21: 28.7183 | BG21: 77.0711 | BH21: =BB21 -> 831.5 | BI21: =BC21 -> 729.5 | BJ21: =(BH21-BI21) -> 102 | BK21: =(BJ21)/BI21*100 -> 13.98218 | BL21: =BD21 -> 222.5 | BM21: =BE21 -> 134.5 | BN21: =(BL21-BM21) -> 88 | BO21: =(BN21)/BM21*100 -> 65.427509 | BP21: =K21+O21+R21+V21+Z21+AD21+AH21+AL21+AP21+AT21+AX21+BB21 -> 9021.5 | BQ21: =J21+N21+S21+W21+AA21+AE21+AI21+AM21+AQ21+AU21+Table1[[#This Row],[MS-0225]]+Table1[[#This Row],[MS-0325]] -> 8542.5 | BR21: =(BP21-BQ21) -> 479 | BS21: =(BR21)/BQ21*100 -> 5.6072578 | BT21: =M21+Q21+T21+X21+AB21+AF21+AJ21+AN21+AR21+AV21+AZ21+BD21 -> 1872.5 | BU21: =L21+P21+U21+Y21+AC21+AG21+AK21+AO21+AS21+AW21+BA21+BE21 -> 1929.5 | BV21: =(BT21-BU21) -> -57 | BW21: =(BV21)/BU21*100 -> -2.9541332 | BX21: 0 | BY21: =BX21/BH21 -> 0 | BZ21: 0 | CA21: =BZ21/BP21 -> 0 | CB21: =BH21/SUMIFS(BH$2:BH$398,G$2:G$398,G21) -> 0.32652661 | CC21: =BI21/SUMIFS(BI$2:BI$398,G$2:G$398,G21) -> 0.37162506 | CD21: =CB21-CC21 -> -0.045098459 | CE21: =BL21/SUMIFS(BL$2:BL$398,G$2:G$398,G21) -> 0.5771725 | CF21: =BM21/SUMIFS(BM$2:BM$398,G$2:G$398,G21) -> 0.44684385 | CG21: =CE21-CF21 -> 0.13032865 | CH21: =BP21/SUMIFS(BP$2:BP$398,G$2:G$398,G21) -> 0.3230907 | CI21: =BQ21/SUMIFS(BQ$2:BQ$398,G$2:G$398,G21) -> 0.32827992 | CJ21: =CH21-CI21 -> -0.0051892194 | CK21: =BT21/SUMIFS(BT$2:BT$398,G$2:G$398,G21) -> 0.46194647 | CL21: =BU21/SUMIFS(BU$2:BU$398,G$2:G$398,G21) -> 0.44002281 | CM21: =CK21-CL21 -> 0.021923661 | CN21: =COUNTIFS(G$2:G$398,G21)*CH21 -> 2.2616349 | CO21: =COUNTIFS(G$2:G$398,G21)*CK21 -> 3.2336253
A22: 234809 | B22: IOC | C22: SHRI SAI FILLING STATION | D22: PUNJAB KHOD, DELHI | E22: NORTH WEST DELHI | F22: PUNJABKHOR | G22: PUNJABKHOR | H22: Punjabkhor | I22: Abhinav | J22: 76 | K22: 76 | L22: 92 | M22: 92 | N22: 80 | O22: 84 | P22: 88 | Q22: 84 | R22: 76 | S22: 76 | T22: 80 | U22: 68 | V22: 92 | W22: 84 | X22: 76 | Y22: 96 | Z22: 80 | AA22: 77.5 | AB22: 64 | AC22: 60.5 | AD22: 76 | AE22: 79.5 | AF22: 128 | AG22: 104.5 | AH22: 88 | AI22: 74 | AJ22: 104 | AK22: 130 | AL22: 80 | AM22: 92 | AN22: 76 | AO22: 88 | AP22: 72 | AQ22: 67 | AR22: 60 | AS22: 55 | AT22: 76 | AU22: 76.5 | AV22: 68 | AW22: 61.5 | AX22: 72 | AY22: 64 | AZ22: 60 | BA22: 68 | BB22: 80 | BC22: 77 | BD22: 136 | BE22: 73 | BF22: 28.7667 | BG22: 76.9647 | BH22: =BB22 -> 80 | BI22: =BC22 -> 77 | BJ22: =(BH22-BI22) -> 3 | BK22: =(BJ22)/BI22*100 -> 3.8961039 | BL22: =BD22 -> 136 | BM22: =BE22 -> 73 | BN22: =(BL22-BM22) -> 63 | BO22: =(BN22)/BM22*100 -> 86.30137 | BP22: =K22+O22+R22+V22+Z22+AD22+AH22+AL22+AP22+AT22+AX22+BB22 -> 952 | BQ22: =J22+N22+S22+W22+AA22+AE22+AI22+AM22+AQ22+AU22+Table1[[#This Row],[MS-0225]]+Table1[[#This Row],[MS-0325]] -> 923.5 | BR22: =(BP22-BQ22) -> 28.5 | BS22: =(BR22)/BQ22*100 -> 3.0860855 | BT22: =M22+Q22+T22+X22+AB22+AF22+AJ22+AN22+AR22+AV22+AZ22+BD22 -> 1028 | BU22: =L22+P22+U22+Y22+AC22+AG22+AK22+AO22+AS22+AW22+BA22+BE22 -> 984.5 | BV22: =(BT22-BU22) -> 43.5 | BW22: =(BV22)/BU22*100 -> 4.4184865 | BX22: 0 | BY22: =BX22/BH22 -> 0 | BZ22: 0 | CA22: =BZ22/BP22 -> 0 | CB22: =BH22/SUMIFS(BH$2:BH$398,G$2:G$398,G22) -> 0.76923077 | CC22: =BI22/SUMIFS(BI$2:BI$398,G$2:G$398,G22) -> 0.70642202 | CD22: =CB22-CC22 -> 0.062808751 | CE22: =BL22/SUMIFS(BL$2:BL$398,G$2:G$398,G22) -> 0.91891892 | CF22: =BM22/SUMIFS(BM$2:BM$398,G$2:G$398,G22) -> 0.72277228 | CG22: =CE22-CF22 -> 0.19614664 | CH22: =BP22/SUMIFS(BP$2:BP$398,G$2:G$398,G22) -> 0.73769857 | CI22: =BQ22/SUMIFS(BQ$2:BQ$398,G$2:G$398,G22) -> 0.74898621 | CJ22: =CH22-CI22 -> -0.011287646 | CK22: =BT22/SUMIFS(BT$2:BT$398,G$2:G$398,G22) -> 0.84021251 | CL22: =BU22/SUMIFS(BU$2:BU$398,G$2:G$398,G22) -> 0.79845904 | CM22: =CK22-CL22 -> 0.041753462 | CN22: =COUNTIFS(G$2:G$398,G22)*CH22 -> 1.4753971 | CO22: =COUNTIFS(G$2:G$398,G22)*CK22 -> 1.680425
... A55: 107629 | B55: IOC | C55: DELHI AUTOMOBILES LTD | D55: SARITA VIHAR | E55: SOUTH EAST DELHI | F55: AUTO REST_OKHLA | G55: AUTO REST_OKHLA | H55: Okhla | I55: Bhanu Pratap | J55: 553.5 | K55: 513 | L55: 220.5 | M55: 153 | N55: 603 | O55: 558 | P55: 225 | Q55: 162 | R55: 526.5 | S55: 625.5 | T55: 139.5 | U55: 220.5 | V55: 553.5 | W55: 608 | X55: 148.5 | Y55: 216 | Z55: 558 | AA55: 612 | AB55: 144 | AC55: 198 | AD55: 504 | AE55: 545 | AF55: 144 | AG55: 189 | AH55: 549 | AI55: 627.5 | AJ55: 171 | AK55: 202.5 | AL55: 558 | AM55: 553.5 | AN55: 162 | AO55: 148.5 | AP55: 522 | AQ55: 497 | AR55: 144 | AS55: 153 | AT55: 508.5 | AU55: 506 | AV55: 139.5 | AW55: 144 | AX55: 513 | AY55: 524 | AZ55: 153 | BA55: 162 | BB55: 562.5 | BC55: 485.5 | BD55: 139.5 | BE55: 148.5 | BF55: 28.5381 | BG55: 77.2902 | BH55: =BB55 -> 562.5 | BI55: =BC55 -> 485.5 | BJ55: =(BH55-BI55) -> 77 | BK55: =(BJ55)/BI55*100 -> 15.859938 | BL55: =BD55 -> 139.5 | BM55: =BE55 -> 148.5 | BN55: =(BL55-BM55) -> -9 | BO55: =(BN55)/BM55*100 -> -6.0606061 | BP55: =K55+O55+R55+V55+Z55+AD55+AH55+AL55+AP55+AT55+AX55+BB55 -> 6426 | BQ55: =J55+N55+S55+W55+AA55+AE55+AI55+AM55+AQ55+AU55+Table1[[#This Row],[MS-0225]]+Table1[[#This Row],[MS-0325]] -> 6740.5 | BR55: =(BP55-BQ55) -> -314.5 | BS55: =(BR55)/BQ55*100 -> -4.665826 | BT55: =M55+Q55+T55+X55+AB55+AF55+AJ55+AN55+AR55+AV55+AZ55+BD55 -> 1800 | BU55: =L55+P55+U55+Y55+AC55+AG55+AK55+AO55+AS55+AW55+BA55+BE55 -> 2227.5 | BV55: =(BT55-BU55) -> -427.5 | BW55: =(BV55)/BU55*100 -> -19.191919 | BX55: 0 | BY55: =BX55/BH55 -> 0 | BZ55: 0 | CA55: =BZ55/BP55 -> 0 | CB55: =BH55/SUMIFS(BH$2:BH$398,G$2:G$398,G55) -> 0.10217984 | CC55: =BI55/SUMIFS(BI$2:BI$398,G$2:G$398,G55) -> 0.092989849 | CD55: =CB55-CC55 -> 0.0091899878 | CE55: =BL55/SUMIFS(BL$2:BL$398,G$2:G$398,G55) -> 0.096942321 | CF55: =BM55/SUMIFS(BM$2:BM$398,G$2:G$398,G55) -> 0.095498392 | CG55: =CE55-CF55 -> 0.0014439288 | CH55: =BP55/SUMIFS(BP$2:BP$398,G$2:G$398,G55) -> 0.10006384 | CI55: =BQ55/SUMIFS(BQ$2:BQ$398,G$2:G$398,G55) -> 0.10567946 | CJ55: =CH55-CI55 -> -0.0056156134 | CK55: =BT55/SUMIFS(BT$2:BT$398,G$2:G$398,G55) -> 0.10026738 | CL55: =BU55/SUMIFS(BU$2:BU$398,G$2:G$398,G55) -> 0.10657895 | CM55: =CK55-CL55 -> -0.0063115677 | CN55: =COUNTIFS(G$2:G$398,G55)*CH55 -> 1.1007023 | CO55: =COUNTIFS(G$2:G$398,G55)*CK55 -> 1.1029412
A56: 41056544 | B56: HPC | C56: NARAYAN SERVICE STATION | D56: KHYBER PASS | E56: CENTRAL DELHI | F56: RAJINDER-RS BHOLA | G56: White Patch- Naraina | H56: Ashok Vihar | I56: Abhinav | J56: 326 | K56: 446 | L56: 310 | M56: 301 | N56: 403 | O56: 486.5 | P56: 279 | Q56: 273.5 | R56: 451 | S56: 449 | T56: 314 | U56: 294 | V56: 489.5 | W56: 437 | X56: 212.5 | Y56: 202 | Z56: 507.5 | AA56: 457.5 | AB56: 198.5 | AC56: 265.5 | AD56: 492 | AE56: 442 | AF56: 184 | AG56: 264 | AH56: 492 | AI56: 477 | AJ56: 201 | AK56: 297 | AL56: 476 | AM56: 430 | AN56: 179 | AO56: 346 | AP56: 443 | AQ56: 420 | AR56: 182 | AS56: 280 | AT56: 365 | AU56: 392.5 | AV56: 195 | AW56: 266.5 | AX56: 395 | AY56: 415 | AZ56: 207 | BA56: 318 | BB56: 387 | BC56: 458 | BD56: 254 | BE56: 292 | BF56: 28.69301 | BG56: 77.22077 | BH56: =BB56 -> 387 | BI56: =BC56 -> 458 | BJ56: =(BH56-BI56) -> -71 | BK56: =(BJ56)/BI56*100 -> -15.502183 | BL56: =BD56 -> 254 | BM56: =BE56 -> 292 | BN56: =(BL56-BM56) -> -38 | BO56: =(BN56)/BM56*100 -> -13.013699 | BP56: =K56+O56+R56+V56+Z56+AD56+AH56+AL56+AP56+AT56+AX56+BB56 -> 5430.5 | BQ56: =J56+N56+S56+W56+AA56+AE56+AI56+AM56+AQ56+AU56+Table1[[#This Row],[MS-0225]]+Table1[[#This Row],[MS-0325]] -> 5107 | BR56: =(BP56-BQ56) -> 323.5 | BS56: =(BR56)/BQ56*100 -> 6.3344429 | BT56: =M56+Q56+T56+X56+AB56+AF56+AJ56+AN56+AR56+AV56+AZ56+BD56 -> 2701.5 | BU56: =L56+P56+U56+Y56+AC56+AG56+AK56+AO56+AS56+AW56+BA56+BE56 -> 3414 | BV56: =(BT56-BU56) -> -712.5 | BW56: =(BV56)/BU56*100 -> -20.869947 | BX56: 0 | BY56: =BX56/BH56 -> 0 | BZ56: 0 | CA56: =BZ56/BP56 -> 0 | CB56: =BH56/SUMIFS(BH$2:BH$398,G$2:G$398,G56) -> 0.56127629 | CC56: =BI56/SUMIFS(BI$2:BI$398,G$2:G$398,G56) -> 0.60104987 | CD56: =CB56-CC56 -> -0.039773582 | CE56: =BL56/SUMIFS(BL$2:BL$398,G$2:G$398,G56) -> 0.29381145 | CF56: =BM56/SUMIFS(BM$2:BM$398,G$2:G$398,G56) -> 0.33524684 | CG56: =CE56-CF56 -> -0.041435391 | CH56: =BP56/SUMIFS(BP$2:BP$398,G$2:G$398,G56) -> 0.59434169 | CI56: =BQ56/SUMIFS(BQ$2:BQ$398,G$2:G$398,G56) -> 0.59006355 | CJ56: =CH56-CI56 -> 0.0042781406 | CK56: =BT56/SUMIFS(BT$2:BT$398,G$2:G$398,G56) -> 0.26789964 | CL56: =BU56/SUMIFS(BU$2:BU$398,G$2:G$398,G56) -> 0.35729984 | CM56: =CK56-CL56 -> -0.0894002 | CN56: =COUNTIFS(G$2:G$398,G56)*CH56 -> 1.1886834 | CO56: =COUNTIFS(G$2:G$398,G56)*CK56 -> 0.53579929 | CP56: =BD56-AZ56 -> 47
A57: 41019252 | B57: HPC | C57: BHARAT HP CENTRE | D57: DWARKA(COMM.ON31.03.09) | E57: SOUTH WEST DELHI | F57: BS DWARKA | G57: BS DWARKA | H57: Dwarka | I57: Raj Doshi | J57: 463.5 | K57: 536 | L57: 112.5 | M57: 103 | N57: 522 | O57: 560 | P57: 126 | Q57: 122 | R57: 550 | S57: 495 | T57: 110 | U57: 117 | V57: 599 | W57: 567 | X57: 105 | Y57: 117 | Z57: 594 | AA57: 563 | AB57: 106 | AC57: 117 | AD57: 561 | AE57: 531 | AF57: 104 | AG57: 117 | AH57: 583 | AI57: 576 | AJ57: 99 | AK57: 126 | AL57: 547 | AM57: 514.5 | AN57: 91 | AO57: 88.5 | AP57: 527 | AQ57: 487 | AR57: 89 | AS57: 81 | AT57: 518 | AU57: 491 | AV57: 98 | AW57: 103 | AX57: 504 | AY57: 481 | AZ57: 90 | BA57: 91 | BB57: 557 | BC57: 529 | BD57: 105 | BE57: 109 | BF57: 28.593462 | BG57: 77.043284 | BH57: =BB57 -> 557 | BI57: =BC57 -> 529 | BJ57: =(BH57-BI57) -> 28 | BK57: =(BJ57)/BI57*100 -> 5.2930057 | BL57: =BD57 -> 105 | BM57: =BE57 -> 109 | BN57: =(BL57-BM57) -> -4 | BO57: =(BN57)/BM57*100 -> -3.6697248 | BP57: =K57+O57+R57+V57+Z57+AD57+AH57+AL57+AP57+AT57+AX57+BB57 -> 6636 | BQ57: =J57+N57+S57+W57+AA57+AE57+AI57+AM57+AQ57+AU57+Table1[[#This Row],[MS-0225]]+Table1[[#This Row],[MS-0325]] -> 6220 | BR57: =(BP57-BQ57) -> 416 | BS57: =(BR57)/BQ57*100 -> 6.6881029 | BT57: =M57+Q57+T57+X57+AB57+AF57+AJ57+AN57+AR57+AV57+AZ57+BD57 -> 1222 | BU57: =L57+P57+U57+Y57+AC57+AG57+AK57+AO57+AS57+AW57+BA57+BE57 -> 1305 | BV57: =(BT57-BU57) -> -83 | BW57: =(BV57)/BU57*100 -> -6.3601533 | BX57: 0 | BY57: =BX57/BH57 -> 0 | BZ57: 0 | CA57: =BZ57/BP57 -> 0 | CB57: =BH57/SUMIFS(BH$2:BH$398,G$2:G$398,G57) -> 0.32048331 | CC57: =BI57/SUMIFS(BI$2:BI$398,G$2:G$398,G57) -> 0.34417697 | CD57: =CB57-CC57 -> -0.023693654 | CE57: =BL57/SUMIFS(BL$2:BL$398,G$2:G$398,G57) -> 0.32407407 | CF57: =BM57/SUMIFS(BM$2:BM$398,G$2:G$398,G57) -> 0.35737705 | CG57: =CE57-CF57 -> -0.033302975 | CH57: =BP57/SUMIFS(BP$2:BP$398,G$2:G$398,G57) -> 0.33434099 | CI57: =BQ57/SUMIFS(BQ$2:BQ$398,G$2:G$398,G57) -> 0.34437893 | CJ57: =CH57-CI57 -> -0.010037936 | CK57: =BT57/SUMIFS(BT$2:BT$398,G$2:G$398,G57) -> 0.33188485 | CL57: =BU57/SUMIFS(BU$2:BU$398,G$2:G$398,G57) -> 0.34693606 | CM57: =CK57-CL57 -> -0.015051218 | CN57: =COUNTIFS(G$2:G$398,G57)*CH57 -> 1.337364 | CO57: =COUNTIFS(G$2:G$398,G57)*CK57 -> 1.3275394
A58: 106315 | B58: IOC | C58: PRAGATI | D58: MINTO ROAD | E58: CENTRAL DELHI | F58: KRISHNA-RAIZADA | G58: KRISHNA-RAIZADA | H58: Old Delhi | I58: Abhinav | J58: 148.5 | K58: 171 | L58: 31.5 | M58: 27 | N58: 148.5 | O58: 175.5 | P58: 31.5 | Q58: 22.5 | R58: 171 | S58: 144 | T58: 27 | U58: 36 | V58: 171 | W58: 173 | X58: 45 | Y58: 45 | Z58: 189 | AA58: 156 | AB58: 45 | AC58: 28 | AD58: 180 | AE58: 154 | AF58: 36 | AG58: 28 | AH58: 171 | AI58: 174 | AJ58: 45 | AK58: 32 | AL58: 180 | AM58: 173 | AN58: 72 | AO58: 45 | AP58: 171 | AQ58: 162 | AR58: 27 | AS58: 30 | AT58: 171 | AU58: 157.5 | AV58: 27 | AW58: 22.5 | AX58: 180 | AY58: 126 | AZ58: 36 | BA58: 36 | BB58: 171 | BC58: 169.5 | BD58: 63 | BE58: 22.5 | BF58: 28.6413 | BG58: 77.2289 | BH58: =BB58 -> 171 | BI58: =BC58 -> 169.5 | BJ58: =(BH58-BI58) -> 1.5 | BK58: =(BJ58)/BI58*100 -> 0.88495575 | BL58: =BD58 -> 63 | BM58: =BE58 -> 22.5 | BN58: =(BL58-BM58) -> 40.5 | BO58: =(BN58)/BM58*100 -> 180 | BP58: =K58+O58+R58+V58+Z58+AD58+AH58+AL58+AP58+AT58+AX58+BB58 -> 2101.5 | BQ58: =J58+N58+S58+W58+AA58+AE58+AI58+AM58+AQ58+AU58+Table1[[#This Row],[MS-0225]]+Table1[[#This Row],[MS-0325]] -> 1886 | BR58: =(BP58-BQ58) -> 215.5 | BS58: =(BR58)/BQ58*100 -> 11.426299 | BT58: =M58+Q58+T58+X58+AB58+AF58+AJ58+AN58+AR58+AV58+AZ58+BD58 -> 472.5 | BU58: =L58+P58+U58+Y58+AC58+AG58+AK58+AO58+AS58+AW58+BA58+BE58 -> 388 | BV58: =(BT58-BU58) -> 84.5 | BW58: =(BV58)/BU58*100 -> 21.778351 | BX58: 0 | BY58: =BX58/BH58 -> 0 | BZ58: 0 | CA58: =BZ58/BP58 -> 0 | CB58: =BH58/SUMIFS(BH$2:BH$398,G$2:G$398,G58) -> 0.11902135 | CC58: =BI58/SUMIFS(BI$2:BI$398,G$2:G$398,G58) -> 0.1202764 | CD58: =CB58-CC58 -> -0.0012550494 | CE58: =BL58/SUMIFS(BL$2:BL$398,G$2:G$398,G58) -> 0.16392206 | CF58: =BM58/SUMIFS(BM$2:BM$398,G$2:G$398,G58) -> 0.06846939 | CG58: =CE58-CF58 -> 0.095452667 | CH58: =BP58/SUMIFS(BP$2:BP$398,G$2:G$398,G58) -> 0.12183884 | CI58: =BQ58/SUMIFS(BQ$2:BQ$398,G$2:G$398,G58) -> 0.11522902 | CJ58: =CH58-CI58 -> 0.0066098253 | CK58: =BT58/SUMIFS(BT$2:BT$398,G$2:G$398,G58) -> 0.11621512 | CL58: =BU58/SUMIFS(BU$2:BU$398,G$2:G$398,G58) -> 0.097411515 | CM58: =CK58-CL58 -> 0.018803606 | CN58: =COUNTIFS(G$2:G$398,G58)*CH58 -> 0.73103306 | CO58: =COUNTIFS(G$2:G$398,G58)*CK58 -> 0.69729072
A59: 112387 | B59: BPC | C59: ANUP SERVICE STATION | D59: ALAKNANDA | E59: SOUTH EAST DELHI | F59: AIRPORT_SINGH_ANUP | G59: AIRPORT_SINGH_ANUP | H59: Greater Kailash I &II | I59: Bhanu Pratap | J59: 495.00001 | K59: 553.5 | L59: 99 | M59: 76.5 | N59: 576.00001 | O59: 562.5 | P59: 126 | Q59: 85.5 | R59: 513 | S59: 513.00001 | T59: 99 | U59: 117 | V59: 612 | W59: 583.5 | X59: 90 | Y59: 112.5 | Z59: 612 | AA59: 584.5 | AB59: 90 | AC59: 111.5 | AD59: 576 | AE59: 549 | AF59: 90 | AG59: 99 | AH59: 571.5 | AI59: 563 | AJ59: 88.5 | AK59: 117 | AL59: 522 | AM59: 486.00001 | AN59: 66 | AO59: 72 | AP59: 513 | AQ59: 499.5 | AR59: 63 | AS59: 76.5 | AT59: 516.5 | AU59: 490.5 | AV59: 89.5 | AW59: 85.5 | AX59: 490.5 | AY59: 459 | AZ59: 49.5 | BA59: 81 | BB59: 553 | BC59: 504 | BD59: 89 | BE59: 102 | BF59: 28.53108 | BG59: 77.25093 | BH59: =BB59 -> 553 | BI59: =BC59 -> 504 | BJ59: =(BH59-BI59) -> 49 | BK59: =(BJ59)/BI59*100 -> 9.7222222 | BL59: =BD59 -> 89 | BM59: =BE59 -> 102 | BN59: =(BL59-BM59) -> -13 | BO59: =(BN59)/BM59*100 -> -12.745098 | BP59: =K59+O59+R59+V59+Z59+AD59+AH59+AL59+AP59+AT59+AX59+BB59 -> 6595.5 | BQ59: =J59+N59+S59+W59+AA59+AE59+AI59+AM59+AQ59+AU59+Table1[[#This Row],[MS-0225]]+Table1[[#This Row],[MS-0325]] -> 6303 | BR59: =(BP59-BQ59) -> 292.49996 | BS59: =(BR59)/BQ59*100 -> 4.6406467 | BT59: =M59+Q59+T59+X59+AB59+AF59+AJ59+AN59+AR59+AV59+AZ59+BD59 -> 976.5 | BU59: =L59+P59+U59+Y59+AC59+AG59+AK59+AO59+AS59+AW59+BA59+BE59 -> 1199 | BV59: =(BT59-BU59) -> -222.5 | BW59: =(BV59)/BU59*100 -> -18.557131 | BX59: 63 | BY59: =BX59/BH59 -> 0.11392405 | BZ59: 373.5 | CA59: =BZ59/BP59 -> 0.05662952 | CB59: =BH59/SUMIFS(BH$2:BH$398,G$2:G$398,G59) -> 0.26503714 | CC59: =BI59/SUMIFS(BI$2:BI$398,G$2:G$398,G59) -> 0.25806452 | CD59: =CB59-CC59 -> 0.0069726274 | CE59: =BL59/SUMIFS(BL$2:BL$398,G$2:G$398,G59) -> 0.22057001 | CF59: =BM59/SUMIFS(BM$2:BM$398,G$2:G$398,G59) -> 0.23448276 | CG59: =CE59-CF59 -> -0.013912746 | CH59: =BP59/SUMIFS(BP$2:BP$398,G$2:G$398,G59) -> 0.26982633 | CI59: =BQ59/SUMIFS(BQ$2:BQ$398,G$2:G$398,G59) -> 0.26512156 | CJ59: =CH59-CI59 -> 0.0047047719 | CK59: =BT59/SUMIFS(BT$2:BT$398,G$2:G$398,G59) -> 0.21198307 | CL59: =BU59/SUMIFS(BU$2:BU$398,G$2:G$398,G59) -> 0.21510585 | CM59: =CK59-CL59 -> -0.0031227812 | CN59: =COUNTIFS(G$2:G$398,G59)*CH59 -> 1.3491317 | CO59: =COUNTIFS(G$2:G$398,G59)*CK59 -> 1.0599153
A60: 106321 | B60: IOC | C60: QUTAB SERVICE STATION | D60: MEHRAULI ROAD | E60: SOUTH DELHI | F60: BSGS | G60: BSGS | H60: Hauj Khas-Saket-Vasant Kunj | I60: Raj Doshi | J60: 548 | K60: 576 | L60: 166 | M60: 150 | N60: 580.5 | O60: 577 | P60: 193.5 | Q60: 169 | R60: 563 | S60: 584.5 | T60: 145 | U60: 193.5 | V60: 621 | W60: 594 | X60: 163 | Y60: 234 | Z60: 595 | AA60: 594 | AB60: 135 | AC60: 180 | AD60: 561 | AE60: 544.5 | AF60: 139 | AG60: 177.5 | AH60: 575 | AI60: 582.5 | AJ60: 151 | AK60: 175.5 | AL60: 546 | AM60: 540 | AN60: 118 | AO60: 184.5 | AP60: 553 | AQ60: 540 | AR60: 133 | AS60: 144 | AT60: 514 | AU60: 501.5 | AV60: 102 | AW60: 130.5 | AX60: 512 | AY60: 495 | AZ60: 130 | BA60: 187 | BB60: 538 | BC60: 533 | BD60: 126 | BE60: 171 | BF60: 28.5345 | BG60: 77.1964 | BH60: =BB60 -> 538 | BI60: =BC60 -> 533 | BJ60: =(BH60-BI60) -> 5 | BK60: =(BJ60)/BI60*100 -> 0.9380863 | BL60: =BD60 -> 126 | BM60: =BE60 -> 171 | BN60: =(BL60-BM60) -> -45 | BO60: =(BN60)/BM60*100 -> -26.315789 | BP60: =K60+O60+R60+V60+Z60+AD60+AH60+AL60+AP60+AT60+AX60+BB60 -> 6731 | BQ60: =J60+N60+S60+W60+AA60+AE60+AI60+AM60+AQ60+AU60+Table1[[#This Row],[MS-0225]]+Table1[[#This Row],[MS-0325]] -> 6637.5 | BR60: =(BP60-BQ60) -> 93.5 | BS60: =(BR60)/BQ60*100 -> 1.4086629 | BT60: =M60+Q60+T60+X60+AB60+AF60+AJ60+AN60+AR60+AV60+AZ60+BD60 -> 1661 | BU60: =L60+P60+U60+Y60+AC60+AG60+AK60+AO60+AS60+AW60+BA60+BE60 -> 2137 | BV60: =(BT60-BU60) -> -476 | BW60: =(BV60)/BU60*100 -> -22.274216 | BX60: 0 | BY60: =BX60/BH60 -> 0 | BZ60: 0 | CA60: =BZ60/BP60 -> 0 | CB60: =BH60/SUMIFS(BH$2:BH$398,G$2:G$398,G60) -> 0.32754947 | CC60: =BI60/SUMIFS(BI$2:BI$398,G$2:G$398,G60) -> 0.35158311 | CD60: =CB60-CC60 -> -0.024033646 | CE60: =BL60/SUMIFS(BL$2:BL$398,G$2:G$398,G60) -> 0.30920245 | CF60: =BM60/SUMIFS(BM$2:BM$398,G$2:G$398,G60) -> 0.37831858 | CG60: =CE60-CF60 -> -0.06911613 | CH60: =BP60/SUMIFS(BP$2:BP$398,G$2:G$398,G60) -> 0.34983498 | CI60: =BQ60/SUMIFS(BQ$2:BQ$398,G$2:G$398,G60) -> 0.36202242 | CJ60: =CH60-CI60 -> -0.012187433 | CK60: =BT60/SUMIFS(BT$2:BT$398,G$2:G$398,G60) -> 0.36003035 | CL60: =BU60/SUMIFS(BU$2:BU$398,G$2:G$398,G60) -> 0.39765538 | CM60: =CK60-CL60 -> -0.037625032 | CN60: =COUNTIFS(G$2:G$398,G60)*CH60 -> 1.049505 | CO60: =COUNTIFS(G$2:G$398,G60)*CK60 -> 1.080091
A61: 106323 | B61: IOC | C61: R.K.AMAR SAHEED SERVICE STATION | D61: ROHINI, SECTOR-6 | E61: NORTH WEST DELHI | F61: M.L.SETHI | G61: M.L.SETHI | H61: Rohini | I61: Abhinav | J61: 108 | K61: 127.5 | L61: 144 | M61: 132.5 | N61: 130.5 | O61: 126.5 | P61: 193.5 | Q61: 173.5 | R61: 129 | S61: 117.5 | T61: 99 | U61: 220.5 | V61: 134.5 | W61: 133.5 | X61: 141.5 | Y61: 186.5 | Z61: 131 | AA61: 130.5 | AB61: 115 | AC61: 193.5 | AD61: 121.5 | AE61: 130 | AF61: 130.5 | AG61: 168 | AH61: 154 | AI61: 128.5 | AJ61: 128 | AK61: 123.5 | AL61: 125.5 | AM61: 123.5 | AN61: 120.5 | AO61: 94.5 | AP61: 124.5 | AQ61: 116.5 | AR61: 129.5 | AS61: 93.5 | AT61: 113 | AU61: 123 | AV61: 127 | AW61: 111 | AX61: 123 | AY61: 110.5 | AZ61: 141 | BA61: 153.5 | BB61: 130 | BC61: 116.5 | BD61: 164 | BE61: 123.5 | BF61: 28.7115 | BG61: 77.1101 | BH61: =BB61 -> 130 | BI61: =BC61 -> 116.5 | BJ61: =(BH61-BI61) -> 13.5 | BK61: =(BJ61)/BI61*100 -> 11.587983 | BL61: =BD61 -> 164 | BM61: =BE61 -> 123.5 | BN61: =(BL61-BM61) -> 40.5 | BO61: =(BN61)/BM61*100 -> 32.793522 | BP61: =K61+O61+R61+V61+Z61+AD61+AH61+AL61+AP61+AT61+AX61+BB61 -> 1540 | BQ61: =J61+N61+S61+W61+AA61+AE61+AI61+AM61+AQ61+AU61+Table1[[#This Row],[MS-0225]]+Table1[[#This Row],[MS-0325]] -> 1468.5 | BR61: =(BP61-BQ61) -> 71.5 | BS61: =(BR61)/BQ61*100 -> 4.8689139 | BT61: =M61+Q61+T61+X61+AB61+AF61+AJ61+AN61+AR61+AV61+AZ61+BD61 -> 1602 | BU61: =L61+P61+U61+Y61+AC61+AG61+AK61+AO61+AS61+AW61+BA61+BE61 -> 1805.5 | BV61: =(BT61-BU61) -> -203.5 | BW61: =(BV61)/BU61*100 -> -11.271116 | BX61: 0 | BY61: =BX61/BH61 -> 0 | BZ61: 0 | CA61: =BZ61/BP61 -> 0 | CB61: =BH61/SUMIFS(BH$2:BH$398,G$2:G$398,G61) -> 0.042407438 | CC61: =BI61/SUMIFS(BI$2:BI$398,G$2:G$398,G61) -> 0.044279742 | CD61: =CB61-CC61 -> -0.0018723039 | CE61: =BL61/SUMIFS(BL$2:BL$398,G$2:G$398,G61) -> 0.15716339 | CF61: =BM61/SUMIFS(BM$2:BM$398,G$2:G$398,G61) -> 0.12251984 | CG61: =CE61-CF61 -> 0.034643551 | CH61: =BP61/SUMIFS(BP$2:BP$398,G$2:G$398,G61) -> 0.043960436 | CI61: =BQ61/SUMIFS(BQ$2:BQ$398,G$2:G$398,G61) -> 0.046653853 | CJ61: =CH61-CI61 -> -0.0026934173 | CK61: =BT61/SUMIFS(BT$2:BT$398,G$2:G$398,G61) -> 0.13648562 | CL61: =BU61/SUMIFS(BU$2:BU$398,G$2:G$398,G61) -> 0.13893271 | CM61: =CK61-CL61 -> -0.0024470845 | CN61: =COUNTIFS(G$2:G$398,G61)*CH61 -> 0.39564392 | CO61: =COUNTIFS(G$2:G$398,G61)*CK61 -> 1.2283706
A62: 106353 | B62: IOC | C62: SHIVALIK SERVICE CENTRE | D62: SECTOR-2, DWARKA | E62: SOUTH WEST DELHI | F62: SHIV SS | G62: SHIV SS | H62: Dwarka | I62: Raj Doshi | J62: 472.5 | K62: 502.5 | L62: 85.5 | M62: 67.5 | N62: 490.5 | O62: 488 | P62: 85.5 | Q62: 72 | R62: 454.5 | S62: 468 | T62: 67.5 | U62: 72 | V62: 499.5 | W62: 477 | X62: 58.5 | Y62: 81 | Z62: 499.5 | AA62: 472.5 | AB62: 58.5 | AC62: 67.5 | AD62: 477 | AE62: 432 | AF62: 63 | AG62: 72 | AH62: 522 | AI62: 499.5 | AJ62: 54 | AK62: 66.5 | AL62: 481.5 | AM62: 465 | AN62: 58.5 | AO62: 59 | AP62: 468 | AQ62: 414 | AR62: 54 | AS62: 54 | AT62: 463.5 | AU62: 445.5 | AV62: 58.5 | AW62: 58.5 | AX62: 450 | AY62: 406.5 | AZ62: 54 | BA62: 63.5 | BB62: 526.5 | BC62: 468 | BD62: 67.5 | BE62: 72 | BF62: 28.5978 | BG62: 77.0649 | BH62: =BB62 -> 526.5 | BI62: =BC62 -> 468 | BJ62: =(BH62-BI62) -> 58.5 | BK62: =(BJ62)/BI62*100 -> 12.5 | BL62: =BD62 -> 67.5 | BM62: =BE62 -> 72 | BN62: =(BL62-BM62) -> -4.5 | BO62: =(BN62)/BM62*100 -> -6.25 | BP62: =K62+O62+R62+V62+Z62+AD62+AH62+AL62+AP62+AT62+AX62+BB62 -> 5832.5 | BQ62: =J62+N62+S62+W62+AA62+AE62+AI62+AM62+AQ62+AU62+Table1[[#This Row],[MS-0225]]+Table1[[#This Row],[MS-0325]] -> 5511 | BR62: =(BP62-BQ62) -> 321.5 | BS62: =(BR62)/BQ62*100 -> 5.833787 | BT62: =M62+Q62+T62+X62+AB62+AF62+AJ62+AN62+AR62+AV62+AZ62+BD62 -> 733.5 | BU62: =L62+P62+U62+Y62+AC62+AG62+AK62+AO62+AS62+AW62+BA62+BE62 -> 837 | BV62: =(BT62-BU62) -> -103.5 | BW62: =(BV62)/BU62*100 -> -12.365591 | BX62: 0 | BY62: =BX62/BH62 -> 0 | BZ62: 0 | CA62: =BZ62/BP62 -> 0 | CB62: =BH62/SUMIFS(BH$2:BH$398,G$2:G$398,G62) -> 0.13786332 | CC62: =BI62/SUMIFS(BI$2:BI$398,G$2:G$398,G62) -> 0.12921038 | CD62: =CB62-CC62 -> 0.008652934 | CE62: =BL62/SUMIFS(BL$2:BL$398,G$2:G$398,G62) -> 0.12569832 | CF62: =BM62/SUMIFS(BM$2:BM$398,G$2:G$398,G62) -> 0.12631579 | CG62: =CE62-CF62 -> -0.00061746545 | CH62: =BP62/SUMIFS(BP$2:BP$398,G$2:G$398,G62) -> 0.12909759 | CI62: =BQ62/SUMIFS(BQ$2:BQ$398,G$2:G$398,G62) -> 0.12616758 | CJ62: =CH62-CI62 -> 0.0029300073 | CK62: =BT62/SUMIFS(BT$2:BT$398,G$2:G$398,G62) -> 0.11441273 | CL62: =BU62/SUMIFS(BU$2:BU$398,G$2:G$398,G62) -> 0.11842105 | CM62: =CK62-CL62 -> -0.0040083245 | CN62: =COUNTIFS(G$2:G$398,G62)*CH62 -> 0.90368313 | CO62: =COUNTIFS(G$2:G$398,G62)*CK62 -> 0.8008891
A63: 127090 | B63: BPC | C63: SAHAS FILLING STATION | D63: PASCHIM VIHAR, DON BOSCO | E63: WEST DELHI | F63: SAHAS FS | G63: SAHAS FS | H63: Punjabi Bagh | I63: Abhinav | J63: 460 | K63: 420 | L63: 100 | M63: 60 | N63: 500 | O63: 490 | P63: 120 | Q63: 90 | R63: 455 | S63: 460 | T63: 85 | U63: 120 | V63: 510 | W63: 506 | X63: 90 | Y63: 115 | Z63: 505 | AA63: 517 | AB63: 75 | AC63: 129 | AD63: 500 | AE63: 486.5 | AF63: 80 | AG63: 109.5 | AH63: 500 | AI63: 468 | AJ63: 80 | AK63: 90 | AL63: 485 | AM63: 458 | AN63: 75 | AO63: 80 | AP63: 470 | AQ63: 460 | AR63: 70 | AS63: 40 | AT63: 455 | AU63: 455 | AV63: 65 | AW63: 25 | AX63: 445 | AY63: 410 | AZ63: 75 | BA63: 85 | BB63: 520 | BC63: 455 | BD63: 80 | BE63: 85 | BF63: 28.66798 | BG63: 77.08754 | BH63: =BB63 -> 520 | BI63: =BC63 -> 455 | BJ63: =(BH63-BI63) -> 65 | BK63: =(BJ63)/BI63*100 -> 14.285714 | BL63: =BD63 -> 80 | BM63: =BE63 -> 85 | BN63: =(BL63-BM63) -> -5 | BO63: =(BN63)/BM63*100 -> -5.8823529 | BP63: =K63+O63+R63+V63+Z63+AD63+AH63+AL63+AP63+AT63+AX63+BB63 -> 5755 | BQ63: =J63+N63+S63+W63+AA63+AE63+AI63+AM63+AQ63+AU63+Table1[[#This Row],[MS-0225]]+Table1[[#This Row],[MS-0325]] -> 5635.5 | BR63: =(BP63-BQ63) -> 119.5 | BS63: =(BR63)/BQ63*100 -> 2.1204862 | BT63: =M63+Q63+T63+X63+AB63+AF63+AJ63+AN63+AR63+AV63+AZ63+BD63 -> 925 | BU63: =L63+P63+U63+Y63+AC63+AG63+AK63+AO63+AS63+AW63+BA63+BE63 -> 1098.5 | BV63: =(BT63-BU63) -> -173.5 | BW63: =(BV63)/BU63*100 -> -15.794265 | BX63: 20 | BY63: =BX63/BH63 -> 0.038461538 | BZ63: 115 | CA63: =BZ63/BP63 -> 0.019982624 | CB63: =BH63/SUMIFS(BH$2:BH$398,G$2:G$398,G63) -> 0.6824147 | CC63: =BI63/SUMIFS(BI$2:BI$398,G$2:G$398,G63) -> 0.6258597 | CD63: =CB63-CC63 -> 0.056555001 | CE63: =BL63/SUMIFS(BL$2:BL$398,G$2:G$398,G63) -> 0.64 | CF63: =BM63/SUMIFS(BM$2:BM$398,G$2:G$398,G63) -> 0.68548387 | CG63: =CE63-CF63 -> -0.045483871 | CH63: =BP63/SUMIFS(BP$2:BP$398,G$2:G$398,G63) -> 0.65427467 | CI63: =BQ63/SUMIFS(BQ$2:BQ$398,G$2:G$398,G63) -> 0.64928855 | CJ63: =CH63-CI63 -> 0.0049861168 | CK63: =BT63/SUMIFS(BT$2:BT$398,G$2:G$398,G63) -> 0.64685315 | CL63: =BU63/SUMIFS(BU$2:BU$398,G$2:G$398,G63) -> 0.67413317 | CM63: =CK63-CL63 -> -0.027280023 | CN63: =COUNTIFS(G$2:G$398,G63)*CH63 -> 1.3085493 | CO63: =COUNTIFS(G$2:G$398,G63)*CK63 -> 1.2937063
A64: 112452 | B64: BPC | C64: SIDHU SERVICE STATION | D64: G.T. KARNAL ROAD | E64: NORTH DELHI | F64: SIDHU | G64: SIDHU | H64: Old GT Road (NH1) | I64: Raj Doshi | J64: 427.5 | K64: 454 | L64: 1954.5 | M64: 1936 | N64: 454.5 | O64: 462 | P64: 2083.5 | Q64: 2022 | R64: 445.5 | S64: 418.5 | T64: 1964.5 | U64: 1892.5 | V64: 470.5 | W64: 454.5 | X64: 2201.5 | Y64: 2067.5 | Z64: 458 | AA64: 442.5 | AB64: 2100 | AC64: 2194.5 | AD64: 455.5 | AE64: 445.5 | AF64: 2187.5 | AG64: 1971.5 | AH64: 502 | AI64: 450 | AJ64: 2008 | AK64: 2134 | AL64: 482.5 | AM64: 450 | AN64: 2001.5 | AO64: 1679 | AP64: 485.5 | AQ64: 436.5 | AR64: 2004.5 | AS64: 1800.5 | AT64: 467 | AU64: 432 | AV64: 2013 | AW64: 1971 | AX64: 452.5 | AY64: 409.5 | AZ64: 2017.5 | BA64: 1947.5 | BB64: 515 | BC64: 445.5 | BD64: 2081 | BE64: 2117.5 | BF64: 28.72427 | BG64: 77.1645 | BH64: =BB64 -> 515 | BI64: =BC64 -> 445.5 | BJ64: =(BH64-BI64) -> 69.5 | BK64: =(BJ64)/BI64*100 -> 15.600449 | BL64: =BD64 -> 2081 | BM64: =BE64 -> 2117.5 | BN64: =(BL64-BM64) -> -36.5 | BO64: =(BN64)/BM64*100 -> -1.7237308 | BP64: =K64+O64+R64+V64+Z64+AD64+AH64+AL64+AP64+AT64+AX64+BB64 -> 5650 | BQ64: =J64+N64+S64+W64+AA64+AE64+AI64+AM64+AQ64+AU64+Table1[[#This Row],[MS-0225]]+Table1[[#This Row],[MS-0325]] -> 5266.5 | BR64: =(BP64-BQ64) -> 383.5 | BS64: =(BR64)/BQ64*100 -> 7.281876 | BT64: =M64+Q64+T64+X64+AB64+AF64+AJ64+AN64+AR64+AV64+AZ64+BD64 -> 24537 | BU64: =L64+P64+U64+Y64+AC64+AG64+AK64+AO64+AS64+AW64+BA64+BE64 -> 23813.5 | BV64: =(BT64-BU64) -> 723.5 | BW64: =(BV64)/BU64*100 -> 3.0381926 | BX64: 0 | BY64: =BX64/BH64 -> 0 | BZ64: 0 | CA64: =BZ64/BP64 -> 0 | CB64: =BH64/SUMIFS(BH$2:BH$398,G$2:G$398,G64) -> 0.47139588 | CC64: =BI64/SUMIFS(BI$2:BI$398,G$2:G$398,G64) -> 0.45880536 | CD64: =CB64-CC64 -> 0.012590526 | CE64: =BL64/SUMIFS(BL$2:BL$398,G$2:G$398,G64) -> 0.6099956 | CF64: =BM64/SUMIFS(BM$2:BM$398,G$2:G$398,G64) -> 0.56830381 | CG64: =CE64-CF64 -> 0.041691792 | CH64: =BP64/SUMIFS(BP$2:BP$398,G$2:G$398,G64) -> 0.46120567 | CI64: =BQ64/SUMIFS(BQ$2:BQ$398,G$2:G$398,G64) -> 0.45204068 | CJ64: =CH64-CI64 -> 0.0091649801 | CK64: =BT64/SUMIFS(BT$2:BT$398,G$2:G$398,G64) -> 0.60588925 | CL64: =BU64/SUMIFS(BU$2:BU$398,G$2:G$398,G64) -> 0.57747896 | CM64: =CK64-CL64 -> 0.028410289 | CN64: =COUNTIFS(G$2:G$398,G64)*CH64 -> 2.3060283 | CO64: =COUNTIFS(G$2:G$398,G64)*CK64 -> 3.0294463
A65: 112450 | B65: BPC | C65: SHANKAR FILLING STATION | D65: MAIN PUNJABI BAGH CLUB ROAD | E65: WEST DELHI | F65: ANIL-SHANKAR | G65: ANIL-SHANKAR | H65: Punjabi Bagh | I65: Abhinav | J65: 470 | K65: 500 | L65: 70 | M65: 80 | N65: 513 | O65: 535 | P65: 105 | Q65: 105 | R65: 515 | S65: 500 | T65: 105 | U65: 120 | V65: 560 | W65: 520 | X65: 100 | Y65: 100 | Z65: 550 | AA65: 520 | AB65: 110 | AC65: 100 | AD65: 540 | AE65: 510 | AF65: 100 | AG65: 90 | AH65: 556 | AI65: 535 | AJ65: 100 | AK65: 105 | AL65: 505 | AM65: 500 | AN65: 95 | AO65: 80 | AP65: 520 | AQ65: 465 | AR65: 60 | AS65: 55 | AT65: 485 | AU65: 475 | AV65: 75 | AW65: 85 | AX65: 470 | AY65: 435 | AZ65: 70 | BA65: 85 | BB65: 515 | BC65: 500 | BD65: 65 | BE65: 92 | BF65: 28.66721 | BG65: 77.11895 | BH65: =BB65 -> 515 | BI65: =BC65 -> 500 | BJ65: =(BH65-BI65) -> 15 | BK65: =(BJ65)/BI65*100 -> 3 | BL65: =BD65 -> 65 | BM65: =BE65 -> 92 | BN65: =(BL65-BM65) -> -27 | BO65: =(BN65)/BM65*100 -> -29.347826 | BP65: =K65+O65+R65+V65+Z65+AD65+AH65+AL65+AP65+AT65+AX65+BB65 -> 6251 | BQ65: =J65+N65+S65+W65+AA65+AE65+AI65+AM65+AQ65+AU65+Table1[[#This Row],[MS-0225]]+Table1[[#This Row],[MS-0325]] -> 5943 | BR65: =(BP65-BQ65) -> 308 | BS65: =(BR65)/BQ65*100 -> 5.1825677 | BT65: =M65+Q65+T65+X65+AB65+AF65+AJ65+AN65+AR65+AV65+AZ65+BD65 -> 1065 | BU65: =L65+P65+U65+Y65+AC65+AG65+AK65+AO65+AS65+AW65+BA65+BE65 -> 1087 | BV65: =(BT65-BU65) -> -22 | BW65: =(BV65)/BU65*100 -> -2.023919 | BX65: 35 | BY65: =BX65/BH65 -> 0.067961165 | BZ65: 220 | CA65: =BZ65/BP65 -> 0.035194369 | CB65: =BH65/SUMIFS(BH$2:BH$398,G$2:G$398,G65) -> 0.35225718 | CC65: =BI65/SUMIFS(BI$2:BI$398,G$2:G$398,G65) -> 0.36603221 | CD65: =CB65-CC65 -> -0.013775029 | CE65: =BL65/SUMIFS(BL$2:BL$398,G$2:G$398,G65) -> 0.25390625 | CF65: =BM65/SUMIFS(BM$2:BM$398,G$2:G$398,G65) -> 0.33699634 | CG65: =CE65-CF65 -> -0.083090087 | CH65: =BP65/SUMIFS(BP$2:BP$398,G$2:G$398,G65) -> 0.36376862 | CI65: =BQ65/SUMIFS(BQ$2:BQ$398,G$2:G$398,G65) -> 0.36206897 | CJ65: =CH65-CI65 -> 0.0016996565 | CK65: =BT65/SUMIFS(BT$2:BT$398,G$2:G$398,G65) -> 0.33333333 | CL65: =BU65/SUMIFS(BU$2:BU$398,G$2:G$398,G65) -> 0.32045991 | CM65: =CK65-CL65 -> 0.012873428 | CN65: =COUNTIFS(G$2:G$398,G65)*CH65 -> 1.0913059 | CO65: =COUNTIFS(G$2:G$398,G65)*CK65 -> 1
A66: 41019284 | B66: HPC | C66: MOUNT KAILASH HP CENTRE | D66: NETAJI SUBHASH PLACE | E66: NORTH WEST DELHI | F66: White Patch- Rohini | G66: White Patch- Pitampura | H66: Pitampura | I66: Abhinav | J66: 209.5 | K66: 218 | L66: 45.5 | M66: 47 | N66: 232 | O66: 260 | P66: 50 | Q66: 48 | R66: 241 | S66: 225.5 | T66: 45 | U66: 47.5 | V66: 242 | W66: 239 | X66: 45 | Y66: 56 | Z66: 246 | AA66: 239.5 | AB66: 40 | AC66: 54.5 | AD66: 238 | AE66: 230 | AF66: 48 | AG66: 48 | AH66: 242 | AI66: 241 | AJ66: 44 | AK66: 53 | AL66: 214 | AM66: 219 | AN66: 28 | AO66: 34 | AP66: 232 | AQ66: 219 | AR66: 32 | AS66: 40 | AT66: 228 | AU66: 211 | AV66: 36 | AW66: 42 | AX66: 206 | AY66: 183 | AZ66: 36 | BA66: 33 | BB66: 255 | BC66: 224 | BD66: 53 | BE66: 41 | BF66: 28.691883 | BG66: 77.146442 | BH66: =BB66 -> 255 | BI66: =BC66 -> 224 | BJ66: =(BH66-BI66) -> 31 | BK66: =(BJ66)/BI66*100 -> 13.839286 | BL66: =BD66 -> 53 | BM66: =BE66 -> 41 | BN66: =(BL66-BM66) -> 12 | BO66: =(BN66)/BM66*100 -> 29.268293 | BP66: =K66+O66+R66+V66+Z66+AD66+AH66+AL66+AP66+AT66+AX66+BB66 -> 2822 | BQ66: =J66+N66+S66+W66+AA66+AE66+AI66+AM66+AQ66+AU66+Table1[[#This Row],[MS-0225]]+Table1[[#This Row],[MS-0325]] -> 2672.5 | BR66: =(BP66-BQ66) -> 149.5 | BS66: =(BR66)/BQ66*100 -> 5.5940131 | BT66: =M66+Q66+T66+X66+AB66+AF66+AJ66+AN66+AR66+AV66+AZ66+BD66 -> 502 | BU66: =L66+P66+U66+Y66+AC66+AG66+AK66+AO66+AS66+AW66+BA66+BE66 -> 544.5 | BV66: =(BT66-BU66) -> -42.5 | BW66: =(BV66)/BU66*100 -> -7.805326 | BX66: 0 | BY66: =BX66/BH66 -> 0 | BZ66: 0 | CA66: =BZ66/BP66 -> 0 | CB66: =BH66/SUMIFS(BH$2:BH$398,G$2:G$398,G66) -> 0.18840044 | CC66: =BI66/SUMIFS(BI$2:BI$398,G$2:G$398,G66) -> 0.1690566 | CD66: =CB66-CC66 -> 0.01934384 | CE66: =BL66/SUMIFS(BL$2:BL$398,G$2:G$398,G66) -> 0.19449541 | CF66: =BM66/SUMIFS(BM$2:BM$398,G$2:G$398,G66) -> 0.14539007 | CG66: =CE66-CF66 -> 0.049105342 | CH66: =BP66/SUMIFS(BP$2:BP$398,G$2:G$398,G66) -> 0.17977385 | CI66: =BQ66/SUMIFS(BQ$2:BQ$398,G$2:G$398,G66) -> 0.17427454 | CJ66: =CH66-CI66 -> 0.005499314 | CK66: =BT66/SUMIFS(BT$2:BT$398,G$2:G$398,G66) -> 0.17236052 | CL66: =BU66/SUMIFS(BU$2:BU$398,G$2:G$398,G66) -> 0.15865385 | CM66: =CK66-CL66 -> 0.013706669 | CN66: =COUNTIFS(G$2:G$398,G66)*CH66 -> 0.89886925 | CO66: =COUNTIFS(G$2:G$398,G66)*CK66 -> 0.86180258 | CP66: =BD66-AZ66 -> 17
A67: 108140 | B67: IOC | C67: MILLENNIUM PETROCARE | D67: SECTOR-9,DWARKA | E67: SOUTH WEST DELHI | F67: White Patch_Dwarka_To_Bijwasan | G67: White Patch_Dwarka_To_Bijwasan | H67: Dwarka | I67: Raj Doshi | J67: 441 | K67: 479 | L67: 69 | M67: 63 | N67: 467.5 | O67: 494.5 | P67: 76.5 | Q67: 67.5 | R67: 463.5 | S67: 468 | T67: 58.5 | U67: 72 | V67: 504 | W67: 478.5 | X67: 72 | Y67: 75.5 | Z67: 490.5 | AA67: 531.5 | AB67: 67.5 | AC67: 76.5 | AD67: 467.5 | AE67: 481.5 | AF67: 66.5 | AG67: 76.5 | AH67: 491 | AI67: 504 | AJ67: 63 | AK67: 72 | AL67: 463.5 | AM67: 463.5 | AN67: 58.5 | AO67: 58.5 | AP67: 477 | AQ67: 445.5 | AR67: 63 | AS67: 58.5 | AT67: 429.5 | AU67: 463.5 | AV67: 58.5 | AW67: 58.5 | AX67: 450 | AY67: 414 | AZ67: 72 | BA67: 54 | BB67: 508.5 | BC67: 459 | BD67: 67.5 | BE67: 63 | BF67: 28.5748 | BG67: 77.0677 | BH67: =BB67 -> 508.5 | BI67: =BC67 -> 459 | BJ67: =(BH67-BI67) -> 49.5 | BK67: =(BJ67)/BI67*100 -> 10.784314 | BL67: =BD67 -> 67.5 | BM67: =BE67 -> 63 | BN67: =(BL67-BM67) -> 4.5 | BO67: =(BN67)/BM67*100 -> 7.1428571 | BP67: =K67+O67+R67+V67+Z67+AD67+AH67+AL67+AP67+AT67+AX67+BB67 -> 5718.5 | BQ67: =J67+N67+S67+W67+AA67+AE67+AI67+AM67+AQ67+AU67+Table1[[#This Row],[MS-0225]]+Table1[[#This Row],[MS-0325]] -> 5617.5 | BR67: =(BP67-BQ67) -> 101 | BS67: =(BR67)/BQ67*100 -> 1.7979528 | BT67: =M67+Q67+T67+X67+AB67+AF67+AJ67+AN67+AR67+AV67+AZ67+BD67 -> 777.5 | BU67: =L67+P67+U67+Y67+AC67+AG67+AK67+AO67+AS67+AW67+BA67+BE67 -> 810.5 | BV67: =(BT67-BU67) -> -33 | BW67: =(BV67)/BU67*100 -> -4.0715608 | BX67: 0 | BY67: =BX67/BH67 -> 0 | BZ67: 0 | CA67: =BZ67/BP67 -> 0 | CB67: =BH67/SUMIFS(BH$2:BH$398,G$2:G$398,G67) -> 0.57653061 | CC67: =BI67/SUMIFS(BI$2:BI$398,G$2:G$398,G67) -> 0.49143469 | CD67: =CB67-CC67 -> 0.085095923 | CE67: =BL67/SUMIFS(BL$2:BL$398,G$2:G$398,G67) -> 0.44407895 | CF67: =BM67/SUMIFS(BM$2:BM$398,G$2:G$398,G67) -> 0.32984293 | CG67: =CE67-CF67 -> 0.11423602 | CH67: =BP67/SUMIFS(BP$2:BP$398,G$2:G$398,G67) -> 0.516553 | CI67: =BQ67/SUMIFS(BQ$2:BQ$398,G$2:G$398,G67) -> 0.54981893 | CJ67: =CH67-CI67 -> -0.033265928 | CK67: =BT67/SUMIFS(BT$2:BT$398,G$2:G$398,G67) -> 0.38197003 | CL67: =BU67/SUMIFS(BU$2:BU$398,G$2:G$398,G67) -> 0.37127806 | CM67: =CK67-CL67 -> 0.010691974 | CN67: =COUNTIFS(G$2:G$398,G67)*CH67 -> 1.033106 | CO67: =COUNTIFS(G$2:G$398,G67)*CK67 -> 0.76394006
A68: 41056327 | B68: HPC | C68: CHADHA OIL COMPANY | D68: SHIVAJI PARK | E68: WEST DELHI | F68: ANIL-SHANKAR | G68: ANIL-SHANKAR | H68: Rohtak Road | I68: Abhinav | J68: 456 | K68: 468 | L68: 133 | M68: 120 | N68: 511 | O68: 533.5 | P68: 147 | Q68: 131.5 | R68: 488 | S68: 442 | T68: 128 | U68: 139 | V68: 514 | W68: 477 | X68: 124 | Y68: 135 | Z68: 530 | AA68: 500 | AB68: 130 | AC68: 145 | AD68: 524 | AE68: 500 | AF68: 135 | AG68: 137 | AH68: 526 | AI68: 497 | AJ68: 112 | AK68: 134 | AL68: 492 | AM68: 457 | AN68: 102 | AO68: 101 | AP68: 496 | AQ68: 470 | AR68: 98 | AS68: 96 | AT68: 469 | AU68: 464 | AV68: 104 | AW68: 124 | AX68: 440 | AY68: 428 | AZ68: 110 | BA68: 104 | BB68: 512 | BC68: 479 | BD68: 126 | BE68: 118 | BF68: 28.67474 | BG68: 77.13014 | BH68: =BB68 -> 512 | BI68: =BC68 -> 479 | BJ68: =(BH68-BI68) -> 33 | BK68: =(BJ68)/BI68*100 -> 6.8893528 | BL68: =BD68 -> 126 | BM68: =BE68 -> 118 | BN68: =(BL68-BM68) -> 8 | BO68: =(BN68)/BM68*100 -> 6.779661 | BP68: =K68+O68+R68+V68+Z68+AD68+AH68+AL68+AP68+AT68+AX68+BB68 -> 5992.5 | BQ68: =J68+N68+S68+W68+AA68+AE68+AI68+AM68+AQ68+AU68+Table1[[#This Row],[MS-0225]]+Table1[[#This Row],[MS-0325]] -> 5681 | BR68: =(BP68-BQ68) -> 311.5 | BS68: =(BR68)/BQ68*100 -> 5.4831896 | BT68: =M68+Q68+T68+X68+AB68+AF68+AJ68+AN68+AR68+AV68+AZ68+BD68 -> 1420.5 | BU68: =L68+P68+U68+Y68+AC68+AG68+AK68+AO68+AS68+AW68+BA68+BE68 -> 1513 | BV68: =(BT68-BU68) -> -92.5 | BW68: =(BV68)/BU68*100 -> -6.1136814 | BX68: 0 | BY68: =BX68/BH68 -> 0 | BZ68: 0 | CA68: =BZ68/BP68 -> 0 | CB68: =BH68/SUMIFS(BH$2:BH$398,G$2:G$398,G68) -> 0.3502052 | CC68: =BI68/SUMIFS(BI$2:BI$398,G$2:G$398,G68) -> 0.35065886 | CD68: =CB68-CC68 -> -0.00045365962 | CE68: =BL68/SUMIFS(BL$2:BL$398,G$2:G$398,G68) -> 0.4921875 | CF68: =BM68/SUMIFS(BM$2:BM$398,G$2:G$398,G68) -> 0.43223443 | CG68: =CE68-CF68 -> 0.059953068 | CH68: =BP68/SUMIFS(BP$2:BP$398,G$2:G$398,G68) -> 0.34872556 | CI68: =BQ68/SUMIFS(BQ$2:BQ$398,G$2:G$398,G68) -> 0.34610698 | CJ68: =CH68-CI68 -> 0.0026185768 | CK68: =BT68/SUMIFS(BT$2:BT$398,G$2:G$398,G68) -> 0.44460094 | CL68: =BU68/SUMIFS(BU$2:BU$398,G$2:G$398,G68) -> 0.44604953 | CM68: =CK68-CL68 -> -0.0014485893 | CN68: =COUNTIFS(G$2:G$398,G68)*CH68 -> 1.0461767 | CO68: =COUNTIFS(G$2:G$398,G68)*CK68 -> 1.3338028 | CP68: =BD68-AZ68 -> 16
A69: 106324 | B69: IOC | C69: RAJ SUPER SERVICE STATION | D69: MOTI BAGH | E69: NEW DELHI | F69: White Patch_Moti Bagh | G69: White Patch_Moti Bagh | H69: Inner Ring Road | I69: Bhanu Pratap | J69: 486 | K69: 535.5 | L69: 126 | M69: 112.5 | N69: 490.5 | O69: 522 | P69: 121.5 | Q69: 108 | R69: 490.5 | S69: 490.5 | T69: 103.5 | U69: 139.5 | V69: 513 | W69: 490.5 | X69: 99 | Y69: 121.5 | Z69: 499.5 | AA69: 504 | AB69: 94.5 | AC69: 126 | AD69: 441 | AE69: 454.5 | AF69: 81 | AG69: 103.5 | AH69: 481.5 | AI69: 522 | AJ69: 82.5 | AK69: 126 | AL69: 497.5 | AM69: 477 | AN69: 90.5 | AO69: 99 | AP69: 490 | AQ69: 477 | AR69: 80 | AS69: 99 | AT69: 466.5 | AU69: 495 | AV69: 81.5 | AW69: 99 | AX69: 468.5 | AY69: 445.5 | AZ69: 83.5 | BA69: 94.5 | BB69: 502 | BC69: 472.5 | BD69: 90 | BE69: 103.5 | BF69: 28.5844 | BG69: 77.1722 | BH69: =BB69 -> 502 | BI69: =BC69 -> 472.5 | BJ69: =(BH69-BI69) -> 29.5 | BK69: =(BJ69)/BI69*100 -> 6.2433862 | BL69: =BD69 -> 90 | BM69: =BE69 -> 103.5 | BN69: =(BL69-BM69) -> -13.5 | BO69: =(BN69)/BM69*100 -> -13.043478 | BP69: =K69+O69+R69+V69+Z69+AD69+AH69+AL69+AP69+AT69+AX69+BB69 -> 5907.5 | BQ69: =J69+N69+S69+W69+AA69+AE69+AI69+AM69+AQ69+AU69+Table1[[#This Row],[MS-0225]]+Table1[[#This Row],[MS-0325]] -> 5805 | BR69: =(BP69-BQ69) -> 102.5 | BS69: =(BR69)/BQ69*100 -> 1.7657192 | BT69: =M69+Q69+T69+X69+AB69+AF69+AJ69+AN69+AR69+AV69+AZ69+BD69 -> 1106.5 | BU69: =L69+P69+U69+Y69+AC69+AG69+AK69+AO69+AS69+AW69+BA69+BE69 -> 1359 | BV69: =(BT69-BU69) -> -252.5 | BW69: =(BV69)/BU69*100 -> -18.579838 | BX69: 0 | BY69: =BX69/BH69 -> 0 | BZ69: 0 | CA69: =BZ69/BP69 -> 0 | CB69: =BH69/SUMIFS(BH$2:BH$398,G$2:G$398,G69) -> 0.35805991 | CC69: =BI69/SUMIFS(BI$2:BI$398,G$2:G$398,G69) -> 0.32631215 | CD69: =CB69-CC69 -> 0.03174776 | CE69: =BL69/SUMIFS(BL$2:BL$398,G$2:G$398,G69) -> 0.14195584 | CF69: =BM69/SUMIFS(BM$2:BM$398,G$2:G$398,G69) -> 0.16021672 | CG69: =CE69-CF69 -> -0.018260882 | CH69: =BP69/SUMIFS(BP$2:BP$398,G$2:G$398,G69) -> 0.3405488 | CI69: =BQ69/SUMIFS(BQ$2:BQ$398,G$2:G$398,G69) -> 0.3453918 | CJ69: =CH69-CI69 -> -0.004843003 | CK69: =BT69/SUMIFS(BT$2:BT$398,G$2:G$398,G69) -> 0.14942606 | CL69: =BU69/SUMIFS(BU$2:BU$398,G$2:G$398,G69) -> 0.178487 | CM69: =CK69-CL69 -> -0.029060934 | CN69: =COUNTIFS(G$2:G$398,G69)*CH69 -> 1.0216464 | CO69: =COUNTIFS(G$2:G$398,G69)*CK69 -> 0.44827819
A70: 356678 | B70: IOC | C70: ROOP F/STN. -ADHOC (MAHESHWARI)-27.8.20 | D70: GEETA COLONY, SITE II | E70: EAST DELHI | F70: White Patch_Geeta Colony | G70: White Patch_Geeta Colony | H70: Mayur Vihar -Anand Vihar -Preet Vihar | I70: Bhanu Pratap | J70: 422.387 | K70: 508.298 | L70: 46.513 | M70: 40.26 | N70: 458.85 | O70: 504.343 | P70: 54.38 | Q70: 45.87 | R70: 503.5 | S70: 449.887 | T70: 41.5 | U70: 51.731 | V70: 536.009 | W70: 484.628 | X70: 48.224 | Y70: 63.195 | Z70: 561.885 | AA70: 490.926 | AB70: 56.466 | AC70: 46.075 | AD70: 567.956 | AE70: 472.315 | AF70: 63.537 | AG70: 43.799 | AH70: 517.15 | AI70: 495.5 | AJ70: 50.934 | AK70: 40.5 | AL70: 478.795 | AM70: 474.435 | AN70: 45.948 | AO70: 42.759 | AP70: 481.411 | AQ70: 472.349 | AR70: 45.571 | AS70: 41.309 | AT70: 492.786 | AU70: 473.953 | AV70: 48.04 | AW70: 45.732 | AX70: 453.894 | AY70: 470.806 | AZ70: 52.352 | BA70: 52.112 | BB70: 501.799 | BC70: 488 | BD70: 61.103 | BE70: 54 | BF70: 28.652368 | BG70: 77.268317 | BH70: =BB70 -> 501.799 | BI70: =BC70 -> 488 | BJ70: =(BH70-BI70) -> 13.799 | BK70: =(BJ70)/BI70*100 -> 2.8276639 | BL70: =BD70 -> 61.103 | BM70: =BE70 -> 54 | BN70: =(BL70-BM70) -> 7.103 | BO70: =(BN70)/BM70*100 -> 13.153704 | BP70: =K70+O70+R70+V70+Z70+AD70+AH70+AL70+AP70+AT70+AX70+BB70 -> 6107.826 | BQ70: =J70+N70+S70+W70+AA70+AE70+AI70+AM70+AQ70+AU70+Table1[[#This Row],[MS-0225]]+Table1[[#This Row],[MS-0325]] -> 5654.036 | BR70: =(BP70-BQ70) -> 453.79 | BS70: =(BR70)/BQ70*100 -> 8.0259482 | BT70: =M70+Q70+T70+X70+AB70+AF70+AJ70+AN70+AR70+AV70+AZ70+BD70 -> 599.805 | BU70: =L70+P70+U70+Y70+AC70+AG70+AK70+AO70+AS70+AW70+BA70+BE70 -> 582.105 | BV70: =(BT70-BU70) -> 17.7 | BW70: =(BV70)/BU70*100 -> 3.0406885 | BX70: 0 | BY70: =BX70/BH70 -> 0 | BZ70: 0 | CA70: =BZ70/BP70 -> 0 | CB70: =BH70/SUMIFS(BH$2:BH$398,G$2:G$398,G70) -> 0.34350996 | CC70: =BI70/SUMIFS(BI$2:BI$398,G$2:G$398,G70) -> 0.41960447 | CD70: =CB70-CC70 -> -0.076094515 | CE70: =BL70/SUMIFS(BL$2:BL$398,G$2:G$398,G70) -> 0.28015662 | CF70: =BM70/SUMIFS(BM$2:BM$398,G$2:G$398,G70) -> 0.35294118 | CG70: =CE70-CF70 -> -0.072784553 | CH70: =BP70/SUMIFS(BP$2:BP$398,G$2:G$398,G70) -> 0.41065637 | CI70: =BQ70/SUMIFS(BQ$2:BQ$398,G$2:G$398,G70) -> 0.39548293 | CJ70: =CH70-CI70 -> 0.015173432 | CK70: =BT70/SUMIFS(BT$2:BT$398,G$2:G$398,G70) -> 0.31008812 | CL70: =BU70/SUMIFS(BU$2:BU$398,G$2:G$398,G70) -> 0.28290415 | CM70: =CK70-CL70 -> 0.027183966 | CN70: =COUNTIFS(G$2:G$398,G70)*CH70 -> 0.82131273 | CO70: =COUNTIFS(G$2:G$398,G70)*CK70 -> 0.62017624
A71: 212907 | B71: IOC | C71: CHAUDHARY SERVICE STATION | D71: DHEERPUR | E71: NORTH DELHI | F71: White Patch_Model Town | G71: White Patch_Model Town | H71: Outer Ring Road | I71: Raj Doshi | J71: 502.5 | K71: 517.5 | L71: 241.5 | M71: 274.5 | N71: 534 | O71: 522 | P71: 244 | Q71: 252 | R71: 512 | S71: 522 | T71: 282 | U71: 234 | V71: 546 | W71: 531 | X71: 252 | Y71: 207 | Z71: 553 | AA71: 568 | AB71: 251 | AC71: 208 | AD71: 521.5 | AE71: 506 | AF71: 252.5 | AG71: 218 | AH71: 550 | AI71: 508.5 | AJ71: 270 | AK71: 247.5 | AL71: 534 | AM71: 499.5 | AN71: 260 | AO71: 198.5 | AP71: 498 | AQ71: 454.5 | AR71: 272 | AS71: 229.5 | AT71: 489 | AU71: 463.5 | AV71: 269 | AW71: 274.5 | AX71: 528 | AY71: 456.5 | AZ71: 294 | BA71: 265.5 | BB71: 500 | BC71: 481.5 | BD71: 267 | BE71: 238.5 | BF71: 28.7302 | BG71: 77.1832 | BH71: =BB71 -> 500 | BI71: =BC71 -> 481.5 | BJ71: =(BH71-BI71) -> 18.5 | BK71: =(BJ71)/BI71*100 -> 3.8421599 | BL71: =BD71 -> 267 | BM71: =BE71 -> 238.5 | BN71: =(BL71-BM71) -> 28.5 | BO71: =(BN71)/BM71*100 -> 11.949686 | BP71: =K71+O71+R71+V71+Z71+AD71+AH71+AL71+AP71+AT71+AX71+BB71 -> 6271 | BQ71: =J71+N71+S71+W71+AA71+AE71+AI71+AM71+AQ71+AU71+Table1[[#This Row],[MS-0225]]+Table1[[#This Row],[MS-0325]] -> 6027.5 | BR71: =(BP71-BQ71) -> 243.5 | BS71: =(BR71)/BQ71*100 -> 4.0398175 | BT71: =M71+Q71+T71+X71+AB71+AF71+AJ71+AN71+AR71+AV71+AZ71+BD71 -> 3196 | BU71: =L71+P71+U71+Y71+AC71+AG71+AK71+AO71+AS71+AW71+BA71+BE71 -> 2806.5 | BV71: =(BT71-BU71) -> 389.5 | BW71: =(BV71)/BU71*100 -> 13.878496 | BX71: 0 | BY71: =BX71/BH71 -> 0 | BZ71: 0 | CA71: =BZ71/BP71 -> 0 | CB71: =BH71/SUMIFS(BH$2:BH$398,G$2:G$398,G71) -> 0.37453184 | CC71: =BI71/SUMIFS(BI$2:BI$398,G$2:G$398,G71) -> 0.38940558 | CD71: =CB71-CC71 -> -0.014873745 | CE71: =BL71/SUMIFS(BL$2:BL$398,G$2:G$398,G71) -> 0.64805825 | CF71: =BM71/SUMIFS(BM$2:BM$398,G$2:G$398,G71) -> 0.62190352 | CG71: =CE71-CF71 -> 0.026154732 | CH71: =BP71/SUMIFS(BP$2:BP$398,G$2:G$398,G71) -> 0.39343748 | CI71: =BQ71/SUMIFS(BQ$2:BQ$398,G$2:G$398,G71) -> 0.39144694 | CJ71: =CH71-CI71 -> 0.0019905392 | CK71: =BT71/SUMIFS(BT$2:BT$398,G$2:G$398,G71) -> 0.6522449 | CL71: =BU71/SUMIFS(BU$2:BU$398,G$2:G$398,G71) -> 0.59233854 | CM71: =CK71-CL71 -> 0.059906358 | CN71: =COUNTIFS(G$2:G$398,G71)*CH71 -> 1.1803124 | CO71: =COUNTIFS(G$2:G$398,G71)*CK71 -> 1.9567347
A72: 106243 | B72: IOC | C72: CENTRE HALF SERVICE STATION | D72: SADIQ NAGAR | E72: SOUTH DELHI | F72: AUTO CENTRE_NAVYUG_PREM | G72: AUTO CENTRE_NAVYUG_PREM | H72: Greater Kailash I &II | I72: Raj Doshi | J72: 473 | K72: 505 | L72: 105 | M72: 95 | N72: 512.5 | O72: 535 | P72: 117.5 | Q72: 105 | R72: 488 | S72: 536 | T72: 90 | U72: 132 | V72: 570 | W72: 542.5 | X72: 94 | Y72: 127.5 | Z72: 558 | AA72: 535 | AB72: 98 | AC72: 125 | AD72: 508 | AE72: 488.5 | AF72: 88 | AG72: 109.5 | AH72: 535 | AI72: 486.5 | AJ72: 89 | AK72: 109.5 | AL72: 452 | AM72: 493.5 | AN72: 40 | AO72: 84.5 | AP72: 466 | AQ72: 463 | AR72: 64 | AS72: 75 | AT72: 445 | AU72: 465 | AV72: 65 | AW72: 75 | AX72: 430 | AY72: 405 | AZ72: 70 | BA72: 95 | BB72: 498 | BC72: 490 | BD72: 70 | BE72: 90 | BF72: 28.5553 | BG72: 77.2285 | BH72: =BB72 -> 498 | BI72: =BC72 -> 490 | BJ72: =(BH72-BI72) -> 8 | BK72: =(BJ72)/BI72*100 -> 1.6326531 | BL72: =BD72 -> 70 | BM72: =BE72 -> 90 | BN72: =(BL72-BM72) -> -20 | BO72: =(BN72)/BM72*100 -> -22.222222 | BP72: =K72+O72+R72+V72+Z72+AD72+AH72+AL72+AP72+AT72+AX72+BB72 -> 5990 | BQ72: =J72+N72+S72+W72+AA72+AE72+AI72+AM72+AQ72+AU72+Table1[[#This Row],[MS-0225]]+Table1[[#This Row],[MS-0325]] -> 5890.5 | BR72: =(BP72-BQ72) -> 99.5 | BS72: =(BR72)/BQ72*100 -> 1.6891605 | BT72: =M72+Q72+T72+X72+AB72+AF72+AJ72+AN72+AR72+AV72+AZ72+BD72 -> 968 | BU72: =L72+P72+U72+Y72+AC72+AG72+AK72+AO72+AS72+AW72+BA72+BE72 -> 1245.5 | BV72: =(BT72-BU72) -> -277.5 | BW72: =(BV72)/BU72*100 -> -22.280209 | BX72: 0 | BY72: =BX72/BH72 -> 0 | BZ72: 0 | CA72: =BZ72/BP72 -> 0 | CB72: =BH72/SUMIFS(BH$2:BH$398,G$2:G$398,G72) -> 0.14264861 | CC72: =BI72/SUMIFS(BI$2:BI$398,G$2:G$398,G72) -> 0.14312378 | CD72: =CB72-CC72 -> -0.00047516635 | CE72: =BL72/SUMIFS(BL$2:BL$398,G$2:G$398,G72) -> 0.083071165 | CF72: =BM72/SUMIFS(BM$2:BM$398,G$2:G$398,G72) -> 0.10656866 | CG72: =CE72-CF72 -> -0.02349749 | CH72: =BP72/SUMIFS(BP$2:BP$398,G$2:G$398,G72) -> 0.14144062 | CI72: =BQ72/SUMIFS(BQ$2:BQ$398,G$2:G$398,G72) -> 0.14383423 | CJ72: =CH72-CI72 -> -0.0023936072 | CK72: =BT72/SUMIFS(BT$2:BT$398,G$2:G$398,G72) -> 0.10101231 | CL72: =BU72/SUMIFS(BU$2:BU$398,G$2:G$398,G72) -> 0.11526129 | CM72: =CK72-CL72 -> -0.014248974 | CN72: =COUNTIFS(G$2:G$398,G72)*CH72 -> 0.99008433 | CO72: =COUNTIFS(G$2:G$398,G72)*CK72 -> 0.7070862
A73: 186855 | B73: IOC | C73: RUCHIKA SERVICE STATION | D73: KUNDLI GHAROLI | E73: EAST DELHI | F73: VASUNDHARA_VIJ | G73: VASUNDHARA_VIJ | H73: Mayur Vihar -Anand Vihar -Preet Vihar | I73: Bhanu Pratap | J73: 441 | K73: 475 | L73: 207 | M73: 185 | N73: 477 | O73: 485 | P73: 225 | Q73: 195 | R73: 470 | S73: 472.5 | T73: 150 | U73: 229.5 | V73: 505 | W73: 486 | X73: 195 | Y73: 216 | Z73: 490 | AA73: 490.5 | AB73: 170 | AC73: 247.5 | AD73: 475 | AE73: 453 | AF73: 145 | AG73: 207 | AH73: 480 | AI73: 495 | AJ73: 140 | AK73: 225 | AL73: 450 | AM73: 440 | AN73: 110 | AO73: 200 | AP73: 455 | AQ73: 445 | AR73: 105 | AS73: 175 | AT73: 430 | AU73: 415 | AV73: 110 | AW73: 185 | AX73: 435 | AY73: 410 | AZ73: 85 | BA73: 190 | BB73: 495 | BC73: 445 | BD73: 105 | BE73: 175 | BF73: 28.6036 | BG73: 77.3356 | BH73: =BB73 -> 495 | BI73: =BC73 -> 445 | BJ73: =(BH73-BI73) -> 50 | BK73: =(BJ73)/BI73*100 -> 11.235955 | BL73: =BD73 -> 105 | BM73: =BE73 -> 175 | BN73: =(BL73-BM73) -> -70 | BO73: =(BN73)/BM73*100 -> -40 | BP73: =K73+O73+R73+V73+Z73+AD73+AH73+AL73+AP73+AT73+AX73+BB73 -> 5645 | BQ73: =J73+N73+S73+W73+AA73+AE73+AI73+AM73+AQ73+AU73+Table1[[#This Row],[MS-0225]]+Table1[[#This Row],[MS-0325]] -> 5470 | BR73: =(BP73-BQ73) -> 175 | BS73: =(BR73)/BQ73*100 -> 3.1992687 | BT73: =M73+Q73+T73+X73+AB73+AF73+AJ73+AN73+AR73+AV73+AZ73+BD73 -> 1695 | BU73: =L73+P73+U73+Y73+AC73+AG73+AK73+AO73+AS73+AW73+BA73+BE73 -> 2482 | BV73: =(BT73-BU73) -> -787 | BW73: =(BV73)/BU73*100 -> -31.7083 | BX73: 0 | BY73: =BX73/BH73 -> 0 | BZ73: 0 | CA73: =BZ73/BP73 -> 0 | CB73: =BH73/SUMIFS(BH$2:BH$398,G$2:G$398,G73) -> 0.2461462 | CC73: =BI73/SUMIFS(BI$2:BI$398,G$2:G$398,G73) -> 0.24303659 | CD73: =CB73-CC73 -> 0.0031096039 | CE73: =BL73/SUMIFS(BL$2:BL$398,G$2:G$398,G73) -> 0.16006098 | CF73: =BM73/SUMIFS(BM$2:BM$398,G$2:G$398,G73) -> 0.25 | CG73: =CE73-CF73 -> -0.089939024 | CH73: =BP73/SUMIFS(BP$2:BP$398,G$2:G$398,G73) -> 0.24329799 | CI73: =BQ73/SUMIFS(BQ$2:BQ$398,G$2:G$398,G73) -> 0.24882864 | CJ73: =CH73-CI73 -> -0.0055306486 | CK73: =BT73/SUMIFS(BT$2:BT$398,G$2:G$398,G73) -> 0.21344919 | CL73: =BU73/SUMIFS(BU$2:BU$398,G$2:G$398,G73) -> 0.2941804 | CM73: =CK73-CL73 -> -0.080731208 | CN73: =COUNTIFS(G$2:G$398,G73)*CH73 -> 1.4597879 | CO73: =COUNTIFS(G$2:G$398,G73)*CK73 -> 1.2806951
A74: 368600 | B74: IOC | C74: IOC COCO MASJID MOTH(old 186872) | D74: MASJID MOTH | E74: SOUTH DELHI | F74: AUTO CENTRE_NAVYUG_PREM | G74: AUTO CENTRE_NAVYUG_PREM | H74: Greater Kailash I &II | I74: Raj Doshi | J74: 485.945 | K74: 501.941 | L74: 113.201 | M74: 89.824 | N74: 467.013 | O74: 527.953 | P74: 107.177 | Q74: 89.868 | R74: 464.5 | S74: 353.965 | T74: 92 | U74: 77.029 | V74: 518.267 | W74: 450.284 | X74: 87.858 | Y74: 110 | Z74: 505.504 | AA74: 527.301 | AB74: 79.991 | AC74: 111.57 | AD74: 536.661 | AE74: 454.152 | AF74: 92.776 | AG74: 93.758 | AH74: 525.624 | AI74: 523 | AJ74: 85.508 | AK74: 107 | AL74: 472.292 | AM74: 466.504 | AN74: 65.839 | AO74: 78.082 | AP74: 473.535 | AQ74: 437.472 | AR74: 69.326 | AS74: 75.461 | AT74: 485.829 | AU74: 446.078 | AV74: 73.695 | AW74: 79.052 | AX74: 467.331 | AY74: 421.665 | AZ74: 72.539 | BA74: 80.134 | BB74: 489.316 | BC74: 466.017 | BD74: 71.302 | BE74: 82.878 | BF74: 28.548237914595752 | BG74: 77.228388 | BH74: =BB74 -> 489.316 | BI74: =BC74 -> 466.017 | BJ74: =(BH74-BI74) -> 23.299 | BK74: =(BJ74)/BI74*100 -> 4.999603 | BL74: =BD74 -> 71.302 | BM74: =BE74 -> 82.878 | BN74: =(BL74-BM74) -> -11.576 | BO74: =(BN74)/BM74*100 -> -13.967519 | BP74: =K74+O74+R74+V74+Z74+AD74+AH74+AL74+AP74+AT74+AX74+BB74 -> 5968.753 | BQ74: =J74+N74+S74+W74+AA74+AE74+AI74+AM74+AQ74+AU74+Table1[[#This Row],[MS-0225]]+Table1[[#This Row],[MS-0325]] -> 5499.396 | BR74: =(BP74-BQ74) -> 469.357 | BS74: =(BR74)/BQ74*100 -> 8.5347009 | BT74: =M74+Q74+T74+X74+AB74+AF74+AJ74+AN74+AR74+AV74+AZ74+BD74 -> 970.526 | BU74: =L74+P74+U74+Y74+AC74+AG74+AK74+AO74+AS74+AW74+BA74+BE74 -> 1115.342 | BV74: =(BT74-BU74) -> -144.816 | BW74: =(BV74)/BU74*100 -> -12.984 | BX74: 0 | BY74: =BX74/BH74 -> 0 | BZ74: 0 | CA74: =BZ74/BP74 -> 0 | CB74: =BH74/SUMIFS(BH$2:BH$398,G$2:G$398,G74) -> 0.14016114 | CC74: =BI74/SUMIFS(BI$2:BI$398,G$2:G$398,G74) -> 0.1361186 | CD74: =CB74-CC74 -> 0.0040425414 | CE74: =BL74/SUMIFS(BL$2:BL$398,G$2:G$398,G74) -> 0.084616288 | CF74: =BM74/SUMIFS(BM$2:BM$398,G$2:G$398,G74) -> 0.098135522 | CG74: =CE74-CF74 -> -0.013519234 | CH74: =BP74/SUMIFS(BP$2:BP$398,G$2:G$398,G74) -> 0.14093892 | CI74: =BQ74/SUMIFS(BQ$2:BQ$398,G$2:G$398,G74) -> 0.13428425 | CJ74: =CH74-CI74 -> 0.0066546691 | CK74: =BT74/SUMIFS(BT$2:BT$398,G$2:G$398,G74) -> 0.10127591 | CL74: =BU74/SUMIFS(BU$2:BU$398,G$2:G$398,G74) -> 0.10321618 | CM74: =CK74-CL74 -> -0.0019402767 | CN74: =COUNTIFS(G$2:G$398,G74)*CH74 -> 0.98657242 | CO74: =COUNTIFS(G$2:G$398,G74)*CK74 -> 0.70893135
A75: 112429 | B75: BPC | C75: NAVYUG SERVICE STATION | D75: GREATER KAILASH - 1 | E75: SOUTH DELHI | F75: AUTO CENTRE_NAVYUG_PREM | G75: AUTO CENTRE_NAVYUG_PREM | H75: Greater Kailash I &II | I75: Raj Doshi | J75: 441 | K75: 504 | L75: 135 | M75: 126 | N75: 526.50001 | O75: 508.5 | P75: 157.5 | Q75: 139.5 | R75: 468 | S75: 486 | T75: 108 | U75: 144 | V75: 526.5 | W75: 522 | X75: 139.5 | Y75: 144 | Z75: 526.5 | AA75: 517.5 | AB75: 121.5 | AC75: 148.5 | AD75: 558 | AE75: 508.5 | AF75: 126 | AG75: 139.5 | AH75: 535.5 | AI75: 504 | AJ75: 130.5 | AK75: 144 | AL75: 459 | AM75: 450 | AN75: 99 | AO75: 108 | AP75: 489 | AQ75: 463.5 | AR75: 117 | AS75: 94.5 | AT75: 477 | AU75: 450 | AV75: 99 | AW75: 108 | AX75: 450 | AY75: 400.5 | AZ75: 108 | BA75: 103.5 | BB75: 486 | BC75: 468 | BD75: 108 | BE75: 126 | BF75: 28.55918 | BG75: 77.23202 | BH75: =BB75 -> 486 | BI75: =BC75 -> 468 | BJ75: =(BH75-BI75) -> 18 | BK75: =(BJ75)/BI75*100 -> 3.8461538 | BL75: =BD75 -> 108 | BM75: =BE75 -> 126 | BN75: =(BL75-BM75) -> -18 | BO75: =(BN75)/BM75*100 -> -14.285714 | BP75: =K75+O75+R75+V75+Z75+AD75+AH75+AL75+AP75+AT75+AX75+BB75 -> 5988 | BQ75: =J75+N75+S75+W75+AA75+AE75+AI75+AM75+AQ75+AU75+Table1[[#This Row],[MS-0225]]+Table1[[#This Row],[MS-0325]] -> 5737.5 | BR75: =(BP75-BQ75) -> 250.49998 | BS75: =(BR75)/BQ75*100 -> 4.3660127 | BT75: =M75+Q75+T75+X75+AB75+AF75+AJ75+AN75+AR75+AV75+AZ75+BD75 -> 1422 | BU75: =L75+P75+U75+Y75+AC75+AG75+AK75+AO75+AS75+AW75+BA75+BE75 -> 1552.5 | BV75: =(BT75-BU75) -> -130.5 | BW75: =(BV75)/BU75*100 -> -8.4057971 | BX75: 54 | BY75: =BX75/BH75 -> 0.11111111 | BZ75: 256.5 | CA75: =BZ75/BP75 -> 0.042835671 | CB75: =BH75/SUMIFS(BH$2:BH$398,G$2:G$398,G75) -> 0.1392113 | CC75: =BI75/SUMIFS(BI$2:BI$398,G$2:G$398,G75) -> 0.13669781 | CD75: =CB75-CC75 -> 0.0025134833 | CE75: =BL75/SUMIFS(BL$2:BL$398,G$2:G$398,G75) -> 0.12816694 | CF75: =BM75/SUMIFS(BM$2:BM$398,G$2:G$398,G75) -> 0.14919612 | CG75: =CE75-CF75 -> -0.021029177 | CH75: =BP75/SUMIFS(BP$2:BP$398,G$2:G$398,G75) -> 0.14139339 | CI75: =BQ75/SUMIFS(BQ$2:BQ$398,G$2:G$398,G75) -> 0.14009827 | CJ75: =CH75-CI75 -> 0.0012951207 | CK75: =BT75/SUMIFS(BT$2:BT$398,G$2:G$398,G75) -> 0.14838792 | CL75: =BU75/SUMIFS(BU$2:BU$398,G$2:G$398,G75) -> 0.14367174 | CM75: =CK75-CL75 -> 0.004716186 | CN75: =COUNTIFS(G$2:G$398,G75)*CH75 -> 0.98975375 | CO75: =COUNTIFS(G$2:G$398,G75)*CK75 -> 1.0387155
A76: 106218 | B76: IOC | C76: AKASH AUTO CENTRE INDIAN OIL PUMP(Revived in Jul18) | E76: EAST DELHI | F76: ALLIED_MASIH | G76: ALLIED_MASIH | H76: Mayur Vihar -Anand Vihar -Preet Vihar | I76: Bhanu Pratap | J76: 429 | K76: 461 | L76: 37 | M76: 27 | N76: 452 | O76: 470 | P76: 36 | Q76: 44 | R76: 437 | S76: 456.5 | T76: 35 | U76: 49.5 | V76: 501 | W76: 468 | X76: 35 | Y76: 36 | Z76: 517 | AA76: 468 | AB76: 33 | AC76: 54 | AD76: 476 | AE76: 414 | AF76: 34 | AG76: 36 | AH76: 500.5 | AI76: 486 | AJ76: 37.5 | AK76: 36 | AL76: 465 | AM76: 445.5 | AN76: 27 | AO76: 40.5 | AP76: 466.5 | AQ76: 438.5 | AR76: 29.5 | AS76: 31.5 | AT76: 466.5 | AU76: 427.5 | AV76: 33.5 | AW76: 40.5 | AX76: 438.5 | AY76: 378 | AZ76: 33.5 | BA76: 36 | BB76: 486 | BC76: 432 | BD76: 50 | BE76: 36 | BF76: 28.6401 | BG76: 77.2854 | BH76: =BB76 -> 486 | BI76: =BC76 -> 432 | BJ76: =(BH76-BI76) -> 54 | BK76: =(BJ76)/BI76*100 -> 12.5 | BL76: =BD76 -> 50 | BM76: =BE76 -> 36 | BN76: =(BL76-BM76) -> 14 | BO76: =(BN76)/BM76*100 -> 38.888889 | BP76: =K76+O76+R76+V76+Z76+AD76+AH76+AL76+AP76+AT76+AX76+BB76 -> 5685 | BQ76: =J76+N76+S76+W76+AA76+AE76+AI76+AM76+AQ76+AU76+Table1[[#This Row],[MS-0225]]+Table1[[#This Row],[MS-0325]] -> 5295 | BR76: =(BP76-BQ76) -> 390 | BS76: =(BR76)/BQ76*100 -> 7.3654391 | BT76: =M76+Q76+T76+X76+AB76+AF76+AJ76+AN76+AR76+AV76+AZ76+BD76 -> 419 | BU76: =L76+P76+U76+Y76+AC76+AG76+AK76+AO76+AS76+AW76+BA76+BE76 -> 469 | BV76: =(BT76-BU76) -> -50 | BW76: =(BV76)/BU76*100 -> -10.660981 | BX76: 0 | BY76: =BX76/BH76 -> 0 | BZ76: 0 | CA76: =BZ76/BP76 -> 0 | CB76: =BH76/SUMIFS(BH$2:BH$398,G$2:G$398,G76) -> 0.11768979 | CC76: =BI76/SUMIFS(BI$2:BI$398,G$2:G$398,G76) -> 0.11383399 | CD76: =CB76-CC76 -> 0.0038558009 | CE76: =BL76/SUMIFS(BL$2:BL$398,G$2:G$398,G76) -> 0.078431373 | CF76: =BM76/SUMIFS(BM$2:BM$398,G$2:G$398,G76) -> 0.053731343 | CG76: =CE76-CF76 -> 0.024700029 | CH76: =BP76/SUMIFS(BP$2:BP$398,G$2:G$398,G76) -> 0.11581527 | CI76: =BQ76/SUMIFS(BQ$2:BQ$398,G$2:G$398,G76) -> 0.11569345 | CJ76: =CH76-CI76 -> 0.00012182042 | CK76: =BT76/SUMIFS(BT$2:BT$398,G$2:G$398,G76) -> 0.053991729 | CL76: =BU76/SUMIFS(BU$2:BU$398,G$2:G$398,G76) -> 0.055460953 | CM76: =CK76-CL76 -> -0.0014692235 | CN76: =COUNTIFS(G$2:G$398,G76)*CH76 -> 0.92652217 | CO76: =COUNTIFS(G$2:G$398,G76)*CK76 -> 0.43193383
A77: 112420 | B77: BPC | C77: M.L.SETHI SERVICE STATION | D77: SECTOR 5 ROHINI DELHI | E77: NORTH WEST DELHI | F77: M.L.SETHI | G77: M.L.SETHI | H77: Rohini | I77: Abhinav | J77: 352 | K77: 425.5 | L77: 92 | M77: 96.5 | N77: 393.5 | O77: 441 | P77: 116.5 | Q77: 101 | R77: 422.5 | S77: 376.5 | T77: 101.5 | U77: 109.5 | V77: 431.5 | W77: 384 | X77: 102.5 | Y77: 108 | Z77: 462 | AA77: 399 | AB77: 108 | AC77: 117 | AD77: 439 | AE77: 382.5 | AF77: 111 | AG77: 109.5 | AH77: 471 | AI77: 406.5 | AJ77: 117 | AK77: 109.5 | AL77: 456 | AM77: 374 | AN77: 108 | AO77: 64 | AP77: 442.5 | AQ77: 378.5 | AR77: 85.5 | AS77: 77.5 | AT77: 415 | AU77: 377 | AV77: 97 | AW77: 105 | AX77: 450.5 | AY77: 352 | AZ77: 115.5 | BA77: 92 | BB77: 478 | BC77: 400 | BD77: 110 | BE77: 92 | BF77: 28.718 | BG77: 77.11032 | BH77: =BB77 -> 478 | BI77: =BC77 -> 400 | BJ77: =(BH77-BI77) -> 78 | BK77: =(BJ77)/BI77*100 -> 19.5 | BL77: =BD77 -> 110 | BM77: =BE77 -> 92 | BN77: =(BL77-BM77) -> 18 | BO77: =(BN77)/BM77*100 -> 19.565217 | BP77: =K77+O77+R77+V77+Z77+AD77+AH77+AL77+AP77+AT77+AX77+BB77 -> 5334.5 | BQ77: =J77+N77+S77+W77+AA77+AE77+AI77+AM77+AQ77+AU77+Table1[[#This Row],[MS-0225]]+Table1[[#This Row],[MS-0325]] -> 4575.5 | BR77: =(BP77-BQ77) -> 759 | BS77: =(BR77)/BQ77*100 -> 16.588351 | BT77: =M77+Q77+T77+X77+AB77+AF77+AJ77+AN77+AR77+AV77+AZ77+BD77 -> 1253.5 | BU77: =L77+P77+U77+Y77+AC77+AG77+AK77+AO77+AS77+AW77+BA77+BE77 -> 1192.5 | BV77: =(BT77-BU77) -> 61 | BW77: =(BV77)/BU77*100 -> 5.115304 | BX77: 30 | BY77: =BX77/BH77 -> 0.062761506 | BZ77: 134 | CA77: =BZ77/BP77 -> 0.025119505 | CB77: =BH77/SUMIFS(BH$2:BH$398,G$2:G$398,G77) -> 0.15592889 | CC77: =BI77/SUMIFS(BI$2:BI$398,G$2:G$398,G77) -> 0.15203345 | CD77: =CB77-CC77 -> 0.0038954386 | CE77: =BL77/SUMIFS(BL$2:BL$398,G$2:G$398,G77) -> 0.10541447 | CF77: =BM77/SUMIFS(BM$2:BM$398,G$2:G$398,G77) -> 0.091269841 | CG77: =CE77-CF77 -> 0.014144629 | CH77: =BP77/SUMIFS(BP$2:BP$398,G$2:G$398,G77) -> 0.15227724 | CI77: =BQ77/SUMIFS(BQ$2:BQ$398,G$2:G$398,G77) -> 0.14536241 | CJ77: =CH77-CI77 -> 0.0069148229 | CK77: =BT77/SUMIFS(BT$2:BT$398,G$2:G$398,G77) -> 0.10679446 | CL77: =BU77/SUMIFS(BU$2:BU$398,G$2:G$398,G77) -> 0.091762533 | CM77: =CK77-CL77 -> 0.015031929 | CN77: =COUNTIFS(G$2:G$398,G77)*CH77 -> 1.3704951 | CO77: =COUNTIFS(G$2:G$398,G77)*CK77 -> 0.96115016
A78: 41057006 | B78: HPC | C78: YASH FILLING STATION | D78: NAZAFGARH | E78: SOUTH WEST DELHI | F78: SHOKEEN_JAI SHREEKRISHNA_SHANTI | G78: SHOKEEN_JAI SHREEKRISHNA_SHANTI | H78: Nazafgarh-Kapashera | I78: Raj Doshi | J78: 469 | K78: 488 | L78: 87 | M78: 69 | N78: 494 | O78: 502 | P78: 103 | Q78: 92 | R78: 490 | S78: 465 | T78: 88 | U78: 85 | V78: 482 | W78: 491 | X78: 90 | Y78: 103 | Z78: 527 | AA78: 500 | AB78: 67 | AC78: 87 | AD78: 473 | AE78: 484 | AF78: 78 | AG78: 77 | AH78: 504 | AI78: 498 | AJ78: 62 | AK78: 99 | AL78: 472 | AM78: 484 | AN78: 78 | AO78: 77 | AP78: 457.5 | AQ78: 448 | AR78: 66.5 | AS78: 90 | AT78: 438 | AU78: 456 | AV78: 64 | AW78: 79 | AX78: 452 | AY78: 395 | AZ78: 72 | BA78: 89 | BB78: 476 | BC78: 473 | BD78: 52 | BE78: 77 | BF78: 28.611229 | BG78: 76.979244 | BH78: =BB78 -> 476 | BI78: =BC78 -> 473 | BJ78: =(BH78-BI78) -> 3 | BK78: =(BJ78)/BI78*100 -> 0.63424947 | BL78: =BD78 -> 52 | BM78: =BE78 -> 77 | BN78: =(BL78-BM78) -> -25 | BO78: =(BN78)/BM78*100 -> -32.467532 | BP78: =K78+O78+R78+V78+Z78+AD78+AH78+AL78+AP78+AT78+AX78+BB78 -> 5761.5 | BQ78: =J78+N78+S78+W78+AA78+AE78+AI78+AM78+AQ78+AU78+Table1[[#This Row],[MS-0225]]+Table1[[#This Row],[MS-0325]] -> 5657 | BR78: =(BP78-BQ78) -> 104.5 | BS78: =(BR78)/BQ78*100 -> 1.8472689 | BT78: =M78+Q78+T78+X78+AB78+AF78+AJ78+AN78+AR78+AV78+AZ78+BD78 -> 878.5 | BU78: =L78+P78+U78+Y78+AC78+AG78+AK78+AO78+AS78+AW78+BA78+BE78 -> 1053 | BV78: =(BT78-BU78) -> -174.5 | BW78: =(BV78)/BU78*100 -> -16.5717 | BX78: 0 | BY78: =BX78/BH78 -> 0 | BZ78: 0 | CA78: =BZ78/BP78 -> 0 | CB78: =BH78/SUMIFS(BH$2:BH$398,G$2:G$398,G78) -> 0.34795322 | CC78: =BI78/SUMIFS(BI$2:BI$398,G$2:G$398,G78) -> 0.35338065 | CD78: =CB78-CC78 -> -0.0054274336 | CE78: =BL78/SUMIFS(BL$2:BL$398,G$2:G$398,G78) -> 0.12807882 | CF78: =BM78/SUMIFS(BM$2:BM$398,G$2:G$398,G78) -> 0.16227608 | CG78: =CE78-CF78 -> -0.034197262 | CH78: =BP78/SUMIFS(BP$2:BP$398,G$2:G$398,G78) -> 0.36794712 | CI78: =BQ78/SUMIFS(BQ$2:BQ$398,G$2:G$398,G78) -> 0.34938085 | CJ78: =CH78-CI78 -> 0.018566274 | CK78: =BT78/SUMIFS(BT$2:BT$398,G$2:G$398,G78) -> 0.19301329 | CL78: =BU78/SUMIFS(BU$2:BU$398,G$2:G$398,G78) -> 0.19305161 | CM78: =CK78-CL78 -> -3.8316442e-05 | CN78: =COUNTIFS(G$2:G$398,G78)*CH78 -> 2.5756298 | CO78: =COUNTIFS(G$2:G$398,G78)*CK78 -> 1.351093
A79: 112435 | B79: BPC | C79: PAM FILLING STATION | D79: YAMUNA VIHAR DELHI | E79: NORTH EAST DELHI | F79: PAMFS | G79: PAMFS | H79: Wazirabad-Loni | I79: Bhanu Pratap | J79: 427.5 | K79: 457 | L79: 22.5 | M79: 27 | N79: 409.5 | O79: 485.5 | P79: 22.5 | Q79: 26.5 | R79: 437 | S79: 411.5 | T79: 27 | U79: 22.5 | V79: 489 | W79: 443 | X79: 35 | Y79: 27 | Z79: 492.5 | AA79: 424.5 | AB79: 35.5 | AC79: 27.5 | AD79: 482.5 | AE79: 463 | AF79: 31.5 | AG79: 27 | AH79: 504.5 | AI79: 472.5 | AJ79: 31.5 | AK79: 31.5 | AL79: 505 | AM79: 473 | AN79: 33 | AO79: 27 | AP79: 431.5 | AQ79: 443 | AR79: 26.5 | AS79: 27 | AT79: 461.5 | AU79: 458.5 | AV79: 30.5 | AW79: 31.5 | AX79: 450.5 | AY79: 414 | AZ79: 31.5 | BA79: 26 | BB79: 471.5 | BC79: 443 | BD79: 26.5 | BE79: 27 | BF79: 28.69704 | BG79: 77.27185 | BH79: =BB79 -> 471.5 | BI79: =BC79 -> 443 | BJ79: =(BH79-BI79) -> 28.5 | BK79: =(BJ79)/BI79*100 -> 6.4334086 | BL79: =BD79 -> 26.5 | BM79: =BE79 -> 27 | BN79: =(BL79-BM79) -> -0.5 | BO79: =(BN79)/BM79*100 -> -1.8518519 | BP79: =K79+O79+R79+V79+Z79+AD79+AH79+AL79+AP79+AT79+AX79+BB79 -> 5668 | BQ79: =J79+N79+S79+W79+AA79+AE79+AI79+AM79+AQ79+AU79+Table1[[#This Row],[MS-0225]]+Table1[[#This Row],[MS-0325]] -> 5283 | BR79: =(BP79-BQ79) -> 385 | BS79: =(BR79)/BQ79*100 -> 7.287526 | BT79: =M79+Q79+T79+X79+AB79+AF79+AJ79+AN79+AR79+AV79+AZ79+BD79 -> 362 | BU79: =L79+P79+U79+Y79+AC79+AG79+AK79+AO79+AS79+AW79+BA79+BE79 -> 319 | BV79: =(BT79-BU79) -> 43 | BW79: =(BV79)/BU79*100 -> 13.479624 | BX79: 0 | BY79: =BX79/BH79 -> 0 | BZ79: 0 | CA79: =BZ79/BP79 -> 0 | CB79: =BH79/SUMIFS(BH$2:BH$398,G$2:G$398,G79) -> 0.42268041 | CC79: =BI79/SUMIFS(BI$2:BI$398,G$2:G$398,G79) -> 0.43219512 | CD79: =CB79-CC79 -> -0.0095147096 | CE79: =BL79/SUMIFS(BL$2:BL$398,G$2:G$398,G79) -> 0.24423963 | CF79: =BM79/SUMIFS(BM$2:BM$398,G$2:G$398,G79) -> 0.3253012 | CG79: =CE79-CF79 -> -0.081061573 | CH79: =BP79/SUMIFS(BP$2:BP$398,G$2:G$398,G79) -> 0.44013046 | CI79: =BQ79/SUMIFS(BQ$2:BQ$398,G$2:G$398,G79) -> 0.42791187 | CJ79: =CH79-CI79 -> 0.012218581 | CK79: =BT79/SUMIFS(BT$2:BT$398,G$2:G$398,G79) -> 0.28730159 | CL79: =BU79/SUMIFS(BU$2:BU$398,G$2:G$398,G79) -> 0.26627713 | CM79: =CK79-CL79 -> 0.021024459 | CN79: =COUNTIFS(G$2:G$398,G79)*CH79 -> 0.88026091 | CO79: =COUNTIFS(G$2:G$398,G79)*CK79 -> 0.57460317
A80: 41056821 | B80: HPC | C80: DHAULA KUAN SERVICE STATION | D80: DHAULA KUAN | E80: SOUTH WEST DELHI | F80: White Patch_Dhaula Kuan_NH8 | G80: White Patch_Dhaula Kuan_NH8 | H80: Dwarka | I80: Raj Doshi | J80: 468 | K80: 464.5 | L80: 378 | M80: 396.5 | N80: 573 | O80: 589 | P80: 442 | Q80: 490 | R80: 577.5 | S80: 526.5 | T80: 404.5 | U80: 427.5 | V80: 543.5 | W80: 504 | X80: 371.5 | Y80: 324 | Z80: 597 | AA80: 527 | AB80: 443 | AC80: 421 | AD80: 528 | AE80: 545.5 | AF80: 441 | AG80: 361.5 | AH80: 572 | AI80: 503 | AJ80: 460 | AK80: 419 | AL80: 554 | AM80: 536 | AN80: 364 | AO80: 375 | AP80: 537.5 | AQ80: 535.5 | AR80: 380.5 | AS80: 383.5 | AT80: 513 | AU80: 535.5 | AV80: 343 | AW80: 412.5 | AX80: 465 | AY80: 465 | AZ80: 319 | BA80: 385 | BB80: 470 | BC80: 553.5 | BD80: 268 | BE80: 450.5 | BF80: 28.59026 | BG80: 77.15751 | BH80: =BB80 -> 470 | BI80: =BC80 -> 553.5 | BJ80: =(BH80-BI80) -> -83.5 | BK80: =(BJ80)/BI80*100 -> -15.085818 | BL80: =BD80 -> 268 | BM80: =BE80 -> 450.5 | BN80: =(BL80-BM80) -> -182.5 | BO80: =(BN80)/BM80*100 -> -40.510544 | BP80: =K80+O80+R80+V80+Z80+AD80+AH80+AL80+AP80+AT80+AX80+BB80 -> 6411 | BQ80: =J80+N80+S80+W80+AA80+AE80+AI80+AM80+AQ80+AU80+Table1[[#This Row],[MS-0225]]+Table1[[#This Row],[MS-0325]] -> 6272.5 | BR80: =(BP80-BQ80) -> 138.5 | BS80: =(BR80)/BQ80*100 -> 2.208051 | BT80: =M80+Q80+T80+X80+AB80+AF80+AJ80+AN80+AR80+AV80+AZ80+BD80 -> 4681 | BU80: =L80+P80+U80+Y80+AC80+AG80+AK80+AO80+AS80+AW80+BA80+BE80 -> 4779.5 | BV80: =(BT80-BU80) -> -98.5 | BW80: =(BV80)/BU80*100 -> -2.060885 | BX80: 0 | BY80: =BX80/BH80 -> 0 | BZ80: 0 | CA80: =BZ80/BP80 -> 0 | CB80: =BH80/SUMIFS(BH$2:BH$398,G$2:G$398,G80) -> 0.32959327 | CC80: =BI80/SUMIFS(BI$2:BI$398,G$2:G$398,G80) -> 0.37487301 | CD80: =CB80-CC80 -> -0.045279743 | CE80: =BL80/SUMIFS(BL$2:BL$398,G$2:G$398,G80) -> 0.42438638 | CF80: =BM80/SUMIFS(BM$2:BM$398,G$2:G$398,G80) -> 0.5385535 | CG80: =CE80-CF80 -> -0.11416712 | CH80: =BP80/SUMIFS(BP$2:BP$398,G$2:G$398,G80) -> 0.35509153 | CI80: =BQ80/SUMIFS(BQ$2:BQ$398,G$2:G$398,G80) -> 0.36524296 | CJ80: =CH80-CI80 -> -0.010151433 | CK80: =BT80/SUMIFS(BT$2:BT$398,G$2:G$398,G80) -> 0.51658114 | CL80: =BU80/SUMIFS(BU$2:BU$398,G$2:G$398,G80) -> 0.51232715 | CM80: =CK80-CL80 -> 0.0042539881 | CN80: =COUNTIFS(G$2:G$398,G80)*CH80 -> 1.0652746 | CO80: =COUNTIFS(G$2:G$398,G80)*CK80 -> 1.5497434
A81: 112383 | B81: BPC | C81: AIRPORT SERVICE STATION | D81: KALKAJI,NEHRU PLACE | E81: SOUTH EAST DELHI | F81: AIRPORT_SINGH_ANUP | G81: AIRPORT_SINGH_ANUP | H81: Outer Ring Road | I81: Bhanu Pratap | J81: 463.5 | K81: 499.5 | L81: 112.5 | M81: 112.5 | N81: 517.5 | O81: 517.5 | P81: 148.5 | Q81: 112.5 | R81: 486 | S81: 499.5 | T81: 90 | U81: 130.5 | V81: 517.5 | W81: 526.5 | X81: 94.5 | Y81: 121.5 | Z81: 486 | AA81: 513 | AB81: 90 | AC81: 117 | AD81: 477 | AE81: 490.5 | AF81: 99 | AG81: 121.5 | AH81: 490.5 | AI81: 486 | AJ81: 85.5 | AK81: 108 | AL81: 445.5 | AM81: 450 | AN81: 76.5 | AO81: 90 | AP81: 445.5 | AQ81: 459 | AR81: 58.5 | AS81: 99 | AT81: 432 | AU81: 454.5 | AV81: 90 | AW81: 85.5 | AX81: 463.5 | AY81: 423 | AZ81: 94.5 | BA81: 99 | BB81: 468 | BC81: 486 | BD81: 90 | BE81: 108 | BF81: 28.54802 | BG81: 77.25614 | BH81: =BB81 -> 468 | BI81: =BC81 -> 486 | BJ81: =(BH81-BI81) -> -18 | BK81: =(BJ81)/BI81*100 -> -3.7037037 | BL81: =BD81 -> 90 | BM81: =BE81 -> 108 | BN81: =(BL81-BM81) -> -18 | BO81: =(BN81)/BM81*100 -> -16.666667 | BP81: =K81+O81+R81+V81+Z81+AD81+AH81+AL81+AP81+AT81+AX81+BB81 -> 5728.5 | BQ81: =J81+N81+S81+W81+AA81+AE81+AI81+AM81+AQ81+AU81+Table1[[#This Row],[MS-0225]]+Table1[[#This Row],[MS-0325]] -> 5769 | BR81: =(BP81-BQ81) -> -40.500001 | BS81: =(BR81)/BQ81*100 -> -0.7020281 | BT81: =M81+Q81+T81+X81+AB81+AF81+AJ81+AN81+AR81+AV81+AZ81+BD81 -> 1093.5 | BU81: =L81+P81+U81+Y81+AC81+AG81+AK81+AO81+AS81+AW81+BA81+BE81 -> 1341 | BV81: =(BT81-BU81) -> -247.5 | BW81: =(BV81)/BU81*100 -> -18.456376 | BX81: 40.5 | BY81: =BX81/BH81 -> 0.086538462 | BZ81: 198 | CA81: =BZ81/BP81 -> 0.034564022 | CB81: =BH81/SUMIFS(BH$2:BH$398,G$2:G$398,G81) -> 0.22429907 | CC81: =BI81/SUMIFS(BI$2:BI$398,G$2:G$398,G81) -> 0.24884793 | CD81: =CB81-CC81 -> -0.024548861 | CE81: =BL81/SUMIFS(BL$2:BL$398,G$2:G$398,G81) -> 0.22304833 | CF81: =BM81/SUMIFS(BM$2:BM$398,G$2:G$398,G81) -> 0.24827586 | CG81: =CE81-CF81 -> -0.025227535 | CH81: =BP81/SUMIFS(BP$2:BP$398,G$2:G$398,G81) -> 0.23435678 | CI81: =BQ81/SUMIFS(BQ$2:BQ$398,G$2:G$398,G81) -> 0.24266005 | CJ81: =CH81-CI81 -> -0.0083032662 | CK81: =BT81/SUMIFS(BT$2:BT$398,G$2:G$398,G81) -> 0.23738196 | CL81: =BU81/SUMIFS(BU$2:BU$398,G$2:G$398,G81) -> 0.24058127 | CM81: =CK81-CL81 -> -0.0031993099 | CN81: =COUNTIFS(G$2:G$398,G81)*CH81 -> 1.1717839 | CO81: =COUNTIFS(G$2:G$398,G81)*CK81 -> 1.1869098
A82: 112454 | B82: BPC | C82: SOAMI SERVICE CENTRE | D82: SOAMI NAGAR DELHI | E82: SOUTH DELHI | F82: SAOMI SS | G82: SAOMI SS | H82: Outer Ring Road | I82: Raj Doshi | J82: 427.5 | K82: 440 | L82: 112.5 | M82: 100 | N82: 468 | O82: 485 | P82: 126 | Q82: 95 | R82: 435 | S82: 427.5 | T82: 85 | U82: 112.5 | V82: 490 | W82: 477 | X82: 90 | Y82: 117 | Z82: 475 | AA82: 450 | AB82: 85 | AC82: 108 | AD82: 484.5 | AE82: 436.5 | AF82: 93.5 | AG82: 121.5 | AH82: 465 | AI82: 432 | AJ82: 95 | AK82: 126 | AL82: 435 | AM82: 409.5 | AN82: 85 | AO82: 94.5 | AP82: 460 | AQ82: 443.5 | AR82: 80 | AS82: 76.5 | AT82: 423 | AU82: 439 | AV82: 75 | AW82: 99 | AX82: 400 | AY82: 383.5 | AZ82: 80 | BA82: 94.5 | BB82: 465 | BC82: 420 | BD82: 95 | BE82: 100 | BF82: 28.54221 | BG82: 77.22102 | BH82: =BB82 -> 465 | BI82: =BC82 -> 420 | BJ82: =(BH82-BI82) -> 45 | BK82: =(BJ82)/BI82*100 -> 10.714286 | BL82: =BD82 -> 95 | BM82: =BE82 -> 100 | BN82: =(BL82-BM82) -> -5 | BO82: =(BN82)/BM82*100 -> -5 | BP82: =K82+O82+R82+V82+Z82+AD82+AH82+AL82+AP82+AT82+AX82+BB82 -> 5457.5 | BQ82: =J82+N82+S82+W82+AA82+AE82+AI82+AM82+AQ82+AU82+Table1[[#This Row],[MS-0225]]+Table1[[#This Row],[MS-0325]] -> 5214 | BR82: =(BP82-BQ82) -> 243.49999 | BS82: =(BR82)/BQ82*100 -> 4.6701187 | BT82: =M82+Q82+T82+X82+AB82+AF82+AJ82+AN82+AR82+AV82+AZ82+BD82 -> 1058.5 | BU82: =L82+P82+U82+Y82+AC82+AG82+AK82+AO82+AS82+AW82+BA82+BE82 -> 1288 | BV82: =(BT82-BU82) -> -229.5 | BW82: =(BV82)/BU82*100 -> -17.818323 | BX82: 40 | BY82: =BX82/BH82 -> 0.086021505 | BZ82: 229.5 | CA82: =BZ82/BP82 -> 0.042052222 | CB82: =BH82/SUMIFS(BH$2:BH$398,G$2:G$398,G82) -> 0.2621195 | CC82: =BI82/SUMIFS(BI$2:BI$398,G$2:G$398,G82) -> 0.26095061 | CD82: =CB82-CC82 -> 0.0011688982 | CE82: =BL82/SUMIFS(BL$2:BL$398,G$2:G$398,G82) -> 0.31879195 | CF82: =BM82/SUMIFS(BM$2:BM$398,G$2:G$398,G82) -> 0.30257186 | CG82: =CE82-CF82 -> 0.016220085 | CH82: =BP82/SUMIFS(BP$2:BP$398,G$2:G$398,G82) -> 0.25658807 | CI82: =BQ82/SUMIFS(BQ$2:BQ$398,G$2:G$398,G82) -> 0.25790177 | CJ82: =CH82-CI82 -> -0.0013136941 | CK82: =BT82/SUMIFS(BT$2:BT$398,G$2:G$398,G82) -> 0.28043449 | CL82: =BU82/SUMIFS(BU$2:BU$398,G$2:G$398,G82) -> 0.2913368 | CM82: =CK82-CL82 -> -0.010902307 | CN82: =COUNTIFS(G$2:G$398,G82)*CH82 -> 0.76976422 | CO82: =COUNTIFS(G$2:G$398,G82)*CK82 -> 0.84130348
A83: 231563 | B83: IOC | C83: GLOBAL PETRO | D83: BHIKAJI CAMA PLACE | E83: NEW DELHI | F83: White Patch_Bhikaji Kama to South Ex RING Road | G83: White Patch_Bhikaji Kama to South Ex RING Road | H83: Inner Ring Road | I83: Bhanu Pratap | J83: 465 | K83: 508 | L83: 315 | M83: 240 | N83: 520 | O83: 539 | P83: 300 | Q83: 253 | R83: 531 | S83: 510 | T83: 261 | U83: 290 | V83: 512.5 | W83: 475 | X83: 223.5 | Y83: 265 | Z83: 504 | AA83: 490 | AB83: 200 | AC83: 270 | AD83: 484 | AE83: 475 | AF83: 212 | AG83: 245 | AH83: 529 | AI83: 515 | AJ83: 232 | AK83: 245 | AL83: 520 | AM83: 510 | AN83: 216 | AO83: 210 | AP83: 494 | AQ83: 504.5 | AR83: 198 | AS83: 203.5 | AT83: 470 | AU83: 482 | AV83: 216 | AW83: 200 | AX83: 461 | AY83: 494 | AZ83: 208 | BA83: 254 | BB83: 461 | BC83: 494 | BD83: 225 | BE83: 232 | BF83: 28.5713 | BG83: 77.1866 | BH83: =BB83 -> 461 | BI83: =BC83 -> 494 | BJ83: =(BH83-BI83) -> -33 | BK83: =(BJ83)/BI83*100 -> -6.6801619 | BL83: =BD83 -> 225 | BM83: =BE83 -> 232 | BN83: =(BL83-BM83) -> -7 | BO83: =(BN83)/BM83*100 -> -3.0172414 | BP83: =K83+O83+R83+V83+Z83+AD83+AH83+AL83+AP83+AT83+AX83+BB83 -> 6013.5 | BQ83: =J83+N83+S83+W83+AA83+AE83+AI83+AM83+AQ83+AU83+Table1[[#This Row],[MS-0225]]+Table1[[#This Row],[MS-0325]] -> 5934.5 | BR83: =(BP83-BQ83) -> 79 | BS83: =(BR83)/BQ83*100 -> 1.3311989 | BT83: =M83+Q83+T83+X83+AB83+AF83+AJ83+AN83+AR83+AV83+AZ83+BD83 -> 2684.5 | BU83: =L83+P83+U83+Y83+AC83+AG83+AK83+AO83+AS83+AW83+BA83+BE83 -> 3029.5 | BV83: =(BT83-BU83) -> -345 | BW83: =(BV83)/BU83*100 -> -11.388018 | BX83: 0 | BY83: =BX83/BH83 -> 0 | BZ83: 0 | CA83: =BZ83/BP83 -> 0 | CB83: =BH83/SUMIFS(BH$2:BH$398,G$2:G$398,G83) -> 0.45508391 | CC83: =BI83/SUMIFS(BI$2:BI$398,G$2:G$398,G83) -> 0.46559849 | CD83: =CB83-CC83 -> -0.010514583 | CE83: =BL83/SUMIFS(BL$2:BL$398,G$2:G$398,G83) -> 0.44554455 | CF83: =BM83/SUMIFS(BM$2:BM$398,G$2:G$398,G83) -> 0.42028986 | CG83: =CE83-CF83 -> 0.025254699 | CH83: =BP83/SUMIFS(BP$2:BP$398,G$2:G$398,G83) -> 0.46659683 | CI83: =BQ83/SUMIFS(BQ$2:BQ$398,G$2:G$398,G83) -> 0.47485497 | CJ83: =CH83-CI83 -> -0.0082581367 | CK83: =BT83/SUMIFS(BT$2:BT$398,G$2:G$398,G83) -> 0.45662528 | CL83: =BU83/SUMIFS(BU$2:BU$398,G$2:G$398,G83) -> 0.46661533 | CM83: =CK83-CL83 -> -0.009990049 | CN83: =COUNTIFS(G$2:G$398,G83)*CH83 -> 1.3997905 | CO83: =COUNTIFS(G$2:G$398,G83)*CK83 -> 1.3698758
A84: 186864 | B84: IOC | C84: CITY SERVICE CENTRE | D84: MANGOLPURI(CSC) | E84: NORTH WEST DELHI | F84: GANPATI | G84: GANPATI | H84: Rohini | I84: Abhinav | J84: 276 | K84: 316 | L84: 48 | M84: 56 | N84: 288 | O84: 332 | P84: 72 | Q84: 52 | R84: 308 | S84: 280 | T84: 52 | U84: 68 | V84: 332 | W84: 304 | X84: 76 | Y84: 68 | Z84: 360 | AA84: 292 | AB84: 60 | AC84: 68 | AD84: 316 | AE84: 300 | AF84: 68 | AG84: 60 | AH84: 368 | AI84: 308 | AJ84: 64 | AK84: 76 | AL84: 338 | AM84: 308 | AN84: 52 | AO84: 64 | AP84: 340 | AQ84: 292 | AR84: 56 | AS84: 80 | AT84: 320 | AU84: 288 | AV84: 64 | AW84: 84 | AX84: 312 | AY84: 280 | AZ84: 60 | BA84: 68 | BB84: 352 | BC84: 322 | BD84: 92 | BE84: 52 | BF84: 28.6882 | BG84: 77.0896 | BH84: =BB84 -> 352 | BI84: =BC84 -> 322 | BJ84: =(BH84-BI84) -> 30 | BK84: =(BJ84)/BI84*100 -> 9.3167702 | BL84: =BD84 -> 92 | BM84: =BE84 -> 52 | BN84: =(BL84-BM84) -> 40 | BO84: =(BN84)/BM84*100 -> 76.923077 | BP84: =K84+O84+R84+V84+Z84+AD84+AH84+AL84+AP84+AT84+AX84+BB84 -> 3994 | BQ84: =J84+N84+S84+W84+AA84+AE84+AI84+AM84+AQ84+AU84+Table1[[#This Row],[MS-0225]]+Table1[[#This Row],[MS-0325]] -> 3538 | BR84: =(BP84-BQ84) -> 456 | BS84: =(BR84)/BQ84*100 -> 12.888638 | BT84: =M84+Q84+T84+X84+AB84+AF84+AJ84+AN84+AR84+AV84+AZ84+BD84 -> 752 | BU84: =L84+P84+U84+Y84+AC84+AG84+AK84+AO84+AS84+AW84+BA84+BE84 -> 808 | BV84: =(BT84-BU84) -> -56 | BW84: =(BV84)/BU84*100 -> -6.9306931 | BX84: 0 | BY84: =BX84/BH84 -> 0 | BZ84: 0 | CA84: =BZ84/BP84 -> 0 | CB84: =BH84/SUMIFS(BH$2:BH$398,G$2:G$398,G84) -> 0.40320733 | CC84: =BI84/SUMIFS(BI$2:BI$398,G$2:G$398,G84) -> 0.35404068 | CD84: =CB84-CC84 -> 0.049166649 | CE84: =BL84/SUMIFS(BL$2:BL$398,G$2:G$398,G84) -> 0.19287212 | CF84: =BM84/SUMIFS(BM$2:BM$398,G$2:G$398,G84) -> 0.12855377 | CG84: =CE84-CF84 -> 0.064318347 | CH84: =BP84/SUMIFS(BP$2:BP$398,G$2:G$398,G84) -> 0.39836425 | CI84: =BQ84/SUMIFS(BQ$2:BQ$398,G$2:G$398,G84) -> 0.35403012 | CJ84: =CH84-CI84 -> 0.044334133 | CK84: =BT84/SUMIFS(BT$2:BT$398,G$2:G$398,G84) -> 0.1498605 | CL84: =BU84/SUMIFS(BU$2:BU$398,G$2:G$398,G84) -> 0.14422133 | CM84: =CK84-CL84 -> 0.0056391724 | CN84: =COUNTIFS(G$2:G$398,G84)*CH84 -> 1.1950928 | CO84: =COUNTIFS(G$2:G$398,G84)*CK84 -> 0.44958151
A85: 163741 | B85: BPC | C85: B.S DWARKA | D85: SECTOR-11,DWARAKA | E85: SOUTH WEST DELHI | F85: BS DWARKA | G85: BS DWARKA | H85: Dwarka | I85: Raj Doshi | J85: 372 | K85: 436 | L85: 84 | M85: 92 | N85: 432 | O85: 440 | P85: 108 | Q85: 88 | R85: 404 | S85: 364 | T85: 88 | U85: 104 | V85: 468 | W85: 404 | X85: 84 | Y85: 100 | Z85: 476 | AA85: 432 | AB85: 88 | AC85: 96 | AD85: 428 | AE85: 396 | AF85: 88 | AG85: 96 | AH85: 448 | AI85: 416 | AJ85: 80 | AK85: 100 | AL85: 416 | AM85: 368 | AN85: 76 | AO85: 76 | AP85: 428 | AQ85: 412 | AR85: 64 | AS85: 80 | AT85: 412 | AU85: 388 | AV85: 68 | AW85: 80 | AX85: 400 | AY85: 340 | AZ85: 80 | BA85: 80 | BB85: 460 | BC85: 400 | BD85: 80 | BE85: 80 | BF85: 28.59127 | BG85: 77.04699 | BH85: =BB85 -> 460 | BI85: =BC85 -> 400 | BJ85: =(BH85-BI85) -> 60 | BK85: =(BJ85)/BI85*100 -> 15 | BL85: =BD85 -> 80 | BM85: =BE85 -> 80 | BN85: =(BL85-BM85) -> 0 | BO85: =(BN85)/BM85*100 -> 0 | BP85: =K85+O85+R85+V85+Z85+AD85+AH85+AL85+AP85+AT85+AX85+BB85 -> 5216 | BQ85: =J85+N85+S85+W85+AA85+AE85+AI85+AM85+AQ85+AU85+Table1[[#This Row],[MS-0225]]+Table1[[#This Row],[MS-0325]] -> 4724 | BR85: =(BP85-BQ85) -> 492 | BS85: =(BR85)/BQ85*100 -> 10.414903 | BT85: =M85+Q85+T85+X85+AB85+AF85+AJ85+AN85+AR85+AV85+AZ85+BD85 -> 976 | BU85: =L85+P85+U85+Y85+AC85+AG85+AK85+AO85+AS85+AW85+BA85+BE85 -> 1084 | BV85: =(BT85-BU85) -> -108 | BW85: =(BV85)/BU85*100 -> -9.9630996 | BX85: 40 | BY85: =BX85/BH85 -> 0.086956522 | BZ85: 204 | CA85: =BZ85/BP85 -> 0.039110429 | CB85: =BH85/SUMIFS(BH$2:BH$398,G$2:G$398,G85) -> 0.26467204 | CC85: =BI85/SUMIFS(BI$2:BI$398,G$2:G$398,G85) -> 0.26024723 | CD85: =CB85-CC85 -> 0.004424802 | CE85: =BL85/SUMIFS(BL$2:BL$398,G$2:G$398,G85) -> 0.24691358 | CF85: =BM85/SUMIFS(BM$2:BM$398,G$2:G$398,G85) -> 0.26229508 | CG85: =CE85-CF85 -> -0.015381502 | CH85: =BP85/SUMIFS(BP$2:BP$398,G$2:G$398,G85) -> 0.26279726 | CI85: =BQ85/SUMIFS(BQ$2:BQ$398,G$2:G$398,G85) -> 0.26155081 | CJ85: =CH85-CI85 -> 0.0012464467 | CK85: =BT85/SUMIFS(BT$2:BT$398,G$2:G$398,G85) -> 0.26507333 | CL85: =BU85/SUMIFS(BU$2:BU$398,G$2:G$398,G85) -> 0.28818291 | CM85: =CK85-CL85 -> -0.023109576 | CN85: =COUNTIFS(G$2:G$398,G85)*CH85 -> 1.051189 | CO85: =COUNTIFS(G$2:G$398,G85)*CK85 -> 1.0602933
A86: 41056845 | B86: HPC | C86: VICTORY SERVICE STATION | D86: GT RD,SHAHDARA | E86: SHAHDARA | F86: DEEPAK AUTOMOBILES | G86: DEEPAK AUTOMOBILES | H86: Old GT Road (NH1) | I86: Bhanu Pratap | J86: 448 | K86: 456.5 | L86: 363 | M86: 312.5 | N86: 439 | O86: 505 | P86: 398 | Q86: 330 | R86: 486 | S86: 470 | T86: 301 | U86: 354 | V86: 451 | W86: 452.5 | X86: 300 | Y86: 352.5 | Z86: 450.5 | AA86: 445.5 | AB86: 291.5 | AC86: 325.5 | AD86: 431 | AE86: 445.5 | AF86: 286 | AG86: 332.5 | AH86: 472 | AI86: 424 | AJ86: 356 | AK86: 364 | AL86: 477 | AM86: 462 | AN86: 310 | AO86: 338 | AP86: 457 | AQ86: 404 | AR86: 302 | AS86: 360 | AT86: 427.5 | AU86: 422 | AV86: 253.5 | AW86: 319 | AX86: 425 | AY86: 406.5 | AZ86: 278 | BA86: 303.5 | BB86: 456.5 | BC86: 449.5 | BD86: 267.5 | BE86: 331.5 | BF86: 28.6766 | BG86: 77.31669 | BH86: =BB86 -> 456.5 | BI86: =BC86 -> 449.5 | BJ86: =(BH86-BI86) -> 7 | BK86: =(BJ86)/BI86*100 -> 1.5572859 | BL86: =BD86 -> 267.5 | BM86: =BE86 -> 331.5 | BN86: =(BL86-BM86) -> -64 | BO86: =(BN86)/BM86*100 -> -19.306184 | BP86: =K86+O86+R86+V86+Z86+AD86+AH86+AL86+AP86+AT86+AX86+BB86 -> 5495 | BQ86: =J86+N86+S86+W86+AA86+AE86+AI86+AM86+AQ86+AU86+Table1[[#This Row],[MS-0225]]+Table1[[#This Row],[MS-0325]] -> 5268.5 | BR86: =(BP86-BQ86) -> 226.5 | BS86: =(BR86)/BQ86*100 -> 4.2991364 | BT86: =M86+Q86+T86+X86+AB86+AF86+AJ86+AN86+AR86+AV86+AZ86+BD86 -> 3588 | BU86: =L86+P86+U86+Y86+AC86+AG86+AK86+AO86+AS86+AW86+BA86+BE86 -> 4141.5 | BV86: =(BT86-BU86) -> -553.5 | BW86: =(BV86)/BU86*100 -> -13.364723 | BX86: 0 | BY86: =BX86/BH86 -> 0 | BZ86: 0 | CA86: =BZ86/BP86 -> 0 | CB86: =BH86/SUMIFS(BH$2:BH$398,G$2:G$398,G86) -> 0.31668401 | CC86: =BI86/SUMIFS(BI$2:BI$398,G$2:G$398,G86) -> 0.31566011 | CD86: =CB86-CC86 -> 0.0010238974 | CE86: =BL86/SUMIFS(BL$2:BL$398,G$2:G$398,G86) -> 0.38351254 | CF86: =BM86/SUMIFS(BM$2:BM$398,G$2:G$398,G86) -> 0.34567258 | CG86: =CE86-CF86 -> 0.037839969 | CH86: =BP86/SUMIFS(BP$2:BP$398,G$2:G$398,G86) -> 0.31500803 | CI86: =BQ86/SUMIFS(BQ$2:BQ$398,G$2:G$398,G86) -> 0.30933858 | CJ86: =CH86-CI86 -> 0.0056694472 | CK86: =BT86/SUMIFS(BT$2:BT$398,G$2:G$398,G86) -> 0.3552827 | CL86: =BU86/SUMIFS(BU$2:BU$398,G$2:G$398,G86) -> 0.33215704 | CM86: =CK86-CL86 -> 0.023125666 | CN86: =COUNTIFS(G$2:G$398,G86)*CH86 -> 1.5750401 | CO86: =COUNTIFS(G$2:G$398,G86)*CK86 -> 1.7764135
A87: 112417 | B87: BPC | C87: LAXMI FILLING STATION | D87: VIKAS PURI(PVR) | E87: WEST DELHI | F87: VAIBHAV-KARTIK-LAXMI | G87: VAIBHAV-KARTIK-LAXMI | H87: Punjabi Bagh | I87: Abhinav | J87: 435.00001 | K87: 442 | L87: 45 | M87: 40 | N87: 424.50001 | O87: 434 | P87: 49.5 | Q87: 40 | R87: 447.5 | S87: 435.00001 | T87: 40.5 | U87: 45 | V87: 479.5 | W87: 455 | X87: 40.5 | Y87: 49 | Z87: 490.5 | AA87: 459.5 | AB87: 35.5 | AC87: 44.5 | AD87: 458 | AE87: 421.5 | AF87: 40 | AG87: 40.5 | AH87: 494 | AI87: 441 | AJ87: 36 | AK87: 45 | AL87: 434.5 | AM87: 418.50001 | AN87: 35.5 | AO87: 31.5 | AP87: 449 | AQ87: 426 | AR87: 27 | AS87: 36 | AT87: 414.5 | AU87: 410 | AV87: 31.5 | AW87: 36 | AX87: 425.5 | AY87: 376 | AZ87: 36.5 | BA87: 36 | BB87: 446.5 | BC87: 422.5 | BD87: 36 | BE87: 35.5 | BF87: 28.64025 | BG87: 77.07491 | BH87: =BB87 -> 446.5 | BI87: =BC87 -> 422.5 | BJ87: =(BH87-BI87) -> 24 | BK87: =(BJ87)/BI87*100 -> 5.6804734 | BL87: =BD87 -> 36 | BM87: =BE87 -> 35.5 | BN87: =(BL87-BM87) -> 0.5 | BO87: =(BN87)/BM87*100 -> 1.4084507 | BP87: =K87+O87+R87+V87+Z87+AD87+AH87+AL87+AP87+AT87+AX87+BB87 -> 5415.5 | BQ87: =J87+N87+S87+W87+AA87+AE87+AI87+AM87+AQ87+AU87+Table1[[#This Row],[MS-0225]]+Table1[[#This Row],[MS-0325]] -> 5124.5 | BR87: =(BP87-BQ87) -> 290.99997 | BS87: =(BR87)/BQ87*100 -> 5.6786021 | BT87: =M87+Q87+T87+X87+AB87+AF87+AJ87+AN87+AR87+AV87+AZ87+BD87 -> 439 | BU87: =L87+P87+U87+Y87+AC87+AG87+AK87+AO87+AS87+AW87+BA87+BE87 -> 493.5 | BV87: =(BT87-BU87) -> -54.5 | BW87: =(BV87)/BU87*100 -> -11.043566 | BX87: 51 | BY87: =BX87/BH87 -> 0.11422172 | BZ87: 317.5 | CA87: =BZ87/BP87 -> 0.058628012 | CB87: =BH87/SUMIFS(BH$2:BH$398,G$2:G$398,G87) -> 0.18128299 | CC87: =BI87/SUMIFS(BI$2:BI$398,G$2:G$398,G87) -> 0.17917727 | CD87: =CB87-CC87 -> 0.0021057194 | CE87: =BL87/SUMIFS(BL$2:BL$398,G$2:G$398,G87) -> 0.13980583 | CF87: =BM87/SUMIFS(BM$2:BM$398,G$2:G$398,G87) -> 0.1109375 | CG87: =CE87-CF87 -> 0.028868325 | CH87: =BP87/SUMIFS(BP$2:BP$398,G$2:G$398,G87) -> 0.183455 | CI87: =BQ87/SUMIFS(BQ$2:BQ$398,G$2:G$398,G87) -> 0.1795267 | CJ87: =CH87-CI87 -> 0.0039282997 | CK87: =BT87/SUMIFS(BT$2:BT$398,G$2:G$398,G87) -> 0.12651297 | CL87: =BU87/SUMIFS(BU$2:BU$398,G$2:G$398,G87) -> 0.12296001 | CM87: =CK87-CL87 -> 0.0035529583 | CN87: =COUNTIFS(G$2:G$398,G87)*CH87 -> 0.73382002 | CO87: =COUNTIFS(G$2:G$398,G87)*CK87 -> 0.50605187
A88: 102106 | B88: IOC | C88: VEER SERVICE STATION | D88: MAJNU-KA-TILA | E88: CENTRAL DELHI | F88: RAJINDER-RS BHOLA | G88: White Patch- Outer Ring Road | H88: Outer Ring Road | I88: Abhinav | J88: 409.5 | K88: 435 | L88: 256.5 | M88: 283 | N88: 477 | O88: 477 | P88: 333 | Q88: 281 | R88: 456 | S88: 447.5 | T88: 264 | U88: 292.5 | V88: 514.5 | W88: 445 | X88: 167.5 | Y88: 221 | Z88: 508.5 | AA88: 464.5 | AB88: 229.5 | AC88: 235.5 | AD88: 465.5 | AE88: 443.5 | AF88: 270.5 | AG88: 210.5 | AH88: 546 | AI88: 471 | AJ88: 330 | AK88: 249 | AL88: 488 | AM88: 457 | AN88: 246 | AO88: 241 | AP88: 418 | AQ88: 426.5 | AR88: 300 | AS88: 247.5 | AT88: 394 | AU88: 456 | AV88: 286 | AW88: 274 | AX88: 369.5 | AY88: 393 | AZ88: 214.5 | BA88: 297 | BB88: 396 | BC88: 436 | BD88: 244 | BE88: 210 | BF88: 28.701 | BG88: 77.2271 | BH88: =BB88 -> 396 | BI88: =BC88 -> 436 | BJ88: =(BH88-BI88) -> -40 | BK88: =(BJ88)/BI88*100 -> -9.1743119 | BL88: =BD88 -> 244 | BM88: =BE88 -> 210 | BN88: =(BL88-BM88) -> 34 | BO88: =(BN88)/BM88*100 -> 16.190476 | BP88: =K88+O88+R88+V88+Z88+AD88+AH88+AL88+AP88+AT88+AX88+BB88 -> 5468 | BQ88: =J88+N88+S88+W88+AA88+AE88+AI88+AM88+AQ88+AU88+Table1[[#This Row],[MS-0225]]+Table1[[#This Row],[MS-0325]] -> 5326.5 | BR88: =(BP88-BQ88) -> 141.5 | BS88: =(BR88)/BQ88*100 -> 2.6565287 | BT88: =M88+Q88+T88+X88+AB88+AF88+AJ88+AN88+AR88+AV88+AZ88+BD88 -> 3116 | BU88: =L88+P88+U88+Y88+AC88+AG88+AK88+AO88+AS88+AW88+BA88+BE88 -> 3067.5 | BV88: =(BT88-BU88) -> 48.5 | BW88: =(BV88)/BU88*100 -> 1.5810921 | BX88: 0 | BY88: =BX88/BH88 -> 0 | BZ88: 0 | CA88: =BZ88/BP88 -> 0 | CB88: =BH88/SUMIFS(BH$2:BH$398,G$2:G$398,G88) -> 0.29988641 | CC88: =BI88/SUMIFS(BI$2:BI$398,G$2:G$398,G88) -> 0.33118116 | CD88: =CB88-CC88 -> -0.031294756 | CE88: =BL88/SUMIFS(BL$2:BL$398,G$2:G$398,G88) -> 0.31626701 | CF88: =BM88/SUMIFS(BM$2:BM$398,G$2:G$398,G88) -> 0.27504912 | CG88: =CE88-CF88 -> 0.041217896 | CH88: =BP88/SUMIFS(BP$2:BP$398,G$2:G$398,G88) -> 0.32374186 | CI88: =BQ88/SUMIFS(BQ$2:BQ$398,G$2:G$398,G88) -> 0.34584294 | CJ88: =CH88-CI88 -> -0.022101078 | CK88: =BT88/SUMIFS(BT$2:BT$398,G$2:G$398,G88) -> 0.31945868 | CL88: =BU88/SUMIFS(BU$2:BU$398,G$2:G$398,G88) -> 0.32172636 | CM88: =CK88-CL88 -> -0.0022676785 | CN88: =COUNTIFS(G$2:G$398,G88)*CH88 -> 1.2949674 | CO88: =COUNTIFS(G$2:G$398,G88)*CK88 -> 1.2778347
... A95: 102104 | B95: IOC | C95: BAKSHI ENTERPRISES | D95: ROHINI | E95: NORTH WEST DELHI | F95: GANPATI | G95: ROHINI_SANJEEV | H95: Rohini | I95: Abhinav | J95: 297.5 | K95: 318 | L95: 38.5 | M95: 36 | N95: 344.5 | O95: 325.5 | P95: 53.5 | Q95: 40.5 | R95: 332 | S95: 331 | T95: 40 | U95: 37 | V95: 360 | W95: 338 | X95: 36 | Y95: 40 | Z95: 376 | AA95: 338 | AB95: 32 | AC95: 40 | AD95: 380 | AE95: 340 | AF95: 40 | AG95: 36 | AH95: 404 | AI95: 344 | AJ95: 40 | AK95: 40 | AL95: 372 | AM95: 348 | AN95: 36 | AO95: 36 | AP95: 352 | AQ95: 330 | AR95: 32 | AS95: 36 | AT95: 340 | AU95: 288 | AV95: 32 | AW95: 36 | AX95: 333.5 | AY95: 264 | AZ95: 44.5 | BA95: 24 | BB95: 368 | BC95: 57.5 | BD95: 40 | BE95: 8.5 | BF95: 28.7013 | BG95: 77.0921 | BH95: =BB95 -> 368 | BI95: =BC95 -> 57.5 | BJ95: =(BH95-BI95) -> 310.5 | BK95: =(BJ95)/BI95*100 -> 540 | BL95: =BD95 -> 40 | BM95: =BE95 -> 8.5 | BN95: =(BL95-BM95) -> 31.5 | BO95: =(BN95)/BM95*100 -> 370.58824 | BP95: =K95+O95+R95+V95+Z95+AD95+AH95+AL95+AP95+AT95+AX95+BB95 -> 4261 | BQ95: =J95+N95+S95+W95+AA95+AE95+AI95+AM95+AQ95+AU95+Table1[[#This Row],[MS-0225]]+Table1[[#This Row],[MS-0325]] -> 3620.5 | BR95: =(BP95-BQ95) -> 640.5 | BS95: =(BR95)/BQ95*100 -> 17.690927 | BT95: =M95+Q95+T95+X95+AB95+AF95+AJ95+AN95+AR95+AV95+AZ95+BD95 -> 449 | BU95: =L95+P95+U95+Y95+AC95+AG95+AK95+AO95+AS95+AW95+BA95+BE95 -> 425.5 | BV95: =(BT95-BU95) -> 23.5 | BW95: =(BV95)/BU95*100 -> 5.5229142 | BX95: 0 | BY95: =BX95/BH95 -> 0 | BZ95: 0 | CA95: =BZ95/BP95 -> 0 | CB95: =BH95/SUMIFS(BH$2:BH$398,G$2:G$398,G95) -> 0.14451208 | CC95: =BI95/SUMIFS(BI$2:BI$398,G$2:G$398,G95) -> 0.0292919 | CD95: =CB95-CC95 -> 0.11522018 | CE95: =BL95/SUMIFS(BL$2:BL$398,G$2:G$398,G95) -> 0.10376135 | CF95: =BM95/SUMIFS(BM$2:BM$398,G$2:G$398,G95) -> 0.028239203 | CG95: =CE95-CF95 -> 0.075522146 | CH95: =BP95/SUMIFS(BP$2:BP$398,G$2:G$398,G95) -> 0.15260095 | CI95: =BQ95/SUMIFS(BQ$2:BQ$398,G$2:G$398,G95) -> 0.13913227 | CJ95: =CH95-CI95 -> 0.013468676 | CK95: =BT95/SUMIFS(BT$2:BT$398,G$2:G$398,G95) -> 0.11076847 | CL95: =BU95/SUMIFS(BU$2:BU$398,G$2:G$398,G95) -> 0.097035348 | CM95: =CK95-CL95 -> 0.013733124 | CN95: =COUNTIFS(G$2:G$398,G95)*CH95 -> 1.0682066 | CO95: =COUNTIFS(G$2:G$398,G95)*CK95 -> 0.7753793
A96: 41032594 | B96: HPC | C96: KEELKAR SERVICE STATION | D96: ROHINI | E96: NORTH WEST DELHI | F96: M.L.SETHI | G96: M.L.SETHI | H96: Rohini | I96: Abhinav | J96: 229.5 | K96: 294.5 | L96: 76.5 | M96: 72.5 | N96: 261 | O96: 321 | P96: 81 | Q96: 80 | R96: 324 | S96: 265.5 | T96: 72 | U96: 76.5 | V96: 325.5 | W96: 256.5 | X96: 75.5 | Y96: 67.5 | Z96: 336 | AA96: 256.5 | AB96: 85 | AC96: 67.5 | AD96: 317.5 | AE96: 234 | AF96: 84.5 | AG96: 72 | AH96: 319.5 | AI96: 243.5 | AJ96: 88.5 | AK96: 66.5 | AL96: 329 | AM96: 262.5 | AN96: 74 | AO96: 78.5 | AP96: 306.5 | AQ96: 234 | AR96: 93.5 | AS96: 72 | AT96: 307.5 | AU96: 241.5 | AV96: 85.5 | AW96: 67.5 | AX96: 282 | AY96: 213.5 | AZ96: 81 | BA96: 63.5 | BB96: 322.5 | BC96: 238.5 | BD96: 96.5 | BE96: 54.5 | BF96: 28.71592 | BG96: 77.11501 | BH96: =BB96 -> 322.5 | BI96: =BC96 -> 238.5 | BJ96: =(BH96-BI96) -> 84 | BK96: =(BJ96)/BI96*100 -> 35.220126 | BL96: =BD96 -> 96.5 | BM96: =BE96 -> 54.5 | BN96: =(BL96-BM96) -> 42 | BO96: =(BN96)/BM96*100 -> 77.06422 | BP96: =K96+O96+R96+V96+Z96+AD96+AH96+AL96+AP96+AT96+AX96+BB96 -> 3785.5 | BQ96: =J96+N96+S96+W96+AA96+AE96+AI96+AM96+AQ96+AU96+Table1[[#This Row],[MS-0225]]+Table1[[#This Row],[MS-0325]] -> 2936.5 | BR96: =(BP96-BQ96) -> 849 | BS96: =(BR96)/BQ96*100 -> 28.91197 | BT96: =M96+Q96+T96+X96+AB96+AF96+AJ96+AN96+AR96+AV96+AZ96+BD96 -> 988.5 | BU96: =L96+P96+U96+Y96+AC96+AG96+AK96+AO96+AS96+AW96+BA96+BE96 -> 843.5 | BV96: =(BT96-BU96) -> 145 | BW96: =(BV96)/BU96*100 -> 17.190279 | BX96: 0 | BY96: =BX96/BH96 -> 0 | BZ96: 0 | CA96: =BZ96/BP96 -> 0 | CB96: =BH96/SUMIFS(BH$2:BH$398,G$2:G$398,G96) -> 0.10520307 | CC96: =BI96/SUMIFS(BI$2:BI$398,G$2:G$398,G96) -> 0.090649943 | CD96: =CB96-CC96 -> 0.014553123 | CE96: =BL96/SUMIFS(BL$2:BL$398,G$2:G$398,G96) -> 0.09247724 | CF96: =BM96/SUMIFS(BM$2:BM$398,G$2:G$398,G96) -> 0.05406746 | CG96: =CE96-CF96 -> 0.03840978 | CH96: =BP96/SUMIFS(BP$2:BP$398,G$2:G$398,G96) -> 0.10805989 | CI96: =BQ96/SUMIFS(BQ$2:BQ$398,G$2:G$398,G96) -> 0.093291821 | CJ96: =CH96-CI96 -> 0.014768068 | CK96: =BT96/SUMIFS(BT$2:BT$398,G$2:G$398,G96) -> 0.084217252 | CL96: =BU96/SUMIFS(BU$2:BU$398,G$2:G$398,G96) -> 0.064907083 | CM96: =CK96-CL96 -> 0.019310169 | CN96: =COUNTIFS(G$2:G$398,G96)*CH96 -> 0.972539 | CO96: =COUNTIFS(G$2:G$398,G96)*CK96 -> 0.75795527 | CP96: =BD96-AZ96 -> 15.5
A97: 123784 | B97: BPC | C97: BP SHANTIPATH | D97: MOTI BAGH DELHI | E97: NEW DELHI | F97: BP SHANTIPATH | G97: BP SHANTIPATH | H97: Lutyens | I97: Bhanu Pratap | J97: 368.586 | K97: 420 | L97: 121.543 | M97: 116 | N97: 406.129 | O97: 422 | P97: 128.565 | Q97: 112 | R97: 397.5 | S97: 369.131 | T97: 100 | U97: 117.611 | V97: 438 | W97: 416 | X97: 107 | Y97: 119.646 | Z97: 448 | AA97: 409 | AB97: 105 | AC97: 120.364 | AD97: 416 | AE97: 381 | AF97: 110 | AG97: 120.237 | AH97: 431 | AI97: 404.07 | AJ97: 119 | AK97: 131.993 | AL97: 413 | AM97: 373.291 | AN97: 98 | AO97: 105.008 | AP97: 392 | AQ97: 372.186 | AR97: 99 | AS97: 97.49899 | AT97: 397.706 | AU97: 380.214 | AV97: 96.081 | AW97: 101.58 | AX97: 396.01 | AY97: 366.067 | AZ97: 107.426 | BA97: 116.824 | BB97: 428.333 | BC97: 382.242 | BD97: 108.511 | BE97: 116.31 | BF97: 28.580494 | BG97: 77.17927 | BH97: =BB97 -> 428.333 | BI97: =BC97 -> 382.242 | BJ97: =(BH97-BI97) -> 46.091 | BK97: =(BJ97)/BI97*100 -> 12.058068 | BL97: =BD97 -> 108.511 | BM97: =BE97 -> 116.31 | BN97: =(BL97-BM97) -> -7.799 | BO97: =(BN97)/BM97*100 -> -6.7053564 | BP97: =K97+O97+R97+V97+Z97+AD97+AH97+AL97+AP97+AT97+AX97+BB97 -> 4999.549 | BQ97: =J97+N97+S97+W97+AA97+AE97+AI97+AM97+AQ97+AU97+Table1[[#This Row],[MS-0225]]+Table1[[#This Row],[MS-0325]] -> 4627.916 | BR97: =(BP97-BQ97) -> 371.633 | BS97: =(BR97)/BQ97*100 -> 8.0302451 | BT97: =M97+Q97+T97+X97+AB97+AF97+AJ97+AN97+AR97+AV97+AZ97+BD97 -> 1278.018 | BU97: =L97+P97+U97+Y97+AC97+AG97+AK97+AO97+AS97+AW97+BA97+BE97 -> 1397.18 | BV97: =(BT97-BU97) -> -119.16199 | BW97: =(BV97)/BU97*100 -> -8.5287501 | BX97: 46.921 | BY97: =BX97/BH97 -> 0.10954328 | BZ97: 295.275 | CA97: =BZ97/BP97 -> 0.059060327 | CB97: =BH97/SUMIFS(BH$2:BH$398,G$2:G$398,G97) -> 0.42563744 | CC97: =BI97/SUMIFS(BI$2:BI$398,G$2:G$398,G97) -> 0.40827265 | CD97: =CB97-CC97 -> 0.017364791 | CE97: =BL97/SUMIFS(BL$2:BL$398,G$2:G$398,G97) -> 0.41023247 | CF97: =BM97/SUMIFS(BM$2:BM$398,G$2:G$398,G97) -> 0.40341993 | CG97: =CE97-CF97 -> 0.0068125368 | CH97: =BP97/SUMIFS(BP$2:BP$398,G$2:G$398,G97) -> 0.42011079 | CI97: =BQ97/SUMIFS(BQ$2:BQ$398,G$2:G$398,G97) -> 0.41035205 | CJ97: =CH97-CI97 -> 0.0097587321 | CK97: =BT97/SUMIFS(BT$2:BT$398,G$2:G$398,G97) -> 0.40507471 | CL97: =BU97/SUMIFS(BU$2:BU$398,G$2:G$398,G97) -> 0.38099575 | CM97: =CK97-CL97 -> 0.02407896 | CN97: =COUNTIFS(G$2:G$398,G97)*CH97 -> 0.84022157 | CO97: =COUNTIFS(G$2:G$398,G97)*CK97 -> 0.81014942
A98: 102107 | B98: IOC | C98: SHIVAN AUTO CENTRE | D98: MAYUR VIHAR PH -2, NH-24 | E98: EAST DELHI | F98: White Patch_Merrut Expressway | G98: White Patch_Merrut Expressway | H98: Mayur Vihar -Anand Vihar -Preet Vihar | I98: Bhanu Pratap | J98: 311 | K98: 441.5 | L98: 85 | M98: 104.5 | N98: 345.5 | O98: 504 | P98: 98.5 | Q98: 108 | R98: 436.5 | S98: 346.5 | T98: 103.5 | U98: 85.5 | V98: 408 | W98: 319.5 | X98: 82 | Y98: 94.5 | Z98: 414 | AA98: 366.5 | AB98: 72 | AC98: 85.5 | AD98: 400.5 | AE98: 316.5 | AF98: 85.5 | AG98: 81.5 | AH98: 373.5 | AI98: 369 | AJ98: 76.5 | AK98: 81 | AL98: 382.5 | AM98: 324 | AN98: 67.5 | AO98: 72 | AP98: 384.5 | AQ98: 345 | AR98: 67.5 | AS98: 67 | AT98: 404 | AU98: 328.5 | AV98: 72 | AW98: 67.5 | AX98: 420.5 | AY98: 307.5 | AZ98: 67.5 | BA98: 72.5 | BB98: 425.5 | BC98: 414 | BD98: 76.5 | BE98: 90 | BF98: 28.6217 | BG98: 77.3016 | BH98: =BB98 -> 425.5 | BI98: =BC98 -> 414 | BJ98: =(BH98-BI98) -> 11.5 | BK98: =(BJ98)/BI98*100 -> 2.7777778 | BL98: =BD98 -> 76.5 | BM98: =BE98 -> 90 | BN98: =(BL98-BM98) -> -13.5 | BO98: =(BN98)/BM98*100 -> -15 | BP98: =K98+O98+R98+V98+Z98+AD98+AH98+AL98+AP98+AT98+AX98+BB98 -> 4995 | BQ98: =J98+N98+S98+W98+AA98+AE98+AI98+AM98+AQ98+AU98+Table1[[#This Row],[MS-0225]]+Table1[[#This Row],[MS-0325]] -> 4093.5 | BR98: =(BP98-BQ98) -> 901.5 | BS98: =(BR98)/BQ98*100 -> 22.022719 | BT98: =M98+Q98+T98+X98+AB98+AF98+AJ98+AN98+AR98+AV98+AZ98+BD98 -> 983 | BU98: =L98+P98+U98+Y98+AC98+AG98+AK98+AO98+AS98+AW98+BA98+BE98 -> 980.5 | BV98: =(BT98-BU98) -> 2.5 | BW98: =(BV98)/BU98*100 -> 0.25497195 | BX98: 0 | BY98: =BX98/BH98 -> 0 | BZ98: 0 | CA98: =BZ98/BP98 -> 0 | CB98: =BH98/SUMIFS(BH$2:BH$398,G$2:G$398,G98) -> 0.23245015 | CC98: =BI98/SUMIFS(BI$2:BI$398,G$2:G$398,G98) -> 0.24790419 | CD98: =CB98-CC98 -> -0.015454041 | CE98: =BL98/SUMIFS(BL$2:BL$398,G$2:G$398,G98) -> 0.19844358 | CF98: =BM98/SUMIFS(BM$2:BM$398,G$2:G$398,G98) -> 0.2195122 | CG98: =CE98-CF98 -> -0.021068615 | CH98: =BP98/SUMIFS(BP$2:BP$398,G$2:G$398,G98) -> 0.238152 | CI98: =BQ98/SUMIFS(BQ$2:BQ$398,G$2:G$398,G98) -> 0.20591564 | CJ98: =CH98-CI98 -> 0.032236356 | CK98: =BT98/SUMIFS(BT$2:BT$398,G$2:G$398,G98) -> 0.20977379 | CL98: =BU98/SUMIFS(BU$2:BU$398,G$2:G$398,G98) -> 0.19284099 | CM98: =CK98-CL98 -> 0.016932807 | CN98: =COUNTIFS(G$2:G$398,G98)*CH98 -> 1.19076 | CO98: =COUNTIFS(G$2:G$398,G98)*CK98 -> 1.048869
A99: 244099 | B99: BPC | C99: Syall Service Station ADHOC (WELCOME AUTOS CC112465) | D99: RAJOURI GARDEN DELHI | E99: WEST DELHI | F99: AUTO CARE-WELCOME | G99: AUTO CARE-WELCOME | H99: Punjabi Bagh | I99: Abhinav | J99: 430.5 | K99: 423 | L99: 67.5 | M99: 55 | N99: 445.5 | O99: 445 | P99: 76.5 | Q99: 55 | R99: 462 | S99: 417 | T99: 50 | U99: 63 | V99: 433 | W99: 430.5 | X99: 59 | Y99: 67.5 | Z99: 424 | AA99: 471.5 | AB99: 38 | AC99: 62.5 | AD99: 427.5 | AE99: 426 | AF99: 58.5 | AG99: 72 | AH99: 433 | AI99: 459 | AJ99: 53 | AK99: 63 | AL99: 403 | AM99: 396 | AN99: 45 | AO99: 54 | AP99: 407 | AQ99: 405 | AR99: 41 | AS99: 45 | AT99: 379 | AU99: 400.5 | AV99: 41 | AW99: 49.5 | AX99: 364 | AY99: 358 | AZ99: 42 | BA99: 42 | BB99: 425 | BC99: 413 | BD99: 54 | BE99: 55 | BF99: 28.63723 | BG99: 77.11966 | BH99: =BB99 -> 425 | BI99: =BC99 -> 413 | BJ99: =(BH99-BI99) -> 12 | BK99: =(BJ99)/BI99*100 -> 2.905569 | BL99: =BD99 -> 54 | BM99: =BE99 -> 55 | BN99: =(BL99-BM99) -> -1 | BO99: =(BN99)/BM99*100 -> -1.8181818 | BP99: =K99+O99+R99+V99+Z99+AD99+AH99+AL99+AP99+AT99+AX99+BB99 -> 5025.5 | BQ99: =J99+N99+S99+W99+AA99+AE99+AI99+AM99+AQ99+AU99+Table1[[#This Row],[MS-0225]]+Table1[[#This Row],[MS-0325]] -> 5052.5 | BR99: =(BP99-BQ99) -> -27 | BS99: =(BR99)/BQ99*100 -> -0.53438892 | BT99: =M99+Q99+T99+X99+AB99+AF99+AJ99+AN99+AR99+AV99+AZ99+BD99 -> 591.5 | BU99: =L99+P99+U99+Y99+AC99+AG99+AK99+AO99+AS99+AW99+BA99+BE99 -> 717.5 | BV99: =(BT99-BU99) -> -126 | BW99: =(BV99)/BU99*100 -> -17.560976 | BX99: 0 | BY99: =BX99/BH99 -> 0 | BZ99: 0 | CA99: =BZ99/BP99 -> 0 | CB99: =BH99/SUMIFS(BH$2:BH$398,G$2:G$398,G99) -> 0.14728816 | CC99: =BI99/SUMIFS(BI$2:BI$398,G$2:G$398,G99) -> 0.15175455 | CD99: =CB99-CC99 -> -0.0044663822 | CE99: =BL99/SUMIFS(BL$2:BL$398,G$2:G$398,G99) -> 0.14117647 | CF99: =BM99/SUMIFS(BM$2:BM$398,G$2:G$398,G99) -> 0.13530135 | CG99: =CE99-CF99 -> 0.0058751176 | CH99: =BP99/SUMIFS(BP$2:BP$398,G$2:G$398,G99) -> 0.14609649 | CI99: =BQ99/SUMIFS(BQ$2:BQ$398,G$2:G$398,G99) -> 0.15454379 | CJ99: =CH99-CI99 -> -0.0084472993 | CK99: =BT99/SUMIFS(BT$2:BT$398,G$2:G$398,G99) -> 0.12893733 | CL99: =BU99/SUMIFS(BU$2:BU$398,G$2:G$398,G99) -> 0.13491914 | CM99: =CK99-CL99 -> -0.0059818128 | CN99: =COUNTIFS(G$2:G$398,G99)*CH99 -> 0.73048243 | CO99: =COUNTIFS(G$2:G$398,G99)*CK99 -> 0.64468665
A100: 112404 | B100: BPC | C100: HARI CHAND & CO. | D100: GOKULPUR DELHI | E100: NORTH EAST DELHI | F100: HARICHAND | G100: HARICHAND | H100: Wazirabad-Loni | I100: Bhanu Pratap | J100: 423 | K100: 427.5 | L100: 261 | M100: 292.5 | N100: 454.5 | O100: 459 | P100: 247.5 | Q100: 297 | R100: 444 | S100: 440.5 | T100: 324 | U100: 309.5 | V100: 432 | W100: 432 | X100: 306 | Y100: 306 | Z100: 441 | AA100: 441 | AB100: 297 | AC100: 315 | AD100: 418.5 | AE100: 418.5 | AF100: 283.5 | AG100: 283.5 | AH100: 451.5 | AI100: 441 | AJ100: 288.5 | AK100: 333 | AL100: 432 | AM100: 446 | AN100: 288 | AO100: 263 | AP100: 432 | AQ100: 428 | AR100: 342 | AS100: 288 | AT100: 405 | AU100: 405 | AV100: 261 | AW100: 237 | AX100: 387 | AY100: 400.5 | AZ100: 315 | BA100: 229.5 | BB100: 423 | BC100: 400 | BD100: 261 | BE100: 296 | BF100: 28.70563 | BG100: 77.29185 | BH100: =BB100 -> 423 | BI100: =BC100 -> 400 | BJ100: =(BH100-BI100) -> 23 | BK100: =(BJ100)/BI100*100 -> 5.75 | BL100: =BD100 -> 261 | BM100: =BE100 -> 296 | BN100: =(BL100-BM100) -> -35 | BO100: =(BN100)/BM100*100 -> -11.824324 | BP100: =K100+O100+R100+V100+Z100+AD100+AH100+AL100+AP100+AT100+AX100+BB100 -> 5152.5 | BQ100: =J100+N100+S100+W100+AA100+AE100+AI100+AM100+AQ100+AU100+Table1[[#This Row],[MS-0225]]+Table1[[#This Row],[MS-0325]] -> 5130 | BR100: =(BP100-BQ100) -> 22.499991 | BS100: =(BR100)/BQ100*100 -> 0.43859632 | BT100: =M100+Q100+T100+X100+AB100+AF100+AJ100+AN100+AR100+AV100+AZ100+BD100 -> 3555.5 | BU100: =L100+P100+U100+Y100+AC100+AG100+AK100+AO100+AS100+AW100+BA100+BE100 -> 3369 | BV100: =(BT100-BU100) -> 186.5 | BW100: =(BV100)/BU100*100 -> 5.5357673 | BX100: 9 | BY100: =BX100/BH100 -> 0.021276596 | BZ100: 58.5 | CA100: =BZ100/BP100 -> 0.011353712 | CB100: =BH100/SUMIFS(BH$2:BH$398,G$2:G$398,G100) -> 0.52093596 | CC100: =BI100/SUMIFS(BI$2:BI$398,G$2:G$398,G100) -> 0.55555556 | CD100: =CB100-CC100 -> -0.034619595 | CE100: =BL100/SUMIFS(BL$2:BL$398,G$2:G$398,G100) -> 0.70540541 | CF100: =BM100/SUMIFS(BM$2:BM$398,G$2:G$398,G100) -> 0.71497585 | CG100: =CE100-CF100 -> -0.00957044 | CH100: =BP100/SUMIFS(BP$2:BP$398,G$2:G$398,G100) -> 0.56271501 | CI100: =BQ100/SUMIFS(BQ$2:BQ$398,G$2:G$398,G100) -> 0.55712424 | CJ100: =CH100-CI100 -> 0.005590771 | CK100: =BT100/SUMIFS(BT$2:BT$398,G$2:G$398,G100) -> 0.74781786 | CL100: =BU100/SUMIFS(BU$2:BU$398,G$2:G$398,G100) -> 0.71604676 | CM100: =CK100-CL100 -> 0.031771098 | CN100: =COUNTIFS(G$2:G$398,G100)*CH100 -> 1.12543 | CO100: =COUNTIFS(G$2:G$398,G100)*CK100 -> 1.4956357
A101: 41056986 | B101: HPC | C101: M/S EXCHANGE STORES | D101: SHASTRI PARK | E101: NORTH EAST DELHI | F101: White Patch_Old GT Road | G101: White Patch_Old GT Road | H101: Old GT Road (NH1) | I101: Bhanu Pratap | J101: 342 | K101: 377 | L101: 36 | M101: 41 | N101: 378 | O101: 399 | P101: 36 | Q101: 41 | R101: 395 | S101: 361 | T101: 50 | U101: 36 | V101: 357 | W101: 360 | X101: 22 | Y101: 36 | Z101: 418 | AA101: 414 | AB101: 44 | AC101: 54 | AD101: 408 | AE101: 414 | AF101: 44 | AG101: 36 | AH101: 443 | AI101: 432 | AJ101: 44 | AK101: 36 | AL101: 399 | AM101: 400 | AN101: 22 | AO101: 41 | AP101: 375 | AQ101: 396 | AR101: 44 | AS101: 38 | AT101: 351 | AU101: 366 | AV101: 22 | AW101: 38 | AX101: 354 | AY101: 355 | AZ101: 44 | BA101: 46 | BB101: 422 | BC101: 405 | BD101: 25 | BE101: 28 | BF101: 28.67279 | BG101: 77.25233 | BH101: =BB101 -> 422 | BI101: =BC101 -> 405 | BJ101: =(BH101-BI101) -> 17 | BK101: =(BJ101)/BI101*100 -> 4.1975309 | BL101: =BD101 -> 25 | BM101: =BE101 -> 28 | BN101: =(BL101-BM101) -> -3 | BO101: =(BN101)/BM101*100 -> -10.714286 | BP101: =K101+O101+R101+V101+Z101+AD101+AH101+AL101+AP101+AT101+AX101+BB101 -> 4698 | BQ101: =J101+N101+S101+W101+AA101+AE101+AI101+AM101+AQ101+AU101+Table1[[#This Row],[MS-0225]]+Table1[[#This Row],[MS-0325]] -> 4623 | BR101: =(BP101-BQ101) -> 75 | BS101: =(BR101)/BQ101*100 -> 1.6223232 | BT101: =M101+Q101+T101+X101+AB101+AF101+AJ101+AN101+AR101+AV101+AZ101+BD101 -> 443 | BU101: =L101+P101+U101+Y101+AC101+AG101+AK101+AO101+AS101+AW101+BA101+BE101 -> 461 | BV101: =(BT101-BU101) -> -18 | BW101: =(BV101)/BU101*100 -> -3.9045553 | BX101: 0 | BY101: =BX101/BH101 -> 0 | BZ101: 0 | CA101: =BZ101/BP101 -> 0 | CB101: =BH101/SUMIFS(BH$2:BH$398,G$2:G$398,G101) -> 0.18623124 | CC101: =BI101/SUMIFS(BI$2:BI$398,G$2:G$398,G101) -> 0.18951802 | CD101: =CB101-CC101 -> -0.0032867714 | CE101: =BL101/SUMIFS(BL$2:BL$398,G$2:G$398,G101) -> 0.10964912 | CF101: =BM101/SUMIFS(BM$2:BM$398,G$2:G$398,G101) -> 0.112 | CG101: =CE101-CF101 -> -0.0023508772 | CH101: =BP101/SUMIFS(BP$2:BP$398,G$2:G$398,G101) -> 0.18065757 | CI101: =BQ101/SUMIFS(BQ$2:BQ$398,G$2:G$398,G101) -> 0.18702213 | CJ101: =CH101-CI101 -> -0.0063645629 | CK101: =BT101/SUMIFS(BT$2:BT$398,G$2:G$398,G101) -> 0.15403338 | CL101: =BU101/SUMIFS(BU$2:BU$398,G$2:G$398,G101) -> 0.14842241 | CM101: =CK101-CL101 -> 0.0056109715 | CN101: =COUNTIFS(G$2:G$398,G101)*CH101 -> 0.90328783 | CO101: =COUNTIFS(G$2:G$398,G101)*CK101 -> 0.7701669
A102: 112459 | B102: BPC | C102: VASANT AUTO SERVICES | D102: VASANT KUNJ DELHI | E102: NEW DELHI | F102: PUSHPANJALI | G102: PUSHPANJALI | H102: Hauj Khas-Saket-Vasant Kunj | I102: Raj Doshi | J102: 370 | K102: 410 | L102: 74 | M102: 90 | N102: 394 | O102: 363 | P102: 98 | Q102: 85 | R102: 326.5 | S102: 374 | T102: 81.5 | U102: 88 | V102: 381.5 | W102: 420 | X102: 112.5 | Y102: 102 | Z102: 392 | AA102: 392.5 | AB102: 102 | AC102: 107.5 | AD102: 415 | AE102: 366.5 | AF102: 127 | AG102: 101.5 | AH102: 351.5 | AI102: 409 | AJ102: 96.5 | AK102: 97 | AL102: 360 | AM102: 327.5 | AN102: 76 | AO102: 52.5 | AP102: 374 | AQ102: 378 | AR102: 66 | AS102: 80 | AT102: 373 | AU102: 376 | AV102: 83 | AW102: 80 | AX102: 398 | AY102: 325 | AZ102: 70 | BA102: 65 | BB102: 416 | BC102: 379 | BD102: 84 | BE102: 79 | BF102: 28.5263 | BG102: 77.15615 | BH102: =BB102 -> 416 | BI102: =BC102 -> 379 | BJ102: =(BH102-BI102) -> 37 | BK102: =(BJ102)/BI102*100 -> 9.762533 | BL102: =BD102 -> 84 | BM102: =BE102 -> 79 | BN102: =(BL102-BM102) -> 5 | BO102: =(BN102)/BM102*100 -> 6.3291139 | BP102: =K102+O102+R102+V102+Z102+AD102+AH102+AL102+AP102+AT102+AX102+BB102 -> 4560.5 | BQ102: =J102+N102+S102+W102+AA102+AE102+AI102+AM102+AQ102+AU102+Table1[[#This Row],[MS-0225]]+Table1[[#This Row],[MS-0325]] -> 4511.5 | BR102: =(BP102-BQ102) -> 48.999992 | BS102: =(BR102)/BQ102*100 -> 1.0861131 | BT102: =M102+Q102+T102+X102+AB102+AF102+AJ102+AN102+AR102+AV102+AZ102+BD102 -> 1073.5 | BU102: =L102+P102+U102+Y102+AC102+AG102+AK102+AO102+AS102+AW102+BA102+BE102 -> 1024.5 | BV102: =(BT102-BU102) -> 49 | BW102: =(BV102)/BU102*100 -> 4.7828209 | BX102: 31 | BY102: =BX102/BH102 -> 0.074519231 | BZ102: 159.5 | CA102: =BZ102/BP102 -> 0.034974235 | CB102: =BH102/SUMIFS(BH$2:BH$398,G$2:G$398,G102) -> 0.27714857 | CC102: =BI102/SUMIFS(BI$2:BI$398,G$2:G$398,G102) -> 0.27877896 | CD102: =CB102-CC102 -> -0.0016303952 | CE102: =BL102/SUMIFS(BL$2:BL$398,G$2:G$398,G102) -> 0.20947631 | CF102: =BM102/SUMIFS(BM$2:BM$398,G$2:G$398,G102) -> 0.18098511 | CG102: =CE102-CF102 -> 0.0284912 | CH102: =BP102/SUMIFS(BP$2:BP$398,G$2:G$398,G102) -> 0.27171711 | CI102: =BQ102/SUMIFS(BQ$2:BQ$398,G$2:G$398,G102) -> 0.2793239 | CJ102: =CH102-CI102 -> -0.0076067904 | CK102: =BT102/SUMIFS(BT$2:BT$398,G$2:G$398,G102) -> 0.2269556 | CL102: =BU102/SUMIFS(BU$2:BU$398,G$2:G$398,G102) -> 0.19342962 | CM102: =CK102-CL102 -> 0.033525979 | CN102: =COUNTIFS(G$2:G$398,G102)*CH102 -> 1.0868684 | CO102: =COUNTIFS(G$2:G$398,G102)*CK102 -> 0.90782241
A103: 186862 | B103: IOC | C103: ROOP FILLING STATION | D103: OLD WAZIRABAD ROAD | E103: NORTH EAST DELHI | F103: White Patch_Wazirabad | G103: White Patch_Wazirabad | H103: Wazirabad-Loni | I103: Bhanu Pratap | J103: 409 | K103: 450 | L103: 117 | M103: 130 | N103: 443 | O103: 425 | P103: 135 | Q103: 115 | R103: 443 | S103: 423 | T103: 109 | U103: 135 | V103: 432 | W103: 402.5 | X103: 84 | Y103: 121.5 | Z103: 447 | AA103: 412.5 | AB103: 107 | AC103: 97.5 | AD103: 404 | AE103: 337.5 | AF103: 114 | AG103: 112.5 | AH103: 439 | AI103: 391.5 | AJ103: 79 | AK103: 130.5 | AL103: 430 | AM103: 427.5 | AN103: 90 | AO103: 112.5 | AP103: 410 | AQ103: 432 | AR103: 90 | AS103: 90 | AT103: 411 | AU103: 378 | AV103: 103 | AW103: 126 | AX103: 397 | AY103: 379 | AZ103: 99 | BA103: 127 | BB103: 415 | BC103: 400.5 | BD103: 105 | BE103: 83.5 | BF103: 28.6977 | BG103: 77.3141 | BH103: =BB103 -> 415 | BI103: =BC103 -> 400.5 | BJ103: =(BH103-BI103) -> 14.5 | BK103: =(BJ103)/BI103*100 -> 3.6204744 | BL103: =BD103 -> 105 | BM103: =BE103 -> 83.5 | BN103: =(BL103-BM103) -> 21.5 | BO103: =(BN103)/BM103*100 -> 25.748503 | BP103: =K103+O103+R103+V103+Z103+AD103+AH103+AL103+AP103+AT103+AX103+BB103 -> 5103 | BQ103: =J103+N103+S103+W103+AA103+AE103+AI103+AM103+AQ103+AU103+Table1[[#This Row],[MS-0225]]+Table1[[#This Row],[MS-0325]] -> 4836 | BR103: =(BP103-BQ103) -> 267 | BS103: =(BR103)/BQ103*100 -> 5.5210918 | BT103: =M103+Q103+T103+X103+AB103+AF103+AJ103+AN103+AR103+AV103+AZ103+BD103 -> 1225 | BU103: =L103+P103+U103+Y103+AC103+AG103+AK103+AO103+AS103+AW103+BA103+BE103 -> 1388 | BV103: =(BT103-BU103) -> -163 | BW103: =(BV103)/BU103*100 -> -11.743516 | BX103: 0 | BY103: =BX103/BH103 -> 0 | BZ103: 0 | CA103: =BZ103/BP103 -> 0 | CB103: =BH103/SUMIFS(BH$2:BH$398,G$2:G$398,G103) -> 0.21469219 | CC103: =BI103/SUMIFS(BI$2:BI$398,G$2:G$398,G103) -> 0.20299037 | CD103: =CB103-CC103 -> 0.011701818 | CE103: =BL103/SUMIFS(BL$2:BL$398,G$2:G$398,G103) -> 0.42510121 | CF103: =BM103/SUMIFS(BM$2:BM$398,G$2:G$398,G103) -> 0.31628788 | CG103: =CE103-CF103 -> 0.10881334 | CH103: =BP103/SUMIFS(BP$2:BP$398,G$2:G$398,G103) -> 0.213895 | CI103: =BQ103/SUMIFS(BQ$2:BQ$398,G$2:G$398,G103) -> 0.20755365 | CJ103: =CH103-CI103 -> 0.0063413535 | CK103: =BT103/SUMIFS(BT$2:BT$398,G$2:G$398,G103) -> 0.39471564 | CL103: =BU103/SUMIFS(BU$2:BU$398,G$2:G$398,G103) -> 0.38384956 | CM103: =CK103-CL103 -> 0.010866086 | CN103: =COUNTIFS(G$2:G$398,G103)*CH103 -> 1.069475 | CO103: =COUNTIFS(G$2:G$398,G103)*CK103 -> 1.9735782
A104: 331623 | B104: IOC | C104: COCO-BAWANA SEC-5 (27.08.20) | D104: BAWANA DELHI | E104: NORTH WEST DELHI | F104: White Patch DSIDC | G104: White Patch DSIDC | H104: Narela- Bawana | I104: Abhinav | J104: 161.143 | K104: 181.094 | L104: 66.713 | M104: 64.209 | N104: 167 | O104: 191.598 | P104: 67.5 | Q104: 64.026 | R104: 198 | S104: 167.77 | T104: 60 | U104: 63.815 | V104: 199.474 | W104: 177.637 | X104: 55.046 | Y104: 84.655 | Z104: 256.405 | AA104: 181.5 | AB104: 74.922 | AC104: 54.5 | AD104: 262.089 | AE104: 183.544 | AF104: 106.918 | AG104: 55.606 | AH104: 232.95 | AI104: 202.5 | AJ104: 85.498 | AK104: 67.5 | AL104: 261.897 | AM104: 161.902 | AN104: 100.242 | AO104: 50.794 | AP104: 222.44 | AQ104: 161.178 | AR104: 71.116 | AS104: 49.413 | AT104: 218.325 | AU104: 162.148 | AV104: 72.994 | AW104: 62.476 | AX104: 216.407 | AY104: 150.453 | AZ104: 79.543 | BA104: 57.348 | BB104: 243.835 | BC104: 168.894 | BD104: 90.965 | BE104: 60.137 | BF104: 28.800177 | BG104: 77.085523 | BH104: =BB104 -> 243.835 | BI104: =BC104 -> 168.894 | BJ104: =(BH104-BI104) -> 74.941 | BK104: =(BJ104)/BI104*100 -> 44.371618 | BL104: =BD104 -> 90.965 | BM104: =BE104 -> 60.137 | BN104: =(BL104-BM104) -> 30.828 | BO104: =(BN104)/BM104*100 -> 51.26295 | BP104: =K104+O104+R104+V104+Z104+AD104+AH104+AL104+AP104+AT104+AX104+BB104 -> 2684.514 | BQ104: =J104+N104+S104+W104+AA104+AE104+AI104+AM104+AQ104+AU104+Table1[[#This Row],[MS-0225]]+Table1[[#This Row],[MS-0325]] -> 2045.669 | BR104: =(BP104-BQ104) -> 638.845 | BS104: =(BR104)/BQ104*100 -> 31.229148 | BT104: =M104+Q104+T104+X104+AB104+AF104+AJ104+AN104+AR104+AV104+AZ104+BD104 -> 925.479 | BU104: =L104+P104+U104+Y104+AC104+AG104+AK104+AO104+AS104+AW104+BA104+BE104 -> 740.457 | BV104: =(BT104-BU104) -> 185.022 | BW104: =(BV104)/BU104*100 -> 24.987541 | BX104: 0 | BY104: =BX104/BH104 -> 0 | BZ104: 0 | CA104: =BZ104/BP104 -> 0 | CB104: =BH104/SUMIFS(BH$2:BH$398,G$2:G$398,G104) -> 0.56269659 | CC104: =BI104/SUMIFS(BI$2:BI$398,G$2:G$398,G104) -> 0.49814479 | CD104: =CB104-CC104 -> 0.064551792 | CE104: =BL104/SUMIFS(BL$2:BL$398,G$2:G$398,G104) -> 0.50826386 | CF104: =BM104/SUMIFS(BM$2:BM$398,G$2:G$398,G104) -> 0.48261721 | CG104: =CE104-CF104 -> 0.025646653 | CH104: =BP104/SUMIFS(BP$2:BP$398,G$2:G$398,G104) -> 0.54142292 | CI104: =BQ104/SUMIFS(BQ$2:BQ$398,G$2:G$398,G104) -> 0.49837612 | CJ104: =CH104-CI104 -> 0.043046806 | CK104: =BT104/SUMIFS(BT$2:BT$398,G$2:G$398,G104) -> 0.51567107 | CL104: =BU104/SUMIFS(BU$2:BU$398,G$2:G$398,G104) -> 0.47238146 | CM104: =CK104-CL104 -> 0.043289609 | CN104: =COUNTIFS(G$2:G$398,G104)*CH104 -> 1.0828458 | CO104: =COUNTIFS(G$2:G$398,G104)*CK104 -> 1.0313421
A105: 41056840 | B105: HPC | C105: SERVICIRCLE | D105: ASHRAM CHOWK | E105: SOUTH EAST DELHI | F105: White Patch_Mathura Road | G105: White Patch_Mathura Road | H105: Mathura Road | I105: Bhanu Pratap | J105: 375 | K105: 405 | L105: 200 | M105: 195 | N105: 395 | O105: 430 | P105: 205 | Q105: 195 | R105: 410 | S105: 405 | T105: 185 | U105: 195 | V105: 430 | W105: 430 | X105: 170 | Y105: 195 | Z105: 415 | AA105: 435 | AB105: 135 | AC105: 215 | AD105: 415 | AE105: 400 | AF105: 135 | AG105: 200 | AH105: 425 | AI105: 415 | AJ105: 150 | AK105: 210 | AL105: 420 | AM105: 430 | AN105: 128 | AO105: 170 | AP105: 397 | AQ105: 390 | AR105: 140 | AS105: 185 | AT105: 404 | AU105: 394 | AV105: 125 | AW105: 185 | AX105: 395 | AY105: 375 | AZ105: 130 | BA105: 175 | BB105: 410 | BC105: 398 | BD105: 165 | BE105: 201 | BF105: 28.57121 | BG105: 77.25963 | BH105: =BB105 -> 410 | BI105: =BC105 -> 398 | BJ105: =(BH105-BI105) -> 12 | BK105: =(BJ105)/BI105*100 -> 3.0150754 | BL105: =BD105 -> 165 | BM105: =BE105 -> 201 | BN105: =(BL105-BM105) -> -36 | BO105: =(BN105)/BM105*100 -> -17.910448 | BP105: =K105+O105+R105+V105+Z105+AD105+AH105+AL105+AP105+AT105+AX105+BB105 -> 4956 | BQ105: =J105+N105+S105+W105+AA105+AE105+AI105+AM105+AQ105+AU105+Table1[[#This Row],[MS-0225]]+Table1[[#This Row],[MS-0325]] -> 4842 | BR105: =(BP105-BQ105) -> 114 | BS105: =(BR105)/BQ105*100 -> 2.354399 | BT105: =M105+Q105+T105+X105+AB105+AF105+AJ105+AN105+AR105+AV105+AZ105+BD105 -> 1853 | BU105: =L105+P105+U105+Y105+AC105+AG105+AK105+AO105+AS105+AW105+BA105+BE105 -> 2336 | BV105: =(BT105-BU105) -> -483 | BW105: =(BV105)/BU105*100 -> -20.67637 | BX105: 0 | BY105: =BX105/BH105 -> 0 | BZ105: 0 | CA105: =BZ105/BP105 -> 0 | CB105: =BH105/SUMIFS(BH$2:BH$398,G$2:G$398,G105) -> 1 | CC105: =BI105/SUMIFS(BI$2:BI$398,G$2:G$398,G105) -> 1 | CD105: =CB105-CC105 -> 0 | CE105: =BL105/SUMIFS(BL$2:BL$398,G$2:G$398,G105) -> 1 | CF105: =BM105/SUMIFS(BM$2:BM$398,G$2:G$398,G105) -> 1 | CG105: =CE105-CF105 -> 0 | CH105: =BP105/SUMIFS(BP$2:BP$398,G$2:G$398,G105) -> 1 | CI105: =BQ105/SUMIFS(BQ$2:BQ$398,G$2:G$398,G105) -> 1 | CJ105: =CH105-CI105 -> 0 | CK105: =BT105/SUMIFS(BT$2:BT$398,G$2:G$398,G105) -> 1 | CL105: =BU105/SUMIFS(BU$2:BU$398,G$2:G$398,G105) -> 1 | CM105: =CK105-CL105 -> 0 | CN105: =COUNTIFS(G$2:G$398,G105)*CH105 -> 1 | CO105: =COUNTIFS(G$2:G$398,G105)*CK105 -> 1
A106: 179735 | B106: IOC | C106: MAHENDRA | D106: CBD SHAHDARA-II | E106: SHAHDARA | F106: ALLIED_MASIH | G106: ALLIED_MASIH | H106: Mayur Vihar -Anand Vihar -Preet Vihar | I106: Bhanu Pratap | J106: 328.5 | K106: 373.5 | L106: 103.5 | M106: 94.5 | N106: 373.5 | O106: 396 | P106: 112.5 | Q106: 90 | R106: 378 | S106: 351 | T106: 90 | U106: 99 | V106: 436.5 | W106: 387 | X106: 85.5 | Y106: 99 | Z106: 415.5 | AA106: 409.5 | AB106: 90.5 | AC106: 112.5 | AD106: 396 | AE106: 360 | AF106: 72 | AG106: 108 | AH106: 391.5 | AI106: 384.5 | AJ106: 76.5 | AK106: 103.5 | AL106: 381 | AM106: 363 | AN106: 99 | AO106: 109 | AP106: 368 | AQ106: 342 | AR106: 76 | AS106: 90 | AT106: 342 | AU106: 359.5 | AV106: 72 | AW106: 78.5 | AX106: 333 | AY106: 310.5 | AZ106: 81 | BA106: 103.5 | BB106: 409.5 | BC106: 364.5 | BD106: 76.5 | BE106: 103.5 | BF106: 28.6271 | BG106: 77.3129 | BH106: =BB106 -> 409.5 | BI106: =BC106 -> 364.5 | BJ106: =(BH106-BI106) -> 45 | BK106: =(BJ106)/BI106*100 -> 12.345679 | BL106: =BD106 -> 76.5 | BM106: =BE106 -> 103.5 | BN106: =(BL106-BM106) -> -27 | BO106: =(BN106)/BM106*100 -> -26.086957 | BP106: =K106+O106+R106+V106+Z106+AD106+AH106+AL106+AP106+AT106+AX106+BB106 -> 4620.5 | BQ106: =J106+N106+S106+W106+AA106+AE106+AI106+AM106+AQ106+AU106+Table1[[#This Row],[MS-0225]]+Table1[[#This Row],[MS-0325]] -> 4333.5 | BR106: =(BP106-BQ106) -> 287 | BS106: =(BR106)/BQ106*100 -> 6.6228222 | BT106: =M106+Q106+T106+X106+AB106+AF106+AJ106+AN106+AR106+AV106+AZ106+BD106 -> 1003.5 | BU106: =L106+P106+U106+Y106+AC106+AG106+AK106+AO106+AS106+AW106+BA106+BE106 -> 1222.5 | BV106: =(BT106-BU106) -> -219 | BW106: =(BV106)/BU106*100 -> -17.91411 | BX106: 0 | BY106: =BX106/BH106 -> 0 | BZ106: 0 | CA106: =BZ106/BP106 -> 0 | CB106: =BH106/SUMIFS(BH$2:BH$398,G$2:G$398,G106) -> 0.099164548 | CC106: =BI106/SUMIFS(BI$2:BI$398,G$2:G$398,G106) -> 0.096047431 | CD106: =CB106-CC106 -> 0.0031171169 | CE106: =BL106/SUMIFS(BL$2:BL$398,G$2:G$398,G106) -> 0.12 | CF106: =BM106/SUMIFS(BM$2:BM$398,G$2:G$398,G106) -> 0.15447761 | CG106: =CE106-CF106 -> -0.034477612 | CH106: =BP106/SUMIFS(BP$2:BP$398,G$2:G$398,G106) -> 0.094129192 | CI106: =BQ106/SUMIFS(BQ$2:BQ$398,G$2:G$398,G106) -> 0.094685093 | CJ106: =CH106-CI106 -> -0.00055590057 | CK106: =BT106/SUMIFS(BT$2:BT$398,G$2:G$398,G106) -> 0.12930955 | CL106: =BU106/SUMIFS(BU$2:BU$398,G$2:G$398,G106) -> 0.14456506 | CM106: =CK106-CL106 -> -0.015255516 | CN106: =COUNTIFS(G$2:G$398,G106)*CH106 -> 0.75303354 | CO106: =COUNTIFS(G$2:G$398,G106)*CK106 -> 1.0344764
A107: 194183 | B107: IOC | C107: GANGA PETRO | D107: SEC-10, DWARKA | E107: SOUTH WEST DELHI | F107: White Patch_Dwarka Sector19 | G107: White Patch_Dwarka Sector19 | H107: Dwarka | I107: Raj Doshi | J107: 300 | K107: 368 | L107: 72 | M107: 76 | N107: 316 | O107: 368 | P107: 80 | Q107: 72 | R107: 332 | S107: 320 | T107: 60 | U107: 76 | V107: 404 | W107: 348 | X107: 76 | Y107: 84 | Z107: 392 | AA107: 328 | AB107: 76 | AC107: 92 | AD107: 388 | AE107: 328 | AF107: 76 | AG107: 80 | AH107: 424 | AI107: 356 | AJ107: 80 | AK107: 88 | AL107: 388 | AM107: 312 | AN107: 68 | AO107: 60 | AP107: 384 | AQ107: 312 | AR107: 68 | AS107: 56 | AT107: 356 | AU107: 312 | AV107: 64 | AW107: 72 | AX107: 361 | AY107: 300 | AZ107: 73 | BA107: 68 | BB107: 408 | BC107: 341 | BD107: 84 | BE107: 69 | BF107: 28.5791 | BG107: 77.0552 | BH107: =BB107 -> 408 | BI107: =BC107 -> 341 | BJ107: =(BH107-BI107) -> 67 | BK107: =(BJ107)/BI107*100 -> 19.648094 | BL107: =BD107 -> 84 | BM107: =BE107 -> 69 | BN107: =(BL107-BM107) -> 15 | BO107: =(BN107)/BM107*100 -> 21.73913 | BP107: =K107+O107+R107+V107+Z107+AD107+AH107+AL107+AP107+AT107+AX107+BB107 -> 4573 | BQ107: =J107+N107+S107+W107+AA107+AE107+AI107+AM107+AQ107+AU107+Table1[[#This Row],[MS-0225]]+Table1[[#This Row],[MS-0325]] -> 3873 | BR107: =(BP107-BQ107) -> 700 | BS107: =(BR107)/BQ107*100 -> 18.073845 | BT107: =M107+Q107+T107+X107+AB107+AF107+AJ107+AN107+AR107+AV107+AZ107+BD107 -> 873 | BU107: =L107+P107+U107+Y107+AC107+AG107+AK107+AO107+AS107+AW107+BA107+BE107 -> 897 | BV107: =(BT107-BU107) -> -24 | BW107: =(BV107)/BU107*100 -> -2.6755853 | BX107: 0 | BY107: =BX107/BH107 -> 0 | BZ107: 0 | CA107: =BZ107/BP107 -> 0 | CB107: =BH107/SUMIFS(BH$2:BH$398,G$2:G$398,G107) -> 0.53160094 | CC107: =BI107/SUMIFS(BI$2:BI$398,G$2:G$398,G107) -> 0.48947486 | CD107: =CB107-CC107 -> 0.042126084 | CE107: =BL107/SUMIFS(BL$2:BL$398,G$2:G$398,G107) -> 0.50136981 | CF107: =BM107/SUMIFS(BM$2:BM$398,G$2:G$398,G107) -> 0.4320006 | CG107: =CE107-CF107 -> 0.069369213 | CH107: =BP107/SUMIFS(BP$2:BP$398,G$2:G$398,G107) -> 0.51313384 | CI107: =BQ107/SUMIFS(BQ$2:BQ$398,G$2:G$398,G107) -> 0.47950663 | CJ107: =CH107-CI107 -> 0.033627204 | CK107: =BT107/SUMIFS(BT$2:BT$398,G$2:G$398,G107) -> 0.45743329 | CL107: =BU107/SUMIFS(BU$2:BU$398,G$2:G$398,G107) -> 0.44778645 | CM107: =CK107-CL107 -> 0.0096468387 | CN107: =COUNTIFS(G$2:G$398,G107)*CH107 -> 1.0262677 | CO107: =COUNTIFS(G$2:G$398,G107)*CK107 -> 0.91486658
A108: 106345 | B108: IOC | C108: SHAHEED SUMEET ROY ENTERPRISES | D108: SECTOR-24, ROHINI | E108: NORTH WEST DELHI | F108: M.L.SETHI | G108: M.L.SETHI | H108: Rohini | I108: Abhinav | J108: 456 | K108: 528 | L108: 144 | M108: 156 | N108: 476 | O108: 536 | P108: 148 | Q108: 148 | R108: 511 | S108: 456 | T108: 139 | U108: 132 | V108: 560 | W108: 496 | X108: 148 | Y108: 140 | Z108: 597 | AA108: 500 | AB108: 153 | AC108: 136 | AD108: 584 | AE108: 477.5 | AF108: 160 | AG108: 140.5 | AH108: 608 | AI108: 500 | AJ108: 148 | AK108: 136 | AL108: 600.5 | AM108: 468 | AN108: 137.5 | AO108: 108 | AP108: 592 | AQ108: 468 | AR108: 140 | AS108: 108 | AT108: 593 | AU108: 456 | AV108: 153 | AW108: 120 | AX108: 585 | AY108: 428 | AZ108: 153 | BA108: 124 | BB108: 682 | BC108: 488 | BD108: 176 | BE108: 148 | BF108: 28.7298 | BG108: 77.0928 | BH108: =BB108 -> 682 | BI108: =BC108 -> 488 | BJ108: =(BH108-BI108) -> 194 | BK108: =(BJ108)/BI108*100 -> 39.754098 | BL108: =BD108 -> 176 | BM108: =BE108 -> 148 | BN108: =(BL108-BM108) -> 28 | BO108: =(BN108)/BM108*100 -> 18.918919 | BP108: =K108+O108+R108+V108+Z108+AD108+AH108+AL108+AP108+AT108+AX108+BB108 -> 6976.5 | BQ108: =J108+N108+S108+W108+AA108+AE108+AI108+AM108+AQ108+AU108+Table1[[#This Row],[MS-0225]]+Table1[[#This Row],[MS-0325]] -> 5669.5 | BR108: =(BP108-BQ108) -> 1307 | BS108: =(BR108)/BQ108*100 -> 23.053179 | BT108: =M108+Q108+T108+X108+AB108+AF108+AJ108+AN108+AR108+AV108+AZ108+BD108 -> 1811.5 | BU108: =L108+P108+U108+Y108+AC108+AG108+AK108+AO108+AS108+AW108+BA108+BE108 -> 1584.5 | BV108: =(BT108-BU108) -> 227 | BW108: =(BV108)/BU108*100 -> 14.326286 | BX108: 0 | BY108: =BX108/BH108 -> 0 | BZ108: 0 | CA108: =BZ108/BP108 -> 0 | CB108: =BH108/SUMIFS(BH$2:BH$398,G$2:G$398,G108) -> 0.22247594 | CC108: =BI108/SUMIFS(BI$2:BI$398,G$2:G$398,G108) -> 0.18548081 | CD108: =CB108-CC108 -> 0.036995136 | CE108: =BL108/SUMIFS(BL$2:BL$398,G$2:G$398,G108) -> 0.16866315 | CF108: =BM108/SUMIFS(BM$2:BM$398,G$2:G$398,G108) -> 0.1468254 | CG108: =CE108-CF108 -> 0.021837756 | CH108: =BP108/SUMIFS(BP$2:BP$398,G$2:G$398,G108) -> 0.19914934 | CI108: =BQ108/SUMIFS(BQ$2:BQ$398,G$2:G$398,G108) -> 0.1801185 | CJ108: =CH108-CI108 -> 0.019030836 | CK108: =BT108/SUMIFS(BT$2:BT$398,G$2:G$398,G108) -> 0.1543344 | CL108: =BU108/SUMIFS(BU$2:BU$398,G$2:G$398,G108) -> 0.12192682 | CM108: =CK108-CL108 -> 0.032407577 | CN108: =COUNTIFS(G$2:G$398,G108)*CH108 -> 1.792344 | CO108: =COUNTIFS(G$2:G$398,G108)*CK108 -> 1.3890096
... A111: 106364 | B111: IOC | C111: SUSHANTI FILLING STATION | D111: LSC, SECTOR-6, DWARKA | E111: SOUTH WEST DELHI | F111: SHIV SS | G111: SHIV SS | H111: Dwarka | I111: Raj Doshi | J111: 373 | K111: 408 | L111: 59 | M111: 62 | N111: 422.5 | O111: 444 | P111: 71.5 | Q111: 58 | R111: 391 | S111: 381.5 | T111: 49 | U111: 60.5 | V111: 458 | W111: 428 | X111: 56 | Y111: 64 | Z111: 448 | AA111: 450.5 | AB111: 56 | AC111: 61.5 | AD111: 413.5 | AE111: 386 | AF111: 48.5 | AG111: 54 | AH111: 428.5 | AI111: 450 | AJ111: 49.5 | AK111: 72 | AL111: 407.5 | AM111: 342 | AN111: 52.5 | AO111: 54 | AP111: 385 | AQ111: 396 | AR111: 41 | AS111: 44 | AT111: 372 | AU111: 374 | AV111: 38 | AW111: 44 | AX111: 364 | AY111: 328 | AZ111: 48 | BA111: 42 | BB111: 403 | BC111: 410.5 | BD111: 51 | BE111: 57.5 | BF111: 28.5927 | BG111: 77.0659 | BH111: =BB111 -> 403 | BI111: =BC111 -> 410.5 | BJ111: =(BH111-BI111) -> -7.5 | BK111: =(BJ111)/BI111*100 -> -1.8270402 | BL111: =BD111 -> 51 | BM111: =BE111 -> 57.5 | BN111: =(BL111-BM111) -> -6.5 | BO111: =(BN111)/BM111*100 -> -11.304348 | BP111: =K111+O111+R111+V111+Z111+AD111+AH111+AL111+AP111+AT111+AX111+BB111 -> 4922.5 | BQ111: =J111+N111+S111+W111+AA111+AE111+AI111+AM111+AQ111+AU111+Table1[[#This Row],[MS-0225]]+Table1[[#This Row],[MS-0325]] -> 4742 | BR111: =(BP111-BQ111) -> 180.5 | BS111: =(BR111)/BQ111*100 -> 3.8064108 | BT111: =M111+Q111+T111+X111+AB111+AF111+AJ111+AN111+AR111+AV111+AZ111+BD111 -> 609.5 | BU111: =L111+P111+U111+Y111+AC111+AG111+AK111+AO111+AS111+AW111+BA111+BE111 -> 684 | BV111: =(BT111-BU111) -> -74.5 | BW111: =(BV111)/BU111*100 -> -10.891813 | BX111: 0 | BY111: =BX111/BH111 -> 0 | BZ111: 0 | CA111: =BZ111/BP111 -> 0 | CB111: =BH111/SUMIFS(BH$2:BH$398,G$2:G$398,G111) -> 0.10552501 | CC111: =BI111/SUMIFS(BI$2:BI$398,G$2:G$398,G111) -> 0.11333517 | CD111: =CB111-CC111 -> -0.0078101674 | CE111: =BL111/SUMIFS(BL$2:BL$398,G$2:G$398,G111) -> 0.094972067 | CF111: =BM111/SUMIFS(BM$2:BM$398,G$2:G$398,G111) -> 0.10087719 | CG111: =CE111-CF111 -> -0.0059051259 | CH111: =BP111/SUMIFS(BP$2:BP$398,G$2:G$398,G111) -> 0.10895549 | CI111: =BQ111/SUMIFS(BQ$2:BQ$398,G$2:G$398,G111) -> 0.10856227 | CJ111: =CH111-CI111 -> 0.00039321718 | CK111: =BT111/SUMIFS(BT$2:BT$398,G$2:G$398,G111) -> 0.095070972 | CL111: =BU111/SUMIFS(BU$2:BU$398,G$2:G$398,G111) -> 0.096774194 | CM111: =CK111-CL111 -> -0.0017032218 | CN111: =COUNTIFS(G$2:G$398,G111)*CH111 -> 0.76268842 | CO111: =COUNTIFS(G$2:G$398,G111)*CK111 -> 0.6654968
A112: 41057000 | B112: HPC | C112: BANSAL SER CENTRE | D112: LIBERTY CINEMA | E112: CENTRAL DELHI | F112: White Patch- Karol Bagh | G112: LINK ROAD | H112: Rohtak Road | I112: Abhinav | J112: 347.5 | K112: 342 | L112: 59.5 | M112: 42 | N112: 346 | O112: 356 | P112: 69 | Q112: 50 | R112: 338.5 | S112: 349 | T112: 45.5 | U112: 32 | V112: 361 | W112: 389 | X112: 45 | Y112: 64 | Z112: 389 | AA112: 351 | AB112: 46 | AC112: 45 | AD112: 366 | AE112: 348.5 | AF112: 40 | AG112: 54.5 | AH112: 385 | AI112: 360 | AJ112: 46 | AK112: 54 | AL112: 337 | AM112: 337.5 | AN112: 40 | AO112: 40.5 | AP112: 362 | AQ112: 319 | AR112: 44 | AS112: 37 | AT112: 335 | AU112: 325.5 | AV112: 38 | AW112: 39.5 | AX112: 309 | AY112: 307 | AZ112: 39 | BA112: 44 | BB112: 353 | BC112: 337 | BD112: 53 | BE112: 48 | BF112: 28.65957 | BG112: 77.18942 | BH112: =BB112 -> 353 | BI112: =BC112 -> 337 | BJ112: =(BH112-BI112) -> 16 | BK112: =(BJ112)/BI112*100 -> 4.7477745 | BL112: =BD112 -> 53 | BM112: =BE112 -> 48 | BN112: =(BL112-BM112) -> 5 | BO112: =(BN112)/BM112*100 -> 10.416667 | BP112: =K112+O112+R112+V112+Z112+AD112+AH112+AL112+AP112+AT112+AX112+BB112 -> 4233.5 | BQ112: =J112+N112+S112+W112+AA112+AE112+AI112+AM112+AQ112+AU112+Table1[[#This Row],[MS-0225]]+Table1[[#This Row],[MS-0325]] -> 4117 | BR112: =(BP112-BQ112) -> 116.5 | BS112: =(BR112)/BQ112*100 -> 2.8297304 | BT112: =M112+Q112+T112+X112+AB112+AF112+AJ112+AN112+AR112+AV112+AZ112+BD112 -> 528.5 | BU112: =L112+P112+U112+Y112+AC112+AG112+AK112+AO112+AS112+AW112+BA112+BE112 -> 587 | BV112: =(BT112-BU112) -> -58.5 | BW112: =(BV112)/BU112*100 -> -9.9659284 | BX112: 0 | BY112: =BX112/BH112 -> 0 | BZ112: 0 | CA112: =BZ112/BP112 -> 0 | CB112: =BH112/SUMIFS(BH$2:BH$398,G$2:G$398,G112) -> 0.27018752 | CC112: =BI112/SUMIFS(BI$2:BI$398,G$2:G$398,G112) -> 0.27828241 | CD112: =CB112-CC112 -> -0.0080948873 | CE112: =BL112/SUMIFS(BL$2:BL$398,G$2:G$398,G112) -> 0.12282735 | CF112: =BM112/SUMIFS(BM$2:BM$398,G$2:G$398,G112) -> 0.083333333 | CG112: =CE112-CF112 -> 0.039494013 | CH112: =BP112/SUMIFS(BP$2:BP$398,G$2:G$398,G112) -> 0.27371177 | CI112: =BQ112/SUMIFS(BQ$2:BQ$398,G$2:G$398,G112) -> 0.28344234 | CJ112: =CH112-CI112 -> -0.009730567 | CK112: =BT112/SUMIFS(BT$2:BT$398,G$2:G$398,G112) -> 0.086074919 | CL112: =BU112/SUMIFS(BU$2:BU$398,G$2:G$398,G112) -> 0.08843025 | CM112: =CK112-CL112 -> -0.0023553315 | CN112: =COUNTIFS(G$2:G$398,G112)*CH112 -> 1.0948471 | CO112: =COUNTIFS(G$2:G$398,G112)*CK112 -> 0.34429967 | CP112: =BD112-AZ112 -> 14
A113: 41056499 | B113: HPC | C113: PUSA ROAD SERVICE STATION | D113: PUSA ROAD | E113: CENTRAL DELHI | F113: LINK ROAD | G113: LINK ROAD | H113: Old Delhi | I113: Abhinav | J113: 214.5 | K113: 234 | L113: 107.5 | M113: 102 | N113: 243 | O113: 267 | P113: 137 | Q113: 139 | R113: 226 | S113: 227 | T113: 93 | U113: 109 | V113: 273 | W113: 250 | X113: 129 | Y113: 106 | Z113: 280 | AA113: 245 | AB113: 126 | AC113: 112 | AD113: 269 | AE113: 235.5 | AF113: 137 | AG113: 133.5 | AH113: 259 | AI113: 256 | AJ113: 118 | AK113: 132 | AL113: 247 | AM113: 218.5 | AN113: 101 | AO113: 111.5 | AP113: 241 | AQ113: 229 | AR113: 107 | AS113: 111 | AT113: 235 | AU113: 223.5 | AV113: 103 | AW113: 128.5 | AX113: 220 | AY113: 205 | AZ113: 93 | BA113: 120 | BB113: 242 | BC113: 231 | BD113: 106 | BE113: 113 | BF113: 28.64451 | BG113: 77.19456 | BH113: =BB113 -> 242 | BI113: =BC113 -> 231 | BJ113: =(BH113-BI113) -> 11 | BK113: =(BJ113)/BI113*100 -> 4.7619048 | BL113: =BD113 -> 106 | BM113: =BE113 -> 113 | BN113: =(BL113-BM113) -> -7 | BO113: =(BN113)/BM113*100 -> -6.1946903 | BP113: =K113+O113+R113+V113+Z113+AD113+AH113+AL113+AP113+AT113+AX113+BB113 -> 2993 | BQ113: =J113+N113+S113+W113+AA113+AE113+AI113+AM113+AQ113+AU113+Table1[[#This Row],[MS-0225]]+Table1[[#This Row],[MS-0325]] -> 2778 | BR113: =(BP113-BQ113) -> 215 | BS113: =(BR113)/BQ113*100 -> 7.7393808 | BT113: =M113+Q113+T113+X113+AB113+AF113+AJ113+AN113+AR113+AV113+AZ113+BD113 -> 1354 | BU113: =L113+P113+U113+Y113+AC113+AG113+AK113+AO113+AS113+AW113+BA113+BE113 -> 1421 | BV113: =(BT113-BU113) -> -67 | BW113: =(BV113)/BU113*100 -> -4.7149894 | BX113: 0 | BY113: =BX113/BH113 -> 0 | BZ113: 0 | CA113: =BZ113/BP113 -> 0 | CB113: =BH113/SUMIFS(BH$2:BH$398,G$2:G$398,G113) -> 0.18522771 | CC113: =BI113/SUMIFS(BI$2:BI$398,G$2:G$398,G113) -> 0.19075145 | CD113: =CB113-CC113 -> -0.0055237375 | CE113: =BL113/SUMIFS(BL$2:BL$398,G$2:G$398,G113) -> 0.24565469 | CF113: =BM113/SUMIFS(BM$2:BM$398,G$2:G$398,G113) -> 0.19618056 | CG113: =CE113-CF113 -> 0.049474137 | CH113: =BP113/SUMIFS(BP$2:BP$398,G$2:G$398,G113) -> 0.19350876 | CI113: =BQ113/SUMIFS(BQ$2:BQ$398,G$2:G$398,G113) -> 0.19125645 | CJ113: =CH113-CI113 -> 0.0022523064 | CK113: =BT113/SUMIFS(BT$2:BT$398,G$2:G$398,G113) -> 0.22052117 | CL113: =BU113/SUMIFS(BU$2:BU$398,G$2:G$398,G113) -> 0.2140705 | CM113: =CK113-CL113 -> 0.0064506695 | CN113: =COUNTIFS(G$2:G$398,G113)*CH113 -> 0.77403504 | CO113: =COUNTIFS(G$2:G$398,G113)*CK113 -> 0.88208469 | CP113: =BD113-AZ113 -> 13
A114: 41032431 | B114: HPC | C114: SUPER SERVICE STATION | D114: PITAMPURA | E114: NORTH WEST DELHI | F114: KIRTINANAK | G114: White Patch-Pitampura | H114: Rohtak Road | I114: Abhinav | J114: 342 | K114: 373 | L114: 72 | M114: 70 | N114: 418.5 | O114: 405 | P114: 103.5 | Q114: 75 | R114: 358 | S114: 371.5 | T114: 85 | U114: 85.5 | V114: 397 | W114: 396 | X114: 80 | Y114: 90 | Z114: 416 | AA114: 405 | AB114: 70 | AC114: 81 | AD114: 410 | AE114: 382.5 | AF114: 80 | AG114: 85.5 | AH114: 408 | AI114: 397 | AJ114: 85 | AK114: 74 | AL114: 388 | AM114: 339 | AN114: 60 | AO114: 72 | AP114: 368 | AQ114: 351 | AR114: 55 | AS114: 63 | AT114: 375 | AU114: 352.5 | AV114: 68 | AW114: 53.5 | AX114: 350 | AY114: 315 | AZ114: 65 | BA114: 53 | BB114: 374 | BC114: 348 | BD114: 77 | BE114: 70 | BF114: 28.70503 | BG114: 77.14119 | BH114: =BB114 -> 374 | BI114: =BC114 -> 348 | BJ114: =(BH114-BI114) -> 26 | BK114: =(BJ114)/BI114*100 -> 7.4712644 | BL114: =BD114 -> 77 | BM114: =BE114 -> 70 | BN114: =(BL114-BM114) -> 7 | BO114: =(BN114)/BM114*100 -> 10 | BP114: =K114+O114+R114+V114+Z114+AD114+AH114+AL114+AP114+AT114+AX114+BB114 -> 4622 | BQ114: =J114+N114+S114+W114+AA114+AE114+AI114+AM114+AQ114+AU114+Table1[[#This Row],[MS-0225]]+Table1[[#This Row],[MS-0325]] -> 4418 | BR114: =(BP114-BQ114) -> 204 | BS114: =(BR114)/BQ114*100 -> 4.617474 | BT114: =M114+Q114+T114+X114+AB114+AF114+AJ114+AN114+AR114+AV114+AZ114+BD114 -> 870 | BU114: =L114+P114+U114+Y114+AC114+AG114+AK114+AO114+AS114+AW114+BA114+BE114 -> 903 | BV114: =(BT114-BU114) -> -33 | BW114: =(BV114)/BU114*100 -> -3.654485 | BX114: 0 | BY114: =BX114/BH114 -> 0 | BZ114: 0 | CA114: =BZ114/BP114 -> 0 | CB114: =BH114/SUMIFS(BH$2:BH$398,G$2:G$398,G114) -> 0.2473545 | CC114: =BI114/SUMIFS(BI$2:BI$398,G$2:G$398,G114) -> 0.21969697 | CD114: =CB114-CC114 -> 0.027657528 | CE114: =BL114/SUMIFS(BL$2:BL$398,G$2:G$398,G114) -> 0.16666667 | CF114: =BM114/SUMIFS(BM$2:BM$398,G$2:G$398,G114) -> 0.11308562 | CG114: =CE114-CF114 -> 0.053581045 | CH114: =BP114/SUMIFS(BP$2:BP$398,G$2:G$398,G114) -> 0.24837444 | CI114: =BQ114/SUMIFS(BQ$2:BQ$398,G$2:G$398,G114) -> 0.24162524 | CJ114: =CH114-CI114 -> 0.006749207 | CK114: =BT114/SUMIFS(BT$2:BT$398,G$2:G$398,G114) -> 0.14981918 | CL114: =BU114/SUMIFS(BU$2:BU$398,G$2:G$398,G114) -> 0.11920005 | CM114: =CK114-CL114 -> 0.030619131 | CN114: =COUNTIFS(G$2:G$398,G114)*CH114 -> 1.2418722 | CO114: =COUNTIFS(G$2:G$398,G114)*CK114 -> 0.74909592 | CP114: =BD114-AZ114 -> 12
A115: 112427 | B115: BPC | C115: MUKUL DIESELS | D115: GOKULPUR DELHI | E115: NORTH EAST DELHI | F115: MUKUL | G115: MUKUL | H115: Wazirabad-Loni | I115: Bhanu Pratap | J115: 337.5 | K115: 388.5 | L115: 130.5 | M115: 85.5 | N115: 344 | O115: 393 | P115: 130 | Q115: 99 | R115: 331 | S115: 327.5 | T115: 107 | U115: 98.5 | V115: 405 | W115: 333 | X115: 81 | Y115: 99 | Z115: 408 | AA115: 357 | AB115: 90 | AC115: 81 | AD115: 373.5 | AE115: 351 | AF115: 94.5 | AG115: 81 | AH115: 418.5 | AI115: 364.5 | AJ115: 103.5 | AK115: 103.5 | AL115: 400.5 | AM115: 367.5 | AN115: 103.5 | AO115: 58.5 | AP115: 328.5 | AQ115: 324 | AR115: 103.5 | AS115: 72 | AT115: 319.5 | AU115: 324 | AV115: 148.5 | AW115: 90 | AX115: 333 | AY115: 310.5 | AZ115: 153 | BA115: 103.5 | BB115: 400.5 | BC115: 336 | BD115: 175.5 | BE115: 90 | BF115: 28.70165 | BG115: 77.28962 | BH115: =BB115 -> 400.5 | BI115: =BC115 -> 336 | BJ115: =(BH115-BI115) -> 64.5 | BK115: =(BJ115)/BI115*100 -> 19.196429 | BL115: =BD115 -> 175.5 | BM115: =BE115 -> 90 | BN115: =(BL115-BM115) -> 85.5 | BO115: =(BN115)/BM115*100 -> 95 | BP115: =K115+O115+R115+V115+Z115+AD115+AH115+AL115+AP115+AT115+AX115+BB115 -> 4499.5 | BQ115: =J115+N115+S115+W115+AA115+AE115+AI115+AM115+AQ115+AU115+Table1[[#This Row],[MS-0225]]+Table1[[#This Row],[MS-0325]] -> 4076.5 | BR115: =(BP115-BQ115) -> 423 | BS115: =(BR115)/BQ115*100 -> 10.376549 | BT115: =M115+Q115+T115+X115+AB115+AF115+AJ115+AN115+AR115+AV115+AZ115+BD115 -> 1344.5 | BU115: =L115+P115+U115+Y115+AC115+AG115+AK115+AO115+AS115+AW115+BA115+BE115 -> 1137.5 | BV115: =(BT115-BU115) -> 207 | BW115: =(BV115)/BU115*100 -> 18.197802 | BX115: 9 | BY115: =BX115/BH115 -> 0.02247191 | BZ115: 44 | CA115: =BZ115/BP115 -> 0.0097788643 | CB115: =BH115/SUMIFS(BH$2:BH$398,G$2:G$398,G115) -> 0.31106796 | CC115: =BI115/SUMIFS(BI$2:BI$398,G$2:G$398,G115) -> 0.28414376 | CD115: =CB115-CC115 -> 0.026924198 | CE115: =BL115/SUMIFS(BL$2:BL$398,G$2:G$398,G115) -> 0.42962056 | CF115: =BM115/SUMIFS(BM$2:BM$398,G$2:G$398,G115) -> 0.2907916 | CG115: =CE115-CF115 -> 0.13882896 | CH115: =BP115/SUMIFS(BP$2:BP$398,G$2:G$398,G115) -> 0.29691831 | CI115: =BQ115/SUMIFS(BQ$2:BQ$398,G$2:G$398,G115) -> 0.29555918 | CJ115: =CH115-CI115 -> 0.0013591247 | CK115: =BT115/SUMIFS(BT$2:BT$398,G$2:G$398,G115) -> 0.33926318 | CL115: =BU115/SUMIFS(BU$2:BU$398,G$2:G$398,G115) -> 0.28830313 | CM115: =CK115-CL115 -> 0.050960054 | CN115: =COUNTIFS(G$2:G$398,G115)*CH115 -> 0.89075492 | CO115: =COUNTIFS(G$2:G$398,G115)*CK115 -> 1.0177896
A116: 106276 | B116: IOC | C116: JINDAL SERVICE STATION | D116: ISHWAR NAGAR MATHURA ROAD | E116: SOUTH EAST DELHI | F116: AUTO REST_OKHLA | G116: AUTO REST_OKHLA | H116: Mathura Road | I116: Bhanu Pratap | J116: 386.5 | K116: 390 | L116: 121.5 | M116: 90 | N116: 418.5 | O116: 405 | P116: 121.5 | Q116: 95 | R116: 405 | S116: 405 | T116: 95 | U116: 117 | V116: 445 | W116: 400.5 | X116: 95 | Y116: 103.5 | Z116: 440 | AA116: 451 | AB116: 100 | AC116: 113 | AD116: 410 | AE116: 393.5 | AF116: 90 | AG116: 104.5 | AH116: 428 | AI116: 410 | AJ116: 90 | AK116: 110 | AL116: 400 | AM116: 414.5 | AN116: 80 | AO116: 90 | AP116: 400 | AQ116: 385 | AR116: 80 | AS116: 95 | AT116: 360 | AU116: 370 | AV116: 80 | AW116: 90 | AX116: 395 | AY116: 370 | AZ116: 85 | BA116: 90 | BB116: 400 | BC116: 420 | BD116: 80 | BE116: 100 | BF116: 28.5623 | BG116: 77.2663 | BH116: =BB116 -> 400 | BI116: =BC116 -> 420 | BJ116: =(BH116-BI116) -> -20 | BK116: =(BJ116)/BI116*100 -> -4.7619048 | BL116: =BD116 -> 80 | BM116: =BE116 -> 100 | BN116: =(BL116-BM116) -> -20 | BO116: =(BN116)/BM116*100 -> -20 | BP116: =K116+O116+R116+V116+Z116+AD116+AH116+AL116+AP116+AT116+AX116+BB116 -> 4878 | BQ116: =J116+N116+S116+W116+AA116+AE116+AI116+AM116+AQ116+AU116+Table1[[#This Row],[MS-0225]]+Table1[[#This Row],[MS-0325]] -> 4824.5 | BR116: =(BP116-BQ116) -> 53.5 | BS116: =(BR116)/BQ116*100 -> 1.1089232 | BT116: =M116+Q116+T116+X116+AB116+AF116+AJ116+AN116+AR116+AV116+AZ116+BD116 -> 1060 | BU116: =L116+P116+U116+Y116+AC116+AG116+AK116+AO116+AS116+AW116+BA116+BE116 -> 1256 | BV116: =(BT116-BU116) -> -196 | BW116: =(BV116)/BU116*100 -> -15.605096 | BX116: 0 | BY116: =BX116/BH116 -> 0 | BZ116: 0 | CA116: =BZ116/BP116 -> 0 | CB116: =BH116/SUMIFS(BH$2:BH$398,G$2:G$398,G116) -> 0.072661217 | CC116: =BI116/SUMIFS(BI$2:BI$398,G$2:G$398,G116) -> 0.080444359 | CD116: =CB116-CC116 -> -0.0077831422 | CE116: =BL116/SUMIFS(BL$2:BL$398,G$2:G$398,G116) -> 0.055594163 | CF116: =BM116/SUMIFS(BM$2:BM$398,G$2:G$398,G116) -> 0.064308682 | CG116: =CE116-CF116 -> -0.0087145191 | CH116: =BP116/SUMIFS(BP$2:BP$398,G$2:G$398,G116) -> 0.075958828 | CI116: =BQ116/SUMIFS(BQ$2:BQ$398,G$2:G$398,G116) -> 0.07563987 | CJ116: =CH116-CI116 -> 0.00031895856 | CK116: =BT116/SUMIFS(BT$2:BT$398,G$2:G$398,G116) -> 0.059046346 | CL116: =BU116/SUMIFS(BU$2:BU$398,G$2:G$398,G116) -> 0.060095694 | CM116: =CK116-CL116 -> -0.001049348 | CN116: =COUNTIFS(G$2:G$398,G116)*CH116 -> 0.83554711 | CO116: =COUNTIFS(G$2:G$398,G116)*CK116 -> 0.6495098
A117: 112392 | B117: BPC | C117: AUTO GRIT | D117: BADARPUR, MEHRAULI | E117: SOUTH EAST DELHI | F117: AUTO GRIT | G117: AUTO GRIT | H117: Mehrauli Badarpur Road | I117: Bhanu Pratap | J117: 400.50001 | K117: 414 | L117: 247.5 | M117: 198 | N117: 423.00001 | O117: 427.5 | P117: 207 | Q117: 238.5 | R117: 418.5 | S117: 405.00001 | T117: 229.5 | U117: 225 | V117: 423 | W117: 405 | X117: 207 | Y117: 279 | Z117: 414 | AA117: 423 | AB117: 216 | AC117: 243 | AD117: 373 | AE117: 400.5 | AF117: 229 | AG117: 229.5 | AH117: 405 | AI117: 418.5 | AJ117: 195 | AK117: 265.5 | AL117: 380 | AM117: 400.50001 | AN117: 140 | AO117: 193.5 | AP117: 335 | AQ117: 391.5 | AR117: 145 | AS117: 220.5 | AT117: 380 | AU117: 400.5 | AV117: 180 | AW117: 247.5 | AX117: 365 | AY117: 387 | AZ117: 195 | BA117: 225 | BB117: 400 | BC117: 405 | BD117: 200 | BE117: 225 | BF117: 28.50304 | BG117: 77.28071 | BH117: =BB117 -> 400 | BI117: =BC117 -> 405 | BJ117: =(BH117-BI117) -> -5 | BK117: =(BJ117)/BI117*100 -> -1.2345679 | BL117: =BD117 -> 200 | BM117: =BE117 -> 225 | BN117: =(BL117-BM117) -> -25 | BO117: =(BN117)/BM117*100 -> -11.111111 | BP117: =K117+O117+R117+V117+Z117+AD117+AH117+AL117+AP117+AT117+AX117+BB117 -> 4735 | BQ117: =J117+N117+S117+W117+AA117+AE117+AI117+AM117+AQ117+AU117+Table1[[#This Row],[MS-0225]]+Table1[[#This Row],[MS-0325]] -> 4860 | BR117: =(BP117-BQ117) -> -125.00004 | BS117: =(BR117)/BQ117*100 -> -2.5720172 | BT117: =M117+Q117+T117+X117+AB117+AF117+AJ117+AN117+AR117+AV117+AZ117+BD117 -> 2373 | BU117: =L117+P117+U117+Y117+AC117+AG117+AK117+AO117+AS117+AW117+BA117+BE117 -> 2808 | BV117: =(BT117-BU117) -> -435 | BW117: =(BV117)/BU117*100 -> -15.491453 | BX117: 35 | BY117: =BX117/BH117 -> 0.0875 | BZ117: 280.5 | CA117: =BZ117/BP117 -> 0.059239704 | CB117: =BH117/SUMIFS(BH$2:BH$398,G$2:G$398,G117) -> 0.67114094 | CC117: =BI117/SUMIFS(BI$2:BI$398,G$2:G$398,G117) -> 0.70866142 | CD117: =CB117-CC117 -> -0.037520478 | CE117: =BL117/SUMIFS(BL$2:BL$398,G$2:G$398,G117) -> 0.67114094 | CF117: =BM117/SUMIFS(BM$2:BM$398,G$2:G$398,G117) -> 0.64935065 | CG117: =CE117-CF117 -> 0.02179029 | CH117: =BP117/SUMIFS(BP$2:BP$398,G$2:G$398,G117) -> 0.69428152 | CI117: =BQ117/SUMIFS(BQ$2:BQ$398,G$2:G$398,G117) -> 0.70134931 | CJ117: =CH117-CI117 -> -0.0070677803 | CK117: =BT117/SUMIFS(BT$2:BT$398,G$2:G$398,G117) -> 0.64343818 | CL117: =BU117/SUMIFS(BU$2:BU$398,G$2:G$398,G117) -> 0.62532012 | CM117: =CK117-CL117 -> 0.018118058 | CN117: =COUNTIFS(G$2:G$398,G117)*CH117 -> 1.388563 | CO117: =COUNTIFS(G$2:G$398,G117)*CK117 -> 1.2868764
A118: 332207 | B118: IOC | C118: COCO-BAWANA SEC-3 (12.09.20) | D118: BAWANA DELHI | E118: NORTH WEST DELHI | F118: White Patch DSIDC | G118: White Patch DSIDC | H118: Narela- Bawana | I118: Abhinav | J118: 162.473 | K118: 174.722 | L118: 70.807 | M118: 60.502 | N118: 185 | O118: 178.27 | P118: 67.5 | Q118: 61.602 | R118: 198 | S118: 170.649 | T118: 72 | U118: 67.633 | V118: 182.406 | W118: 181.624 | X118: 63.184 | Y118: 92.051 | Z118: 215.779 | AA118: 168 | AB118: 85.173 | AC118: 66 | AD118: 222.204 | AE118: 182.334 | AF118: 99.871 | AG118: 74.378 | AH118: 180.973 | AI118: 175.5 | AJ118: 67.961 | AK118: 76.5 | AL118: 202.857 | AM118: 152.215 | AN118: 78.738 | AO118: 52.916 | AP118: 185.391 | AQ118: 171.65 | AR118: 62.576 | AS118: 64.402 | AT118: 173.021 | AU118: 184 | AV118: 65.358 | AW118: 70 | AX118: 170.622 | AY118: 155.403 | AZ118: 64.257 | BA118: 60.385 | BB118: 189.498 | BC118: 170.152 | BD118: 88.007 | BE118: 64.469 | BF118: 28.785717 | BG118: 77.049173 | BH118: =BB118 -> 189.498 | BI118: =BC118 -> 170.152 | BJ118: =(BH118-BI118) -> 19.346 | BK118: =(BJ118)/BI118*100 -> 11.369834 | BL118: =BD118 -> 88.007 | BM118: =BE118 -> 64.469 | BN118: =(BL118-BM118) -> 23.538 | BO118: =(BN118)/BM118*100 -> 36.510571 | BP118: =K118+O118+R118+V118+Z118+AD118+AH118+AL118+AP118+AT118+AX118+BB118 -> 2273.743 | BQ118: =J118+N118+S118+W118+AA118+AE118+AI118+AM118+AQ118+AU118+Table1[[#This Row],[MS-0225]]+Table1[[#This Row],[MS-0325]] -> 2059 | BR118: =(BP118-BQ118) -> 214.743 | BS118: =(BR118)/BQ118*100 -> 10.42948 | BT118: =M118+Q118+T118+X118+AB118+AF118+AJ118+AN118+AR118+AV118+AZ118+BD118 -> 869.229 | BU118: =L118+P118+U118+Y118+AC118+AG118+AK118+AO118+AS118+AW118+BA118+BE118 -> 827.041 | BV118: =(BT118-BU118) -> 42.188 | BW118: =(BV118)/BU118*100 -> 5.1010772 | BX118: 0 | BY118: =BX118/BH118 -> 0 | BZ118: 0 | CA118: =BZ118/BP118 -> 0 | CB118: =BH118/SUMIFS(BH$2:BH$398,G$2:G$398,G118) -> 0.43730341 | CC118: =BI118/SUMIFS(BI$2:BI$398,G$2:G$398,G118) -> 0.50185521 | CD118: =CB118-CC118 -> -0.064551792 | CE118: =BL118/SUMIFS(BL$2:BL$398,G$2:G$398,G118) -> 0.49173614 | CF118: =BM118/SUMIFS(BM$2:BM$398,G$2:G$398,G118) -> 0.51738279 | CG118: =CE118-CF118 -> -0.025646653 | CH118: =BP118/SUMIFS(BP$2:BP$398,G$2:G$398,G118) -> 0.45857708 | CI118: =BQ118/SUMIFS(BQ$2:BQ$398,G$2:G$398,G118) -> 0.50162388 | CJ118: =CH118-CI118 -> -0.043046806 | CK118: =BT118/SUMIFS(BT$2:BT$398,G$2:G$398,G118) -> 0.48432893 | CL118: =BU118/SUMIFS(BU$2:BU$398,G$2:G$398,G118) -> 0.52761854 | CM118: =CK118-CL118 -> -0.043289609 | CN118: =COUNTIFS(G$2:G$398,G118)*CH118 -> 0.91715415 | CO118: =COUNTIFS(G$2:G$398,G118)*CK118 -> 0.96865785
A119: 112419 | B119: BPC | C119: LINK ROAD PETROL S.STN. | D119: LINK ROAD KAROL BAG | E119: CENTRAL DELHI | F119: LINK ROAD | G119: LINK ROAD | H119: Old Delhi | I119: Abhinav | J119: 346.5 | K119: 382.5 | L119: 157.5 | M119: 173.5 | N119: 378 | O119: 386 | P119: 180 | Q119: 226 | R119: 369 | S119: 382.5 | T119: 209 | U119: 139.5 | V119: 407 | W119: 382.5 | X119: 207 | Y119: 121.5 | Z119: 408 | AA119: 396 | AB119: 188 | AC119: 162 | AD119: 395 | AE119: 378 | AF119: 145 | AG119: 180 | AH119: 411 | AI119: 378 | AJ119: 139 | AK119: 198 | AL119: 365 | AM119: 351.5 | AN119: 75 | AO119: 150.5 | AP119: 398 | AQ119: 357.5 | AR119: 100 | AS119: 218.5 | AT119: 350 | AU119: 354 | AV119: 110 | AW119: 206 | AX119: 370 | AY119: 321 | AZ119: 110 | BA119: 191 | BB119: 399 | BC119: 356.5 | BD119: 119 | BE119: 157.5 | BF119: 28.64506 | BG119: 77.19888 | BH119: =BB119 -> 399 | BI119: =BC119 -> 356.5 | BJ119: =(BH119-BI119) -> 42.5 | BK119: =(BJ119)/BI119*100 -> 11.921459 | BL119: =BD119 -> 119 | BM119: =BE119 -> 157.5 | BN119: =(BL119-BM119) -> -38.5 | BO119: =(BN119)/BM119*100 -> -24.444444 | BP119: =K119+O119+R119+V119+Z119+AD119+AH119+AL119+AP119+AT119+AX119+BB119 -> 4640.5 | BQ119: =J119+N119+S119+W119+AA119+AE119+AI119+AM119+AQ119+AU119+Table1[[#This Row],[MS-0225]]+Table1[[#This Row],[MS-0325]] -> 4382 | BR119: =(BP119-BQ119) -> 258.49999 | BS119: =(BR119)/BQ119*100 -> 5.8991327 | BT119: =M119+Q119+T119+X119+AB119+AF119+AJ119+AN119+AR119+AV119+AZ119+BD119 -> 1801.5 | BU119: =L119+P119+U119+Y119+AC119+AG119+AK119+AO119+AS119+AW119+BA119+BE119 -> 2062 | BV119: =(BT119-BU119) -> -260.5 | BW119: =(BV119)/BU119*100 -> -12.633366 | BX119: 24 | BY119: =BX119/BH119 -> 0.060150376 | BZ119: 118.5 | CA119: =BZ119/BP119 -> 0.025536041 | CB119: =BH119/SUMIFS(BH$2:BH$398,G$2:G$398,G119) -> 0.3053961 | CC119: =BI119/SUMIFS(BI$2:BI$398,G$2:G$398,G119) -> 0.29438481 | CD119: =CB119-CC119 -> 0.01101129 | CE119: =BL119/SUMIFS(BL$2:BL$398,G$2:G$398,G119) -> 0.27578216 | CF119: =BM119/SUMIFS(BM$2:BM$398,G$2:G$398,G119) -> 0.2734375 | CG119: =CE119-CF119 -> 0.0023446553 | CH119: =BP119/SUMIFS(BP$2:BP$398,G$2:G$398,G119) -> 0.30002586 | CI119: =BQ119/SUMIFS(BQ$2:BQ$398,G$2:G$398,G119) -> 0.30168675 | CJ119: =CH119-CI119 -> -0.0016608855 | CK119: =BT119/SUMIFS(BT$2:BT$398,G$2:G$398,G119) -> 0.29340391 | CL119: =BU119/SUMIFS(BU$2:BU$398,G$2:G$398,G119) -> 0.31063573 | CM119: =CK119-CL119 -> -0.017231825 | CN119: =COUNTIFS(G$2:G$398,G119)*CH119 -> 1.2001034 | CO119: =COUNTIFS(G$2:G$398,G119)*CK119 -> 1.1736156
A120: 41026624 | B120: HPC | C120: GOPI SERVICE STATION | D120: OLD WAZIRABAD ROAD | E120: NORTH EAST DELHI | F120: White Patch_Wazirabad | G120: White Patch_Wazirabad | H120: Wazirabad-Loni | I120: Bhanu Pratap | J120: 360 | K120: 356 | L120: 54 | M120: 23 | N120: 360 | O120: 399.5 | P120: 72 | Q120: 53.5 | R120: 393.5 | S120: 315 | T120: 57.5 | U120: 45 | V120: 350 | W120: 354 | X120: 24 | Y120: 54 | Z120: 379.5 | AA120: 341 | AB120: 50.5 | AC120: 49 | AD120: 401.5 | AE120: 351 | AF120: 46.5 | AG120: 63 | AH120: 383 | AI120: 346.5 | AJ120: 49 | AK120: 67.5 | AL120: 389.5 | AM120: 382.5 | AN120: 59.5 | AO120: 49.5 | AP120: 377.5 | AQ120: 319.5 | AR120: 46.5 | AS120: 41.5 | AT120: 366 | AU120: 354.5 | AV120: 46 | AW120: 63.5 | AX120: 344.5 | AY120: 326 | AZ120: 47.5 | BA120: 34 | BB120: 397 | BC120: 391.5 | BD120: 27 | BE120: 59.5 | BF120: 28.701222 | BG120: 77.285937 | BH120: =BB120 -> 397 | BI120: =BC120 -> 391.5 | BJ120: =(BH120-BI120) -> 5.5 | BK120: =(BJ120)/BI120*100 -> 1.4048531 | BL120: =BD120 -> 27 | BM120: =BE120 -> 59.5 | BN120: =(BL120-BM120) -> -32.5 | BO120: =(BN120)/BM120*100 -> -54.621849 | BP120: =K120+O120+R120+V120+Z120+AD120+AH120+AL120+AP120+AT120+AX120+BB120 -> 4537.5 | BQ120: =J120+N120+S120+W120+AA120+AE120+AI120+AM120+AQ120+AU120+Table1[[#This Row],[MS-0225]]+Table1[[#This Row],[MS-0325]] -> 4201.5 | BR120: =(BP120-BQ120) -> 336 | BS120: =(BR120)/BQ120*100 -> 7.9971439 | BT120: =M120+Q120+T120+X120+AB120+AF120+AJ120+AN120+AR120+AV120+AZ120+BD120 -> 530.5 | BU120: =L120+P120+U120+Y120+AC120+AG120+AK120+AO120+AS120+AW120+BA120+BE120 -> 652.5 | BV120: =(BT120-BU120) -> -122 | BW120: =(BV120)/BU120*100 -> -18.697318 | BX120: 0 | BY120: =BX120/BH120 -> 0 | BZ120: 0 | CA120: =BZ120/BP120 -> 0 | CB120: =BH120/SUMIFS(BH$2:BH$398,G$2:G$398,G120) -> 0.20538024 | CC120: =BI120/SUMIFS(BI$2:BI$398,G$2:G$398,G120) -> 0.19842879 | CD120: =CB120-CC120 -> 0.0069514493 | CE120: =BL120/SUMIFS(BL$2:BL$398,G$2:G$398,G120) -> 0.10931174 | CF120: =BM120/SUMIFS(BM$2:BM$398,G$2:G$398,G120) -> 0.22537879 | CG120: =CE120-CF120 -> -0.11606705 | CH120: =BP120/SUMIFS(BP$2:BP$398,G$2:G$398,G120) -> 0.19019176 | CI120: =BQ120/SUMIFS(BQ$2:BQ$398,G$2:G$398,G120) -> 0.18032189 | CJ120: =CH120-CI120 -> 0.0098698752 | CK120: =BT120/SUMIFS(BT$2:BT$398,G$2:G$398,G120) -> 0.17093604 | CL120: =BU120/SUMIFS(BU$2:BU$398,G$2:G$398,G120) -> 0.18044801 | CM120: =CK120-CL120 -> -0.0095119689 | CN120: =COUNTIFS(G$2:G$398,G120)*CH120 -> 0.95095882 | CO120: =COUNTIFS(G$2:G$398,G120)*CK120 -> 0.8546802
A121: 150887 | B121: IOC | C121: SHREENATH FILLING STATION | D121: KANJHAWALA | E121: NORTH WEST DELHI | F121: BHAGWATI_GREENHRT_TRIYAMJIT | G121: BHAGWATI_GREENHRT_TRIYAMJIT | H121: Narela- Bawana | I121: Abhinav | J121: 36 | K121: 38 | L121: 48 | M121: 34 | N121: 40.5 | O121: 34 | P121: 49.5 | Q121: 26 | R121: 38.5 | S121: 40.5 | T121: 21.5 | U121: 31.5 | V121: 38 | W121: 41.5 | X121: 22 | Y121: 32.5 | Z121: 43.5 | AA121: 40.5 | AB121: 22.5 | AC121: 29.5 | AD121: 39 | AE121: 38 | AF121: 27 | AG121: 34 | AH121: 42 | AI121: 39 | AJ121: 48 | AK121: 27 | AL121: 40 | AM121: 30 | AN121: 26 | AO121: 18 | AP121: 42 | AQ121: 30 | AR121: 18 | AS121: 18 | AT121: 40 | AU121: 38 | AV121: 26 | AW121: 22 | AX121: 42 | AY121: 30 | AZ121: 18 | BA121: 18 | BB121: 36 | BC121: 41 | BD121: 48 | BE121: 25 | BF121: 28.7191 | BG121: 77.0043 | BH121: =BB121 -> 36 | BI121: =BC121 -> 41 | BJ121: =(BH121-BI121) -> -5 | BK121: =(BJ121)/BI121*100 -> -12.195122 | BL121: =BD121 -> 48 | BM121: =BE121 -> 25 | BN121: =(BL121-BM121) -> 23 | BO121: =(BN121)/BM121*100 -> 92 | BP121: =K121+O121+R121+V121+Z121+AD121+AH121+AL121+AP121+AT121+AX121+BB121 -> 473 | BQ121: =J121+N121+S121+W121+AA121+AE121+AI121+AM121+AQ121+AU121+Table1[[#This Row],[MS-0225]]+Table1[[#This Row],[MS-0325]] -> 445 | BR121: =(BP121-BQ121) -> 28 | BS121: =(BR121)/BQ121*100 -> 6.2921348 | BT121: =M121+Q121+T121+X121+AB121+AF121+AJ121+AN121+AR121+AV121+AZ121+BD121 -> 337 | BU121: =L121+P121+U121+Y121+AC121+AG121+AK121+AO121+AS121+AW121+BA121+BE121 -> 353 | BV121: =(BT121-BU121) -> -16 | BW121: =(BV121)/BU121*100 -> -4.5325779 | BX121: 0 | BY121: =BX121/BH121 -> 0 | BZ121: 0 | CA121: =BZ121/BP121 -> 0 | CB121: =BH121/SUMIFS(BH$2:BH$398,G$2:G$398,G121) -> 0.081172492 | CC121: =BI121/SUMIFS(BI$2:BI$398,G$2:G$398,G121) -> 0.08094768 | CD121: =CB121-CC121 -> 0.00022481139 | CE121: =BL121/SUMIFS(BL$2:BL$398,G$2:G$398,G121) -> 0.093658537 | CF121: =BM121/SUMIFS(BM$2:BM$398,G$2:G$398,G121) -> 0.056369786 | CG121: =CE121-CF121 -> 0.037288751 | CH121: =BP121/SUMIFS(BP$2:BP$398,G$2:G$398,G121) -> 0.085727232 | CI121: =BQ121/SUMIFS(BQ$2:BQ$398,G$2:G$398,G121) -> 0.075628824 | CJ121: =CH121-CI121 -> 0.010098408 | CK121: =BT121/SUMIFS(BT$2:BT$398,G$2:G$398,G121) -> 0.057779683 | CL121: =BU121/SUMIFS(BU$2:BU$398,G$2:G$398,G121) -> 0.060136286 | CM121: =CK121-CL121 -> -0.0023566034 | CN121: =COUNTIFS(G$2:G$398,G121)*CH121 -> 0.60009062 | CO121: =COUNTIFS(G$2:G$398,G121)*CK121 -> 0.40445778
A122: 149238 | B122: BPC | C122: BP - VASANT VIHAR | D122: VASANT VIHAR DELHI | E122: NEW DELHI | F122: BP VASANT VIHAR | G122: BP VASANT VIHAR | H122: Outer Ring Road | I122: Raj Doshi | J122: 381.85 | K122: 391 | L122: 141.467 | M122: 136 | N122: 414.22 | O122: 405 | P122: 154.226 | Q122: 133 | R122: 366.8 | S122: 393.044 | T122: 123 | U122: 139.611 | V122: 417 | W122: 425.891 | X122: 115 | Y122: 128.307 | Z122: 415.1 | AA122: 422.684 | AB122: 91.4 | AC122: 136.015 | AD122: 393 | AE122: 409.628 | AF122: 92 | AG122: 139.711 | AH122: 397 | AI122: 424.482 | AJ122: 92 | AK122: 157.317 | AL122: 375 | AM122: 367.195 | AN122: 86 | AO122: 107.452 | AP122: 370 | AQ122: 390.78 | AR122: 82 | AS122: 128.597 | AT122: 345.465 | AU122: 355.41 | AV122: 82.879 | AW122: 113.963 | AX122: 355.3 | AY122: 322.795 | AZ122: 85.401 | BA122: 118.18 | BB122: 393.18 | BC122: 372.839 | BD122: 93.568 | BE122: 139.688 | BF122: 28.55936 | BG122: 77.17101 | BH122: =BB122 -> 393.18 | BI122: =BC122 -> 372.839 | BJ122: =(BH122-BI122) -> 20.341 | BK122: =(BJ122)/BI122*100 -> 5.4557061 | BL122: =BD122 -> 93.568 | BM122: =BE122 -> 139.688 | BN122: =(BL122-BM122) -> -46.12 | BO122: =(BN122)/BM122*100 -> -33.016437 | BP122: =K122+O122+R122+V122+Z122+AD122+AH122+AL122+AP122+AT122+AX122+BB122 -> 4623.845 | BQ122: =J122+N122+S122+W122+AA122+AE122+AI122+AM122+AQ122+AU122+Table1[[#This Row],[MS-0225]]+Table1[[#This Row],[MS-0325]] -> 4680.818 | BR122: =(BP122-BQ122) -> -56.973 | BS122: =(BR122)/BQ122*100 -> -1.2171591 | BT122: =M122+Q122+T122+X122+AB122+AF122+AJ122+AN122+AR122+AV122+AZ122+BD122 -> 1212.248 | BU122: =L122+P122+U122+Y122+AC122+AG122+AK122+AO122+AS122+AW122+BA122+BE122 -> 1604.534 | BV122: =(BT122-BU122) -> -392.286 | BW122: =(BV122)/BU122*100 -> -24.448594 | BX122: 46.563 | BY122: =BX122/BH122 -> 0.11842667 | BZ122: 311.136 | CA122: =BZ122/BP122 -> 0.067289453 | CB122: =BH122/SUMIFS(BH$2:BH$398,G$2:G$398,G122) -> 0.33556944 | CC122: =BI122/SUMIFS(BI$2:BI$398,G$2:G$398,G122) -> 0.3345831 | CD122: =CB122-CC122 -> 0.00098633613 | CE122: =BL122/SUMIFS(BL$2:BL$398,G$2:G$398,G122) -> 0.27759384 | CF122: =BM122/SUMIFS(BM$2:BM$398,G$2:G$398,G122) -> 0.40118557 | CG122: =CE122-CF122 -> -0.12359173 | CH122: =BP122/SUMIFS(BP$2:BP$398,G$2:G$398,G122) -> 0.32999544 | CI122: =BQ122/SUMIFS(BQ$2:BQ$398,G$2:G$398,G122) -> 0.35075922 | CJ122: =CH122-CI122 -> -0.02076378 | CK122: =BT122/SUMIFS(BT$2:BT$398,G$2:G$398,G122) -> 0.3146042 | CL122: =BU122/SUMIFS(BU$2:BU$398,G$2:G$398,G122) -> 0.38709791 | CM122: =CK122-CL122 -> -0.072493712 | CN122: =COUNTIFS(G$2:G$398,G122)*CH122 -> 1.3199818 | CO122: =COUNTIFS(G$2:G$398,G122)*CK122 -> 1.2584168
A123: 41030511 | B123: HPC | C123: AJAY AHUJA FILLING STATION | D123: OKHLA | E123: SOUTH EAST DELHI | F123: White Patch_ Govind Puri to Okhla | G123: White Patch_ Govind Puri to Okhla | H123: Okhla | I123: Bhanu Pratap | J123: 335 | K123: 355 | L123: 370 | M123: 405 | N123: 390 | O123: 375 | P123: 442 | Q123: 403 | R123: 364 | S123: 360 | T123: 409 | U123: 420 | V123: 393 | W123: 395 | X123: 394 | Y123: 423.03 | Z123: 401 | AA123: 380 | AB123: 387 | AC123: 430 | AD123: 389 | AE123: 365 | AF123: 365 | AG123: 420 | AH123: 378 | AI123: 375 | AJ123: 385 | AK123: 445 | AL123: 363 | AM123: 355 | AN123: 358 | AO123: 385 | AP123: 372 | AQ123: 360 | AR123: 396 | AS123: 363 | AT123: 355 | AU123: 340 | AV123: 401 | AW123: 380 | AX123: 345 | AY123: 330 | AZ123: 364 | BA123: 370 | BB123: 390 | BC123: 350 | BD123: 355 | BE123: 375 | BF123: 28.52947 | BG123: 77.2728 | BH123: =BB123 -> 390 | BI123: =BC123 -> 350 | BJ123: =(BH123-BI123) -> 40 | BK123: =(BJ123)/BI123*100 -> 11.428571 | BL123: =BD123 -> 355 | BM123: =BE123 -> 375 | BN123: =(BL123-BM123) -> -20 | BO123: =(BN123)/BM123*100 -> -5.3333333 | BP123: =K123+O123+R123+V123+Z123+AD123+AH123+AL123+AP123+AT123+AX123+BB123 -> 4480 | BQ123: =J123+N123+S123+W123+AA123+AE123+AI123+AM123+AQ123+AU123+Table1[[#This Row],[MS-0225]]+Table1[[#This Row],[MS-0325]] -> 4335 | BR123: =(BP123-BQ123) -> 145 | BS123: =(BR123)/BQ123*100 -> 3.3448674 | BT123: =M123+Q123+T123+X123+AB123+AF123+AJ123+AN123+AR123+AV123+AZ123+BD123 -> 4622 | BU123: =L123+P123+U123+Y123+AC123+AG123+AK123+AO123+AS123+AW123+BA123+BE123 -> 4823.03 | BV123: =(BT123-BU123) -> -201.03 | BW123: =(BV123)/BU123*100 -> -4.1681267 | BX123: 0 | BY123: =BX123/BH123 -> 0 | BZ123: 0 | CA123: =BZ123/BP123 -> 0 | CB123: =BH123/SUMIFS(BH$2:BH$398,G$2:G$398,G123) -> 0.43454039 | CC123: =BI123/SUMIFS(BI$2:BI$398,G$2:G$398,G123) -> 0.40792541 | CD123: =CB123-CC123 -> 0.026614982 | CE123: =BL123/SUMIFS(BL$2:BL$398,G$2:G$398,G123) -> 0.71789687 | CF123: =BM123/SUMIFS(BM$2:BM$398,G$2:G$398,G123) -> 0.72254335 | CG123: =CE123-CF123 -> -0.0046464871 | CH123: =BP123/SUMIFS(BP$2:BP$398,G$2:G$398,G123) -> 0.40849822 | CI123: =BQ123/SUMIFS(BQ$2:BQ$398,G$2:G$398,G123) -> 0.40468633 | CJ123: =CH123-CI123 -> 0.0038118889 | CK123: =BT123/SUMIFS(BT$2:BT$398,G$2:G$398,G123) -> 0.70500305 | CL123: =BU123/SUMIFS(BU$2:BU$398,G$2:G$398,G123) -> 0.71813705 | CM123: =CK123-CL123 -> -0.013134004 | CN123: =COUNTIFS(G$2:G$398,G123)*CH123 -> 1.2254947 | CO123: =COUNTIFS(G$2:G$398,G123)*CK123 -> 2.1150092
A124: 112385 | B124: BPC | C124: ANAND SUPER SEVICE STN. | D124: MALKA GANJ DELHI | E124: CENTRAL DELHI | F124: ANAND SUPER | G124: ANAND SUPER | H124: Old Delhi | I124: Abhinav | J124: 400 | K124: 410 | L124: 60 | M124: 50 | N124: 430 | O124: 415 | P124: 70 | Q124: 65 | R124: 400 | S124: 420 | T124: 60 | U124: 100 | V124: 420 | W124: 405 | X124: 60 | Y124: 75 | Z124: 460 | AA124: 460 | AB124: 60 | AC124: 80 | AD124: 450 | AE124: 425 | AF124: 70 | AG124: 75 | AH124: 455 | AI124: 440 | AJ124: 85 | AK124: 80 | AL124: 410 | AM124: 410 | AN124: 50 | AO124: 50 | AP124: 395 | AQ124: 380 | AR124: 45 | AS124: 45 | AT124: 370 | AU124: 400 | AV124: 30 | AW124: 60 | AX124: 400 | AY124: 330 | AZ124: 40 | BA124: 50 | BB124: 390 | BC124: 405 | BD124: 70 | BE124: 55 | BF124: 28.67947 | BG124: 77.21204 | BH124: =BB124 -> 390 | BI124: =BC124 -> 405 | BJ124: =(BH124-BI124) -> -15 | BK124: =(BJ124)/BI124*100 -> -3.7037037 | BL124: =BD124 -> 70 | BM124: =BE124 -> 55 | BN124: =(BL124-BM124) -> 15 | BO124: =(BN124)/BM124*100 -> 27.272727 | BP124: =K124+O124+R124+V124+Z124+AD124+AH124+AL124+AP124+AT124+AX124+BB124 -> 4975 | BQ124: =J124+N124+S124+W124+AA124+AE124+AI124+AM124+AQ124+AU124+Table1[[#This Row],[MS-0225]]+Table1[[#This Row],[MS-0325]] -> 4905 | BR124: =(BP124-BQ124) -> 70 | BS124: =(BR124)/BQ124*100 -> 1.4271152 | BT124: =M124+Q124+T124+X124+AB124+AF124+AJ124+AN124+AR124+AV124+AZ124+BD124 -> 685 | BU124: =L124+P124+U124+Y124+AC124+AG124+AK124+AO124+AS124+AW124+BA124+BE124 -> 800 | BV124: =(BT124-BU124) -> -115 | BW124: =(BV124)/BU124*100 -> -14.375 | BX124: 25 | BY124: =BX124/BH124 -> 0.064102564 | BZ124: 85 | CA124: =BZ124/BP124 -> 0.017085427 | CB124: =BH124/SUMIFS(BH$2:BH$398,G$2:G$398,G124) -> 1 | CC124: =BI124/SUMIFS(BI$2:BI$398,G$2:G$398,G124) -> 1 | CD124: =CB124-CC124 -> 0 | CE124: =BL124/SUMIFS(BL$2:BL$398,G$2:G$398,G124) -> 1 | CF124: =BM124/SUMIFS(BM$2:BM$398,G$2:G$398,G124) -> 1 | CG124: =CE124-CF124 -> 0 | CH124: =BP124/SUMIFS(BP$2:BP$398,G$2:G$398,G124) -> 1 | CI124: =BQ124/SUMIFS(BQ$2:BQ$398,G$2:G$398,G124) -> 1 | CJ124: =CH124-CI124 -> 0 | CK124: =BT124/SUMIFS(BT$2:BT$398,G$2:G$398,G124) -> 1 | CL124: =BU124/SUMIFS(BU$2:BU$398,G$2:G$398,G124) -> 1 | CM124: =CK124-CL124 -> 0 | CN124: =COUNTIFS(G$2:G$398,G124)*CH124 -> 1 | CO124: =COUNTIFS(G$2:G$398,G124)*CK124 -> 1
A125: 106229 | B125: IOC | C125: AUTO ENGINEERS SERVICE CENTRE | D125: DEREWAL NAGAR MODEL TOWN | E125: NORTH DELHI | F125: White Patch_Model Town | G125: White Patch_Model Town | H125: Inner Ring Road | I125: Raj Doshi | J125: 373.5 | K125: 405 | L125: 94.5 | M125: 75 | N125: 378 | O125: 415 | P125: 90 | Q125: 85 | R125: 408 | S125: 423 | T125: 84 | U125: 81 | V125: 425 | W125: 400.5 | X125: 75 | Y125: 85.5 | Z125: 440 | AA125: 418.5 | AB125: 80 | AC125: 85.5 | AD125: 395 | AE125: 409.5 | AF125: 85 | AG125: 94.5 | AH125: 430 | AI125: 409.5 | AJ125: 70 | AK125: 94.5 | AL125: 390 | AM125: 409.5 | AN125: 70 | AO125: 58.5 | AP125: 370 | AQ125: 355.5 | AR125: 50 | AS125: 76.5 | AT125: 360 | AU125: 364.5 | AV125: 60 | AW125: 67.5 | AX125: 340 | AY125: 342.5 | AZ125: 60 | BA125: 71.5 | BB125: 390 | BC125: 385 | BD125: 70 | BE125: 75 | BF125: 28.7028 | BG125: 77.193 | BH125: =BB125 -> 390 | BI125: =BC125 -> 385 | BJ125: =(BH125-BI125) -> 5 | BK125: =(BJ125)/BI125*100 -> 1.2987013 | BL125: =BD125 -> 70 | BM125: =BE125 -> 75 | BN125: =(BL125-BM125) -> -5 | BO125: =(BN125)/BM125*100 -> -6.6666667 | BP125: =K125+O125+R125+V125+Z125+AD125+AH125+AL125+AP125+AT125+AX125+BB125 -> 4768 | BQ125: =J125+N125+S125+W125+AA125+AE125+AI125+AM125+AQ125+AU125+Table1[[#This Row],[MS-0225]]+Table1[[#This Row],[MS-0325]] -> 4669.5 | BR125: =(BP125-BQ125) -> 98.5 | BS125: =(BR125)/BQ125*100 -> 2.1094336 | BT125: =M125+Q125+T125+X125+AB125+AF125+AJ125+AN125+AR125+AV125+AZ125+BD125 -> 864 | BU125: =L125+P125+U125+Y125+AC125+AG125+AK125+AO125+AS125+AW125+BA125+BE125 -> 974.5 | BV125: =(BT125-BU125) -> -110.5 | BW125: =(BV125)/BU125*100 -> -11.339148 | BX125: 0 | BY125: =BX125/BH125 -> 0 | BZ125: 0 | CA125: =BZ125/BP125 -> 0 | CB125: =BH125/SUMIFS(BH$2:BH$398,G$2:G$398,G125) -> 0.29213483 | CC125: =BI125/SUMIFS(BI$2:BI$398,G$2:G$398,G125) -> 0.31136272 | CD125: =CB125-CC125 -> -0.019227886 | CE125: =BL125/SUMIFS(BL$2:BL$398,G$2:G$398,G125) -> 0.16990291 | CF125: =BM125/SUMIFS(BM$2:BM$398,G$2:G$398,G125) -> 0.19556714 | CG125: =CE125-CF125 -> -0.025664232 | CH125: =BP125/SUMIFS(BP$2:BP$398,G$2:G$398,G125) -> 0.29914047 | CI125: =BQ125/SUMIFS(BQ$2:BQ$398,G$2:G$398,G125) -> 0.30325367 | CJ125: =CH125-CI125 -> -0.0041131963 | CK125: =BT125/SUMIFS(BT$2:BT$398,G$2:G$398,G125) -> 0.17632653 | CL125: =BU125/SUMIFS(BU$2:BU$398,G$2:G$398,G125) -> 0.2056775 | CM125: =CK125-CL125 -> -0.02935097 | CN125: =COUNTIFS(G$2:G$398,G125)*CH125 -> 0.89742142 | CO125: =COUNTIFS(G$2:G$398,G125)*CK125 -> 0.52897959
